Workbook

Sheet 05C_Governance_Coding_RE
A1: company_id | B1: doc_id | C1: gov_crit_id | D1: doc_id_primary_evidence | E1: score_0_3 | F1: evidence_quote | G1: evidence_location | H1: why_not_higher | I1: coder_confidence | J1: notes
A2: 7 | B2: 37 | C2: GOV_01 | E2: 2 | F2: “centre of competence… ensures rapid knowledge and technology sharing across the company.” | G2: S.3 – Project AI (centre of competence) | H2: Rolle/Einheit und Aufgaben sichtbar; keine Review-/Reporting-Belege. | I2: mittel
A3: 7 | B3: 37 | C3: GOV_02 | E3: 1 | F3: “These will be continuously refined and adapted as required…” | G3: S.1 – continuously refined/adapted | H3: Nur Prozessabsicht; keine Prozessstufen/Trigger/Owner. | I3: mittel | M3: Keine Governance-Deltas.
A4: 7 | B4: 37 | C4: GOV_03 | E4: 2 | F4: “a portfolio tool… D³… portfolio currently spans 400 use cases.” | G4: S.3 – D³ portfolio tool | H4: Konkreter Check-/Inventory-Mechanismus, aber ohne Protokoll-/Output-Nachweis. | I4: mittel | M4: Alle sieben BMW-Governance-Codes und alle sieben Deutsche-Telekom-Governance-Codes stimmen im Re-Coding mit den Pilot-Scores überein.
A5: 7 | B5: 37 | C5: GOV_04 | E5: 0 | I5: hoch | J5: Nicht nachweisbar.
A6: 7 | B6: 37 | C6: GOV_05 | E6: 1 | F6: “increase awareness among its employees… sensitivity when working with AI technologies.” | G6: S.1 – increase awareness | H6: Awareness benannt, aber kein Trainingsprogramm/Pflichtgrad. | I6: niedrig
A7: 7 | B7: 37 | C7: GOV_06 | E7: 0 | I7: hoch | J7: Nicht nachweisbar.
A8: 7 | B8: 37 | C8: GOV_07 | E8: 1 | F8: “will identify, assess, report and mitigate risks…” | G8: S.3 – Accountability (“report… risks”) | H8: Reporting-Absicht ja, aber ohne Empfänger/Frequenz/KPI. | I8: mittel
A9: 15 | B9: 86 | C9: GOV_01 | E9: 2 | F9: “we clarify which initiative or product owner has which responsibilities.”; “Group Compliance Management” | G9: S.3 (product owner); p.12 (Group Compliance Management) | H9: Rollen/Verankerung benannt; Aufgaben grob (responsibilities). | I9: mittel
A10: 15 | B10: 86 | C10: GOV_02 | E10: 1 | F10: “developed and enhanced on grounds of deep analysis and evaluation.” | G10: S.8 – deep analysis/evaluation | H10: Prozessabsicht/Schritt erwähnt; Trigger/Owner nicht vollständig. | I10: mittel
A11: 15 | B11: 86 | C11: GOV_03 | E11: 2 | F11: “stop AI systems at any time (kill switch).”; “In case of inconsistencies, we rather stop the AI system”; “reset… in order to remove false or biased data.” | G11: S.9 (kill switch/stop/reset); p.8 (privacy & security by design) | H11: Konkrete Kontrolltools + „wann“ teils klar („any time“, „in case of inconsistencies“). | I11: mittel
A12: 15 | B12: 86 | C12: GOV_04 | E12: 1 | F12: “transparent, auditable, fair, and fully documented.” | G12: S.8 – “auditable” | H12: Audit/Assessment nur als Eigenschaft erwähnt; keine Audit-Mechanik. | I12: niedrig
A13: 15 | B13: 86 | C13: GOV_05 | E13: 1 | F13: “We will engage in AI and ethics education.” | G13: S.11 – AI and ethics education | H13: Education zugesagt, ohne Programm-/Pflichtdetails. | I13: mittel
A14: 15 | B14: 86 | C14: GOV_06 | I14: hoch | J14: Nicht nachweisbar.
A15: 15 | B15: 86 | C15: GOV_07 | I15: hoch | J15: Nicht nachweisbar.

Sheet 03c_Values_Coding_RE
A1: company_id | B1: doc_id | C1: value_id | D1: value_present | E1: binding_level | F1: binding_justification | G1: evidence_quote | H1: evidence_location | I1: coder_confidence | J1: notes | K1: value_points | N1: POST-HOC Vergleich: Re-Coding vs Pilot-Coding
A2: 7 | B2: 37 | C2: VAL_01 | D2: 1 | E2: 3 | F2: Human oversight inkl. Möglichkeit des menschlichen Overrules | G2: “implements appropriate human monitoring… and considers… humans can overrule algorithmic decisions.” | H2: S.2 – Human agency and oversight | I2: hoch | J2: Klarer Kontroll-/Override-Schritt; stärkste Evidenz im Dokument. | K2: =Tabelle5225[[#This Row],[value_present]]*Tabelle5225[[#This Row],[binding_level]] -> 3 | N2: company_id | O2: value_id | P2: pilot_value_present | Q2: recode_value_present | R2: pilot_binding_level | S2: recode_binding_level | T2: delta_type | U2: change_cause | V2: evidence_anchor_recode
A3: 7 | B3: 37 | C3: VAL_02 | D3: 1 | E3: 1 | F3: Risiken werden identifiziert/bewertet/berichtet/mitigiert | G3: “will identify, assess, report and mitigate risks…” | H3: S.3 – Accountability | I3: Hoch | J3: Verantwortungsprinzip explizit, aber ohne Rollen-/Mechanikanker im Wertesinn. | K3: =Tabelle5225[[#This Row],[value_present]]*Tabelle5225[[#This Row],[binding_level]] -> 1 | N3: 7 | O3: VAL_01 | P3: 1 | Q3: 1 | R3: 1 | S3: 3 | T3: binding | U3: Correction of inconsistent pilot coding | V3: doc 37, S.2 – human monitoring / overrule
A4: 7 | B4: 37 | C4: VAL_03 | D4: 1 | E4: 1 | F4: Transparenz über Einsatz der Technologien + Kommunikation | G4: “aims… open communication where respective technologies are used.” | H4: S.2 – Transparency | I4: Hoch | J4: Disclosure/Offenlegung des AI-Einsatzes. | K4: =Tabelle5225[[#This Row],[value_present]]*Tabelle5225[[#This Row],[binding_level]] -> 1 | N4: 7 | O4: VAL_14 | P4: 1 | Q4: 1 | R4: 1 | S4: 2 | T4: binding | U4: Rule change (expected) | V4: doc 37, S.2 – applicable safety standards
A5: 7 | B5: 37 | C5: VAL_04 | D5: 1 | E5: 1 | F5: Explainability als Ziel bei AI applications | G5: “aims for explainability of AI applications…” | H5: S.2 – Transparency | I5: hoch | J5: Explainability explizit, aber nur Prinzipienniveau. | K5: =Tabelle5225[[#This Row],[value_present]]*Tabelle5225[[#This Row],[binding_level]] -> 1 | N5: 7 | O5: VAL_15 | P5: 1 | Q5: 0 | R5: 1 | S5: — | T5: both | U5: Rule change (expected) | V5: kein eigenständiger ethischer Grenzsatz in doc 37
A6: 7 | B6: 37 | C6: VAL_05 | D6: 1 | E6: 1 | F6: Fairness über Human Dignity; Ziel „fair AI“ | G6: “respects human dignity… sets out to build fair AI applications.” | H6: S.2 – Diversity, non-discrimination and fairness | I6: hoch | J6: Fairness klar, ohne operativen Kontrollschritt. | K6: =Tabelle5225[[#This Row],[value_present]]*Tabelle5225[[#This Row],[binding_level]] -> 1 | N6: 15 | O6: VAL_01 | P6: 1 | Q6: 1 | R6: 2 | S6: 3 | T6: binding | U6: Correction of inconsistent pilot coding | V6: doc 86, S.9 – kill switch
A7: 7 | B7: 37 | C7: VAL_06 | D7: 1 | E7: 1 | F7: Privacy & data security auf AI storage/processing erweitert | G7: “extends its… data privacy and data security measures to cover storage and processing in AI applications.” | H7: S.2 – Privacy and data governance | I7: hoch | J7: KI-bezogener Datenschutz eindeutig. | K7: =Tabelle5225[[#This Row],[value_present]]*Tabelle5225[[#This Row],[binding_level]] -> 1 | N7: 15 | O7: VAL_05 | P7: 1 | Q7: 1 | R7: 1 | S7: 3 | T7: binding | U7: Correction of inconsistent pilot coding | V7: doc 86, S.9 – remove inappropriate data to avoid bias
A8: 7 | B8: 37 | C8: VAL_07 | D8: 1 | E8: 1 | F8: Data security measures im AI-Kontext | G8: “data… security measures… in AI applications.” | H8: S.2 – Privacy and data governance | I8: Hoch | J8: Security-Anker vorhanden, aber nicht weiter operationalisiert. | K8: =Tabelle5225[[#This Row],[value_present]]*Tabelle5225[[#This Row],[binding_level]] -> 1 | N8: 15 | O8: VAL_08 | P8: 1 | Q8: 1 | R8: 2 | S8: 3 | T8: binding | U8: Correction of inconsistent pilot coding | V8: doc 86, S.9 – stop AI system on inconsistencies
A9: 7 | B9: 37 | C9: VAL_08 | D9: 1 | E9: 1 | F9: Safety/Vermeidung unbeabsichtigter Folgen/Errors | G9: “decrease the risk of unintended consequences and errors.” | H9: S.2 – Technical robustness and safety | I9: Hoch | J9: Safety/Harm-Prevention klar, jedoch ohne Prozessschritt. | K9: =Tabelle5225[[#This Row],[value_present]]*Tabelle5225[[#This Row],[binding_level]] -> 1 | N9: 15 | O9: VAL_15 | P9: 1 | Q9: 0 | R9: 1 | S9: — | T9: both | U9: Rule change (expected) | V9: kein ethischer Grenzsatz, nur Responsible-AI-Rhetorik
A10: 7 | B10: 37 | C10: VAL_09 | D10: 1 | E10: 1 | F10: Robustheit/Safety-Standards zur Fehler-/Risiko-Reduktion | G10: “aims to develop robust AI applications and observes the applicable safety standards…” | H10: S.2 – Technical robustness and safety | I10: hoch | J10: Robustheit explizit, aber nicht test-/monitoringbezogen. | K10: =Tabelle5225[[#This Row],[value_present]]*Tabelle5225[[#This Row],[binding_level]] -> 1
A11: 7 | B11: 37 | C11: VAL_10 | D11: 0 | H11: — | I11: hoch | J11: Kein belastbarer Redress-/Contestability-Anker. | K11: =Tabelle5225[[#This Row],[value_present]]*Tabelle5225[[#This Row],[binding_level]] -> 0
A12: 7 | B12: 37 | C12: VAL_11 | D12: 0 | H12: — | I12: hoch | J12: Kein Accessibility-/Teilhabebeleg mit KI-Anker. | K12: =Tabelle5225[[#This Row],[value_present]]*Tabelle5225[[#This Row],[binding_level]] -> 0
A13: 7 | B13: 37 | C13: VAL_12 | D13: 1 | E13: 1 | F13: AI soll Umwelt-/Societal Well-being fördern (inkl. Klima/Umweltschutz) | G13: “goals… human rights and sustainability… climate change and environmental protection.” | H13: S.2 – Environmental and societal well-being | I13: hoch | J13: Umweltbezug explizit. | K13: =Tabelle5225[[#This Row],[value_present]]*Tabelle5225[[#This Row],[binding_level]] -> 1
A14: 7 | B14: 37 | C14: VAL_13 | D14: 1 | E14: 1 | F14: AI soll Well-being von Stakeholdern fördern | G14: “AI applications that promote the well-being of customers, employees and partners.” | H14: S.2 – Environmental and societal well-being | I14: hoch | J14: Konkreter Well-being-/Benefit-Anker. | K14: =Tabelle5225[[#This Row],[value_present]]*Tabelle5225[[#This Row],[binding_level]] -> 1
A15: 7 | B15: 37 | C15: VAL_14 | D15: 1 | E15: 2 | F15: „Applicable safety standards“ als Compliance-Anker (indirekt) | G15: “observes the applicable safety standards…” | H15: S.2 – Technical robustness and safety | I15: Mittel | J15: Standard-/Compliance-Bezug; deontisch stärker als bloßes Statement. | K15: =Tabelle5225[[#This Row],[value_present]]*Tabelle5225[[#This Row],[binding_level]] -> 2
A16: 7 | B16: 37 | C16: VAL_15 | D16: 0 | H16: — | I16: mittel | J16: Nur Ethik-/Responsible-AI-Rhetorik; keine eigenständige ethische Grenze. | K16: =Tabelle5225[[#This Row],[value_present]]*Tabelle5225[[#This Row],[binding_level]] -> 0
A17: 7 | B17: 37 | C17: VAL_16 | D17: 0 | H17: — | I17: hoch | J17: Kein konkreter Data-quality-/Dataset-governance-Anker. | K17: =Tabelle5225[[#This Row],[value_present]]*Tabelle5225[[#This Row],[binding_level]] -> 0
A18: 7 | B18: 37 | C18: VAL_17 | D18: 0 | H18: — | I18: hoch | J18: Kein belastbarer KI-spezifischer IP-/Confidentiality-Anker. | K18: =Tabelle5225[[#This Row],[value_present]]*Tabelle5225[[#This Row],[binding_level]] -> 0
A19: 7 | B19: 37 | C19: VAL_18 | D19: 1 | E19: 1 | F19: Bezug zu Human Rights-Zielen | G19: “aligns with the BMW Group’s goals in the areas of human rights…” | H19: S.2 – Environmental and societal well-being | I19: mittel | J19: Human-rights-Frame explizit genannt. | K19: =Tabelle5225[[#This Row],[value_present]]*Tabelle5225[[#This Row],[binding_level]] -> 1
A20: 15 | B20: 86 | C20: VAL_01 | D20: 1 | E20: 3 | F20: Agency/Choice im Kontext Daten/KI-Interaktion.;Kill switch als konkrete Kontrollmöglichkeit | G20: “they can choose the way of further processing their personal data.”; "stop AI systems at any time (kill switch).” | H20: S.6 (Choice); S.9 (kill switch) | I20: Hoch | J20: Klarer menschlicher Kontroll-/Interventionsschritt. | K20: =Tabelle5225[[#This Row],[value_present]]*Tabelle5225[[#This Row],[binding_level]] -> 3
A21: 15 | B21: 86 | C21: VAL_02 | D21: 1 | E21: 2 | F21: Accountability/Responsibility im KI-Kontext.; Product Owner/Initiative Owner Verantwortlichkeiten werden geklärt | G21: “The human always remains responsible.”; “we clarify which initiative or product owner has which responsibilities.” | H21: S.3 – 1. We are responsible. | I21: hoch | J21: Deutliches Verantwortungsprinzip; keine weitergehende Prozesskopplung. | K21: =Tabelle5225[[#This Row],[value_present]]*Tabelle5225[[#This Row],[binding_level]] -> 2
A22: 15 | B22: 86 | C22: VAL_03 | D22: 1 | E22: 2 | F22: Transparenz/Disclosure eindeutig. | G22: “In no case we hide it when the customer’s counterpart is an AI.” | H22: S.6 – 4. We are transparent. | I22: hoch | J22: Klare Disclosure-Regel. | K22: =Tabelle5225[[#This Row],[value_present]]*Tabelle5225[[#This Row],[binding_level]] -> 2
A23: 15 | B23: 86 | C23: VAL_04 | D23: 1 | E23: 1 | F23: Black-Box-Vermeidung als Designziel | G23: “prevent so called ‘Black Boxes’” | H23: S.8 – 6. We set the framework. | I23: Hoch | J23: Explainability-Anker vorhanden, aber nur auf Prinzipienniveau. | K23: =Tabelle5225[[#This Row],[value_present]]*Tabelle5225[[#This Row],[binding_level]] -> 1
A24: 15 | B24: 86 | C24: VAL_05 | D24: 1 | E24: 3 | F24: Fairness als Eigenschaft der AI-Lösungen genannt; Bias-Prävention durch Datenentfernung | G24: “transparent, auditable, fair, and fully documented.”; “we remove inappropriate data to avoid bias.” | H24: S.8 (fair); S.9 (avoid bias) | I24: Hoch | J24: Konkreter Anti-Bias-Kontrollschritt. | K24: =Tabelle5225[[#This Row],[value_present]]*Tabelle5225[[#This Row],[binding_level]] -> 3
A25: 15 | B25: 86 | C25: VAL_06 | D25: 1 | E25: 2 | F25: Keine Verarbeitung privacy-relevanter Daten ohne Rechtsgrundlage; Impact-Analysis-Paradigma: privacy & security by design | G25: “We never process privacy-relevant data without legal permission.”; “impact analysis is ‘privacy und security by design’.” | H25: S.7 (legal permission); S.8 (privacy by design) | I25: hoch | J25: Klare Privacy-Regel; stärkste Evidenz bleibt deontisch. | K25: =Tabelle5225[[#This Row],[value_present]]*Tabelle5225[[#This Row],[binding_level]] -> 2
A26: 15 | B26: 86 | C26: VAL_07 | D26: 1 | E26: 2 | F26: Security/Robustness als technische Anforderung an KI; Überblick über Datennutzung und Zugriffe als Security-Prinzip; Nutzung wird auf passende Use Cases begrenzt + Systeme gesichert | G26: “AI systems have to meet… technical requirements… such as security, robustness.”; “full overview of how customer related data is used and who has access”; “limit the usage to appropriate use cases and thoroughly secure our systems” | H26: S.4 (security/robustness); S.7 (access/secure) | I26: hoch | J26: Security-Regel mit konkreter Absicherungsrichtung. | K26: =Tabelle5225[[#This Row],[value_present]]*Tabelle5225[[#This Row],[binding_level]] -> 2
A27: 15 | B27: 86 | C27: VAL_08 | D27: 1 | E27: 3 | F27: Safety/Harm Prevention, deontisch „shall“.; Konkrete Kontrollregel (Stop-Kriterium). | G27: “In case of inconsistencies, we rather stop the AI system” | H27: S.8 (no harm); S.9 (stop on inconsistencies) | I27: Hoch | J27: Konkrete Harm-prevention-Stop-Regel. | K27: =Tabelle5225[[#This Row],[value_present]]*Tabelle5225[[#This Row],[binding_level]] -> 3
A28: 15 | B28: 86 | C28: VAL_09 | D28: 1 | E28: 2 | F28: Security/Robustness als technische Anforderung an KI; Konkrete Prüf-/Szenarioelemente. | G28: “AI systems have to meet… technical requirements… such as security, robustness.”; “full overview of how customer related data is used and who has access”; “limit the usage to appropriate use cases and thoroughly secure our systems”; “risks and chances scenarios or reliable disaster scenarios.” | H28: S.4 (robustness); S.8 (disaster scenarios) | I28: Hoch | J28: Robustheit explizit; kein Test-/Monitoringbeleg für 3. | K28: =Tabelle5225[[#This Row],[value_present]]*Tabelle5225[[#This Row],[binding_level]] -> 2
A29: 15 | B29: 86 | C29: VAL_10 | D29: 0 | I29: hoch | J29: Kein belastbarer Redress-/Complaint-Mechanismus. | K29: =Tabelle5225[[#This Row],[value_present]]*Tabelle5225[[#This Row],[binding_level]] -> 0
A30: 15 | B30: 86 | C30: VAL_11 | D30: 0 | I30: hoch | J30: Kein Inclusiveness-/Accessibility-Anker. | K30: =Tabelle5225[[#This Row],[value_present]]*Tabelle5225[[#This Row],[binding_level]] -> 0
A31: 15 | B31: 86 | C31: VAL_12 | D31: 0 | I31: hoch | J31: Kein Umwelt-/Green-AI-Anker im Short Doc. | K31: =Tabelle5225[[#This Row],[value_present]]*Tabelle5225[[#This Row],[binding_level]] -> 0
A32: 15 | B32: 86 | C32: VAL_13 | D32: 1 | E32: 1 | F32: Social benefit / well-being (kundenzentriert). | G32: “We enrich and simplify our customers’ lives.” | H32: S.5 – 3. We put our customers first. | I32: Hoch | J32: Konkreter Kundennutzen, aber ohne weitere Operationalisierung. | K32: =Tabelle5225[[#This Row],[value_present]]*Tabelle5225[[#This Row],[binding_level]] -> 1
A33: 15 | B33: 86 | C33: VAL_14 | D33: 1 | E33: 2 | F33: KI-Systeme müssen Regeln und Gesetzen untergeordnet sein; Keine Verarbeitung privacy-relevanter Daten ohne Rechtsgrundlage | G33: “We never process privacy-relevant data without legal permission.”; “AI systems have to meet… technical requirements… such as security, robustness.” | H33: S.4 (laws); S.7 (legal permission) | I33: hoch | J33: Deontische Compliance-Regel. | K33: =Tabelle5225[[#This Row],[value_present]]*Tabelle5225[[#This Row],[binding_level]] -> 2
A34: 15 | B34: 86 | C34: VAL_15 | D34: 0 | I34: hoch | J34: Nur Ethik-Rhetorik; keine explizite ethische Grenze/„do not“-Leitplanke. | K34: =Tabelle5225[[#This Row],[value_present]]*Tabelle5225[[#This Row],[binding_level]] -> 0
A35: 15 | B35: 86 | C35: VAL_16 | D35: 1 | E35: 3 | F35: Data quality/governance + fairness-bezogen.; Diverse/angemessene Dateninput-Verantwortung; Reset zur Entfernung falscher/biased Daten | G35: “we remove inappropriate data to avoid bias.”; “responsibility for a diverse and appropriate data input.”; “reset… in order to remove false or biased data.” | H35: S.9 – 7. We maintain control. | I35: mittel | J35: Konkreter Data-governance-/Data-quality-Kontrollschritt. | K35: =Tabelle5225[[#This Row],[value_present]]*Tabelle5225[[#This Row],[binding_level]] -> 3
A36: 15 | B36: 86 | C36: VAL_17 | D36: 0 | I36: hoch | J36: Kein KI-spezifischer IP-/Confidentiality-Anker. | K36: =Tabelle5225[[#This Row],[value_present]]*Tabelle5225[[#This Row],[binding_level]] -> 0
A37: 15 | B37: 86 | C37: VAL_18 | D37: 0 | I37: hoch | J37: Kein expliziter Human-rights-Frame im Sinne des Codebooks. | K37: =Tabelle5225[[#This Row],[value_present]]*Tabelle5225[[#This Row],[binding_level]] -> 0
K38: =Tabelle5225[[#This Row],[value_present]]*Tabelle5225[[#This Row],[binding_level]] -> 0
K39: =Tabelle5225[[#This Row],[value_present]]*Tabelle5225[[#This Row],[binding_level]] -> 0
K40: =Tabelle5225[[#This Row],[value_present]]*Tabelle5225[[#This Row],[binding_level]] -> 0
K41: =Tabelle5225[[#This Row],[value_present]]*Tabelle5225[[#This Row],[binding_level]] -> 0
K42: =Tabelle5225[[#This Row],[value_present]]*Tabelle5225[[#This Row],[binding_level]] -> 0
K43: =Tabelle5225[[#This Row],[value_present]]*Tabelle5225[[#This Row],[binding_level]] -> 0
K44: =Tabelle5225[[#This Row],[value_present]]*Tabelle5225[[#This Row],[binding_level]] -> 0
K45: =Tabelle5225[[#This Row],[value_present]]*Tabelle5225[[#This Row],[binding_level]] -> 0
K46: =Tabelle5225[[#This Row],[value_present]]*Tabelle5225[[#This Row],[binding_level]] -> 0
K47: =Tabelle5225[[#This Row],[value_present]]*Tabelle5225[[#This Row],[binding_level]] -> 0
K48: =Tabelle5225[[#This Row],[value_present]]*Tabelle5225[[#This Row],[binding_level]] -> 0
K49: =Tabelle5225[[#This Row],[value_present]]*Tabelle5225[[#This Row],[binding_level]] -> 0
... K464: =Tabelle5225[[#This Row],[value_present]]*Tabelle5225[[#This Row],[binding_level]] -> 0

Sheet 00_DAX_Master
A1: company_id | B1: company_name_official | C1: brand_short | D1: sector_cluster | E1: industry_detail | F1: hq_country | G1: dax_member_as_of_date | H1: Marktkapitalisierung in Mio. € (Stand: 04.01.2026) | I1: notes_sampling
A2: 1 | B2: Adidas | C2: ADS | D2: Consumer | E2: Sportartikel | F2: Bayern | G2: 22. Juni 1998 | H2: 28070.86 | I2: Trotz intensiver Recherche auf offiziellen Konzernquellen und in Berichten gibt es keine öffentlich zugängliche KI‑Ethik‑ oder Responsible‑AI‑Policy von adidas
A3: 2 | B3: Airbus | C3: AIR | D3: Industrie | E3: Luftfahrt, Raumfahrt, Rüstung | F3: Niederlande | G3: 20. Sep. 2021 | H3: 146046.49 | I3: Keine öffentlichen, dedizierten „Responsible AI Policies“ im Sinne eines separaten Dokuments gefunden; die wichtigsten Aussagen sind in der Human‑rights‑Seite und im Digital‑Ethics‑Kapitel des Verhaltenskodex integriert.
A4: 3 | B4: Allianz | C4: ALV | D4: Finance | E4: Versicherungen | F4: Bayern | G4: 1. Juli 1988 | H4: 138065.08 | I4: Keine dedizierten öffentlichen „Allianz Standard for Responsible AI“‑Dokumente gefunden; der Standard wird nur intern erwähnt.
A5: 4 | B5: BASF | C5: BAS | D5: Materials/Chemicals | E5: Chemie | F5: Rheinland-Pfalz | G5: 1. Juli 1988 | H5: 36934 | I5: Es wurde keine öffentlich zugängliche, eigenständige „Data & AI Policy“ von BASF gefunden. Hinweise auf eine interne Data‑&‑AI‑Policy erscheinen im Responsible‑AI‑Text, sind aber nicht öffentlich abrufbar.
A6: 5 | B6: Bayer | C6: BAYN | D6: Materials/Chemicals | E6: Chemie, Pharma | F6: Nordrhein-Westfalen | G6: 1. Juli 1988 | H6: 33814.35 | I6: Mehrere relevante Dokumente gefunden.
A7: 6 | B7: Beiersdorf | C7: BEI | D7: Consumer | E7: Konsumgüter (Produktion) | F7: Hamburg | G7: 20. Juni 2022 | H7: 19043.54 | I7: Die einzige explizite AI‑Policy‑Aussage stammt aus dem Annual Report 2024. Die Code‑of‑Conduct‑Dokumente und die Human‑Rights‑Policy enthalten relevante Leitplanken zu digitaler Verantwortung, Daten‑ und Menschenrechtsschutz, aber keine spezifischen KI‑Prinzipien
A8: 7 | B8: BMW | C8: BMW | D8: Industrie | E8: Automobil (Produktion) | F8: Bayern | G8: 1. Juli 1988 | H8: 52864.52 | I8: Mehrere relevante Dokumente gefunden.
A9: 8 | B9: Brenntag | C9: BNR | D9: Materials/Chemicals | E9: Chemie (Handel) | F9: Nordrhein-Westfalen | G9: 20. Sep. 2021 | H9: 6654.82 | I9: Es konnten keine spezifischen öffentlichen KI‑Leitlinien oder Responsible‑AI‑Policies von Brenntag SE gefunden werden
A10: 9 | B10: Commerzbank | C10: CBK | D10: Finance | E10: Banken | F10: Hessen | G10: 27. Feb. 2023 | H10: 37853.56 | I10: Die zentrale AI-Quelle ist das Dokument „KI-Grundsätze im Commerzbank-Konzern“
A11: 10 | B11: Continental | C11: CON | D11: Industrie | E11: Automobil (Zulieferer) | F11: Niedersachsen | G11: 24. Sep. 2012 | H11: 12640.94 | I11: Mehrere semi-relevante Dokumente gefunden.
A12: 11 | B12: Daimler Truck | C12: DTG | D12: Industrie | E12: Nutzfahrzeuge (Produktion) | F12: Baden-Württemberg | G12: 21. März 2022 | H12: 25660.46 | I12: Keine eigenständigen, konzernweiten „Responsible AI Policy“ oder „AI Principles“ separat vom Code of Conduct/Integrity Code identifiziert
A13: 12 | B13: Deutsche Bank | C13: DBK | D13: Finance | E13: Banken | F13: Hessen | G13: 1. Juli 1988 | H13: 57682.6 | I13: Die konkretesten AI-Prinzipien lagen öffentlich am klarsten im Supplier Code of Conduct (AI & Data Ethics Principles) sowie Governance-Hinweise (z. B. „AI Oversight Forum“) in ESG/IR-Reports vor; darüber hinaus keine weiteren belastbaren Policy-Dokumente.
... A41: 40 | B41: Zalando | C41: ZAL | D41: Consumer | E41: Versandhandel (Mode) | F41: Berlin | G41: 20. Sep. 2021 | H41: 6113.98 | I41: relevante Inhalte zu KI-/Algorithmus-Werten und Governance sind über CDR-Report, Code of Ethics, ESG- und D&I-Dokumente sowie Tech-Blog-Artikel verteilt.

Sheet 01_Document_Log
A1: doc_id | B1: company_id | C1: doc_title | D1: doc_type | E1: publisher | F1: publication_date | G1: version | H1: language | I1: url | J1: access_date | K1: file_name_local | L1: inclusion_status | M1: exclusion_reason | N1: relevance_notes | O1: Inkludiert in Pilot?
A2: 1 | B2: 1 | C2: Fair Play Code of Conduct | D2: Code of Conduct | E2: adidas AG | F2: n.n. | G2: n.n. | H2: EN | I2: https://www.adidas-group.com/en/investors/corporate-governance/adidas-fair-play-code-of-conduct | J2: 16.02.2026 | K2: 001_01_FairPlayCode_1602026.pdf | L2: Nicht inkudiert | M2: Keine KI Relevanz | N2: Stellt umfassend die ethischen Erwartungen an alle adidas‑Mitarbeitenden dar (Antikorruption, Datenschutz, Verhalten), enthält Governance‑Mechanismen wie Schulungen und Berichtswege. Trotz fehlendem KI‑Bezug ist es das stärkste normative Dokument.
A3: 2 | B3: 1 | C3: Compliance Policy | D3: Code of Conduct | E3: adidas AG | F3: n.n. | G3: n.n. | H3: EN | I3: https://www.adidas-group.com/en/investors/corporate-governance/adidas-fair-play-code-of-conduct | J3: 16.02.2026 | K3: 002_01_compliance_policy_160226.pdf | L3: Nicht inkudiert | M3: Keine KI Relevanz | N3: Erläutert konkret die Regeln zu Bestechung, Geschenken, Betrug, Wettbewerbsrecht und Interessenkonflikten sowie die Pflichten und Verfahren bei Verstößen. Wichtiges Governance‑Rahmenwerk, obwohl keine KI‑Themen adressiert werden.
A4: 3 | B4: 1 | C4: Human Rights Policy | D4: Other | E4: adidas AG | F4: 01.02.2024 | G4: n.n. | H4: EN | I4: https://www.adidas-group.com/en/sustainability/transparency/policies | J4: 16.02.2026 | K4: 003_01_Human_Rights_Policy_160226.pdf | L4: Nicht inkudiert | M4: Keine KI Relevanz | N4: Verankert adidas’ Verpflichtung zu internationalen Menschenrechtsstandards und beschreibt Due‑Diligence‑Prozesse zur Identifizierung und Vermeidung negativer Auswirkungen. Relevante Werte wie Fairness, Gleichheit und Schutz vulnerabler Gruppen können später als Kontext für KI‑Ethik dienen.
A5: 4 | B5: 1 | C5: ETHICAL COMMUNICATION GUIDELINES | D5: Code of Conduct | E5: Adidas Foundation | F5: n.n. | G5: n.n. | H5: EN | I5: https://www.adidasfoundation.org/about/policies-and-guidelines | J5: 16.02.2026 | K5: 004_01_Ethical_comms_guide_160226.pdf | L5: Nicht inkudiert | M5: Keine KI Relevanz
A6: 5 | B6: 1 | C6: Safeguarding Policy | D6: Code of Conduct | E6: Adidas Foundation | F6: n.n. | G6: n.n. | H6: EN | I6: https://www.adidasfoundation.org/about/policies-and-guidelines | J6: 16.02.2026 | K6: 005_SafeguardingPolicy_160226.pdf | L6: Nicht inkudiert | M6: Keine KI Relevanz
A7: 6 | B7: 1 | C7: Supervisory Board Report 2024 | D7: Annual Report | E7: Adidas Group | F7: 01.03.2025 | G7: n.n. | H7: EN | I7: https://report.adidas-group.com/2024/en/to-our-shareholders/supervisory-board-report.html | J7: 16.02.2026 | K7: 006_01_Supervisory_Report_2024_160226.pdf | L7: Nicht inkudiert | M7: Keine KI Relevanz
A8: 7 | B8: 1 | C8: Integrated Management System Global Policy | D8: Sustainability Report | E8: Adidas AG | F8: 01.01.2026 | G8: n.n. | H8: EN | I8: https://www.adidas-group.com/de/nachhaltigkeit/transparenz/richtlinien?tag=Eigene+Standorte | J8: 16.02.2026 | K8: 007_01_IMSGP_160226.pdf | L8: Nicht inkudiert | M8: Keine KI Relevanz
B9: 1 | D9: AI Principles | E9: Adidas AG | L9: Nicht gefunden | N9: No public AI/Responsible AI guideline, policy or principles found (as of 2026‑02‑16)
B10: 1 | D10: AI Policy | E10: Adidas AG | L10: Nicht gefunden | N10: No public AI/Responsible AI guideline, policy or principles found (as of 2026‑02‑16)
B11: 1 | D11: Responsible AI / Ethics | E11: Adidas AG | L11: Nicht gefunden | N11: No public AI/Responsible AI guideline, policy or principles found (as of 2026‑02‑16)
A12: 8 | B12: 2 | C12: Our approach to Artificial Intelligence (AI) | D12: AI Policy | E12: Airbus SE | F12: n.n. | G12: n.n. | H12: EN | I12: https://www.airbus.com/en/sustainability-draft/our-approach-to-sustainability/human-rights | J12: 16.02.2026 | K12: 008_02_AI_Approach_160226 | L12: Inkludiert
A13: 9 | B13: 2 | C13: Airbus Code of Conduct – 2025 Edition | D13: Code of Conduct | E13: Airbus SE | F13: n.n. | G13: n.n. | H13: EN | I13: https://www.airbus.com/sites/g/files/jlcbta136/files/2025-04/2025-Airbus-Code-of-Conduct-EN.pdf | J13: 16.02.2026 | K13: 009_02_Code-of-Conduct_160226.pdf | L13: Inkludiert
A14: 10 | B14: 2 | C14: Airbus Supplier Code of Conduct | D14: Code of Conduct | E14: Airbus SE | F14: n.n. | G14: n.n. | H14: EN | I14: https://www.airbus.com/sites/g/files/jlcbta136/files/2021-07/Airbus-Supplier-Code-of-Conduct.pdf | J14: 16.02.2026 | K14: 010_02_Supplier-Code-of-Conduct_160226.pdf | L14: Nicht inkudiert | M14: Keine KI Relevanz
A15: 11 | B15: 2 | C15: Airbus Ethics & Compliance Anti‑Corruption Policy | D15: Other | E15: Airbus SE | F15: n.n. | G15: n.n. | H15: EN | I15: https://www.airbus.com/sites/g/files/jlcbta136/files/2021-10/Airbus-Ethics-and-Compliance-Anti-Corruption-Policy.pdf | J15: 16.02.2026 | K15: 011_02_Ethics-and-Compliance-Anti-Corruption-Policy_160226.pdf | L15: Nicht inkudiert | M15: Keine KI Relevanz
A16: 12 | B16: 2 | C16: Pioneering sustainable aerospace (Sustainability publication 2025) | D16: Sustainability Report | E16: Airbus SE | F16: 2025 | G16: n.n. | H16: EN | I16: https://www.airbus.com/sites/g/files/jlcbta136/files/2025-04/2025_Airbus_Pioneering_sustainable_aerospace_publication.pdf | J16: 16.02.2026 | K16: 012_02_Pioneering_sustainable_aerospace_publication_160226.pdf | L16: Nicht inkudiert | M16: Keine KI Relevanz
A17: 13 | B17: 2 | C17: Airbus Summit 2025 – Harnessing the power of responsible AI | D17: Press Release | E17: Airbus SE | F17: 25.03.2025 | G17: n.n. | H17: EN | I17: https://www.airbus.com/en/airbus-summit-2025/harnessing-the-power-of-responsible-ai | J17: 16.02.2026 | K17: 013_02_Harnessing the power of responsible AI _160226pdf | L17: Nicht inkudiert | M17: PR ohne normative Substanz
A18: 14 | B18: 2 | C18: Information Notice of the 2025 Annual General Meeting | D18: Annual Report | E18: Airbus SE | F18: 15.04.2025 | G18: n.n. | I18: https://www.airbus.com/sites/g/files/jlcbta136/files/2025-03/information_notice.pdf | J18: 16.02.2026 | K18: 014_02_Annual_General_Meeting_2025_160226.pdf | L18: Nicht inkudiert | M18: Keine KI Relevanz
A19: 15 | B19: 2 | C19: Artificial Intelligence | D19: Website Page | E19: Airbus SE | F19: n.n. | G19: n.n. | H19: EN | I19: https://www.airbus.com/en/innovation/digital-transformation/artificial-intelligence | J19: 16.02.2026 | K19: 015_02_AI_Website_160226 | L19: Nicht inkudiert | M19: PR ohne normative Substanz | N19: Kein Bezug zur KI Ethikrichtlinien; beschreibt nur technischen/ wirtschaftlichen Einsatz von KI
B20: 2 | D20: AI Principles | E20: Airbus SE | L20: Nicht gefunden | N20: No public AI/Responsible AI guideline or principles found (as of 2026‑02‑16)
B21: 2 | D21: Responsible AI / Ethics | E21: Airbus SE | L21: Nicht gefunden | N21: No public AI/Responsible AI guideline or principles found (as of 2026‑02‑16)
A22: 16 | B22: 3 | C22: Responsible Use of Artificial Intelligence (AI) | D22: Responsible AI / Ethics | E22: Allianz SE | F22: n.n. | G22: n.n. | H22: EN | I22: https://www.allianz.com/en/about-us/strategy-values/responsible-use-of-artificial-intelligence.html | J22: 16.02.2026 | K22: 016_03_Responsible Use of Artificial Intelligence_160226.pdf | L22: Inkludiert | O22: X
A23: 17 | B23: 3 | C23: Allianz Code of Conduct | D23: Code of Conduct | E23: Allianz SE | F23: 2025 | G23: n.n. | H23: EN | I23: https://www.allianz.com/content/dam/onemarketing/azcom/Allianz_com/about-us/strategy-values/compliance/code-of-conduct/code-of-conduct-accessible.pdf | J23: 16.02.2026 | K23: 017_03_code-of-conduct_160226.pdf | L23: Inkludiert | O23: X
A24: 18 | B24: 3 | C24: Privacy Statement – Data Ethics section | D24: Other | E24: Allianz SE | F24: 2025 | G24: n.n. | H24: EN | I24: https://www.allianz.com/en/privacy-statement.html | J24: 16.02.2026 | K24: 018_03_Privacy Statement_160226.pdf | L24: Inkludiert
A25: 19 | B25: 3 | C25: Allianz Privacy Standard – Public Version | D25: Other | E25: Allianz SE | F25: 43221 | G25: 1.0 | H25: EN | I25: https://www.allianzgloballife.com/content/dam/onemarketing/azgl/allianzgloballife/doc/31122019/en_gb/Allianz-Privacy-Standard_PUBLIC_EN.pdf | J25: 16.02.2026 | K25: 019_03_Privacy-Standard_PUBLIC_EN_160226.pdf | L25: Nicht inkudiert | M25: Duplikat / Veraltete Version
A26: 20 | B26: 3 | C26: Allianz Group Sustainability Report 2023 – Data ethics/AI governance sections | D26: Sustainability Report | E26: Allianz SE | F26: 2023 | G26: n.n. | H26: EN | I26: https://www.allianz.com/content/dam/onemarketing/azcom/Allianz_com/sustainability/documents/Allianz_Group_Sustainability_Report_2023-web.pdf | J26: 16.02.2026 | K26: 020_03_Sustainability_Report_2023_160226.pdf | L26: Nicht inkudiert | M26: Duplikat / Veraltete Version
A27: 21 | B27: 3 | C27: Responsible AI: a sustainable approach to transformative technology | D27: Responsible AI / Ethics | E27: Allianz Global Investors (subsidiary) | F27: n.n. | G27: n.n. | H27: EN | I27: https://www.allianzgi.com/documents/Responsible-AI-a-sustainable-approach-to-transformative-technology | J27: 16.02.2026 | K27: 021_03_Responsible_AI_160226.pdf | L27: Inkludiert | N27: Tochtergesellschaft der Allianz SE
B28: 3 | D28: AI Principles | E28: Allianz SE | L28: Nicht gefunden | N28: No public AI policy or principles found (as of 2026‑02‑16)
B29: 3 | D29: AI Policy | E29: Allianz SE | L29: Nicht gefunden | N29: No public AI policy or principles found (as of 2026‑02‑16)
A30: 22 | B30: 4 | C30: Responsible AI at BASF | D30: Responsible AI / Ethics | E30: BASF SE | F30: n.n. | G30: n.n. | H30: EN | I30: https://www.basf.com/global/en/who-we-are/digitalization/artificial-intelligence/Responsible-AI-at-BASF | J30: 16.02.2026 | K30: 022_04_Responsible_AI_160226.pdf | L30: Inkludiert | O30: X
A31: 23 | B31: 4 | C31: BASF Code of Conduct | D31: Code of Conduct | E31: BASF SE | F31: n.n. | G31: n.n. | H31: EN | I31: https://www.basf.com/dam/jcr:0304db1d-bcbb-3015-a965-62627c1b61d2/basf/www/global/documents/en/investor-relations/calendar-and-publications/reports/2025/BASF_Code-of-Conduct.pdf | J31: 16.02.2026 | K31: 023_04_Code-of-Conduct_160226.pdf | L31: Inkludiert | O31: X
A32: 24 | B32: 4 | C32: Data protection @ BASF – Data processing in the BASF Group | D32: Other | E32: BASF SE | F32: n.n. | G32: n.n. | H32: EN | I32: https://www.basf.com/global/en/legal/data-protection-at-basf | J32: 16.02.2026 | K32: 024_04_Data protection_160226.pdf | L32: Inkludiert
A33: 25 | B33: 4 | C33: BASF Group’s Policy Statement on Human Rights | D33: Other | E33: BASF SE | F33: n.n. | G33: n.n. | H33: EN | I33: https://www.basf.com/dam/jcr:4944a24f-defc-4987-9dd6-d38dba24efd9/basf/www/global/documents/en/sustainability/we-value-people-and-treat-them-with-respect/human-rights/Human-Rights-Policy-Statement-BASF-Group.pdf | J33: 16.02.2026 | K33: 025_04_Human-Rights-Policy-Statement_160226.pdf | L33: Nicht inkudiert | M33: Keine KI Relevanz
A34: 26 | B34: 4 | C34: Supplier Code of Conduct (Version 2024) | D34: Code of Conduct | E34: BASF SE | F34: 45474 | G34: n.n. | H34: EN | I34: https://www.basf.com/dam/jcr:83c0af8a-4e46-37c0-945f-3fd15ff4fca3/basf/www/global/documents/en/about-us/suppliers-and-partners/supplier-code-of-conduct/Supplier_Code_of_conduct_Version%202024%20-%20English.pdf | J34: 16.02.2026 | K34: 025_04_Supplier_Code_of_conduct_160226.pdf | L34: Nicht inkudiert | M34: Keine KI Relevanz
B35: 4 | D35: AI Principles | E35: BASF SE | L35: Nicht gefunden | N35: No public AI policy or principles found (as of 2026‑02‑16)
B36: 4 | D36: AI Policy | E36: BASF SE | L36: Nicht gefunden | N36: No public AI policy or principles found (as of 2026‑02‑16)
A37: 27 | B37: 5 | C37: Bioethical Principles – AI in the context of human healthcare | D37: AI Principles | E37: Bayer AG | F37: n.n. | G37: n.n. | H37: EN | I37: https://www.bayer.com/en/sustainability/bioethical-principles | J37: 16.02.2026 | K37: 027_05_Bioethical Principles_160226.pdf | L37: Inkludiert | O37: X
A38: 28 | B38: 5 | C38: Generative Artificial Intelligence (GenAI) Guidance and Rules – version 3 | D38: AI Policy | E38: Bayer AG | F38: 17.10.2024 | G38: V3 | H38: EN | I38: https://idnet.bayer.com/sites/idnet/files/final-en-genai-guidelines-and-rules-v3.pdf | J38: 16.02.2026 | K38: 028_05_genai-guidelines_160226.pdf | L38: Inkludiert | O38: X
A39: 29 | B39: 5 | C39: Our Code of Conduct – Responsible use of Artificial Intelligence section | D39: Code of Conduct | E39: Bayer AG | F39: n.n. | G39: n.n. | H39: EN | I39: https://www.bayer.com/en/commitments/code-of-conduct | J39: 16.02.2026 | K39: 029_05_Code of Conduct_160226.pdf | L39: Inkludiert | O39: X
A40: 30 | B40: 5 | C40: Unleashing the Potential of AI – AI Ethics and Responsibility section | D40: Responsible AI / Ethics | E40: Bayer AG | F40: n.n. | G40: n.n. | H40: EN | I40: https://www.bayer.com/en/innovation/unleashing-the-potential-of-ai | J40: 16.02.2026 | K40: 030_05_Unleashing the Potential of AI_160226.pdf | L40: Inkludiert
A41: 31 | B41: 5 | C41: Bioethics Council: Responsible innovation with ethical AI | D41: Other | E41: Bayer AG | F41: 45261 | G41: n.n. | H41: EN | I41: https://www.bayer.com/sites/default/files/interview-bioethics-council-meeting-ethics-of-generative-ai-2023.pdf | J41: 16.02.2026 | K41: 31_05_interview-bioethics-council-meeting_160226.pdf | L41: Inkludiert | N41: Interview
A42: 32 | B42: 6 | C42: Beiersdorf Code of Conduct 2024 | D42: Code of Conduct | E42: Beiersdorf AG | F42: 2024 | G42: n.n. | H42: EN | I42: https://www.beiersdorf.com/-/media/Beiersdorf/landingpages/code-of-conduct/Beiersdorf-Code-of-Conduct-2024-EN.pdf | J42: 16.02.2026 | K42: 032_06_Code-of-Conduct_160226.pdf | L42: Nicht inkudiert | M42: Keine KI Relevanz | N42: Update: 2. März 26: doch kein KI-Bezug & nun exkludiert | O42: X
A43: 33 | B43: 6 | C43: Declaration of Principles on Upholding Human Rights | D43: ESG/CSR Report | E43: Beiersdorf AG | F43: 2023 | G43: n.n. | H43: EN | I43: https://www.beiersdorf.com/-/media/Beiersdorf/stories/news-and-stories/news/BW_Declaration_of_Principles_on_Upholding_Human_Rights.pdf | J43: 16.02.2026 | K43: 033_06_Declaration of Principles on Upholding Human Rights_160226.pdf | L43: Nicht inkudiert | M43: Keine KI Relevanz
A44: 34 | B44: 6 | C44: Beiersdorf Annual Report 2024 (Combined Management Report – digitalisation and AI section) | D44: Annual Report | E44: Beiersdorf AG | F44: 2024 | G44: n.n. | H44: EN | I44: https://www.beiersdorf.com/~/media/Beiersdorf/investors/financial-publication/2025/annual-report/Beiersdorf-Annual-Report-2024.pdf | J44: 16.02.2026 | K44: 034_06_Annual-Report-2024_160226.pdf | L44: Inkludiert | O44: X
A46: 36 | B46: 6 | C46: Beiersdorf driving AI innovations – interview with Dirk Ploss (Hamburg News) | D46: Other | E46: Beiersdorf AG | F46: 12.02.2025 | G46: n.n. | H46: EN | I46: https://hamburg-business.com/en/news/beiersdorf-driving-ai-innovations | J46: 16.02.2026 | K46: 036_06_Hamburg Business_120626.pdf | L46: Inkludiert | N46: Interview
B47: 6 | D47: AI Principles | E47: Beiersdorf AG | L47: Nicht gefunden | N47: No public AI/Responsible AI guideline, policy or principles found (as of 2026‑02‑16)
B48: 6 | D48: AI Policy | E48: Beiersdorf AG | L48: Nicht gefunden | N48: No public AI/Responsible AI guideline, policy or principles found (as of 2026‑02‑16)
B49: 6 | D49: Responsible AI / Ethics | E49: Beiersdorf AG | L49: Nicht gefunden | N49: No public AI/Responsible AI guideline, policy or principles found (as of 2026‑02‑16)
A50: 37 | B50: 7 | C50: BMW Group code of ethics for artificial intelligence | D50: AI Principles | E50: BMW Group | F50: 12.10.2020 | G50: n.n. | H50: EN | I50: https://www.press.bmwgroup.com/global/article/detail/T0318411EN/seven-principles-for-ai:-bmw-group-sets-out-code-of-ethics-for-the-use-of-artificial-intelligence?language=en | J50: 16.02.2026 | K50: 037_07_Code_of_ethics_for_AI_160226.PDF | L50: Inkludiert | O50: X
A51: 38 | B51: 7 | C51: BMW Group digital identity: Five guiding principles for dealing with digital technology | D51: Responsible AI / Ethics | E51: BMW Group | F51: Juni 2024 | G51: n.n. | H51: EN | I51: https://www.bmwgroup.com/content/dam/grpw/websites/bmwgroup_com/innovation/downloadds/en/2024/Digitales_Selbstverstaendnis_EN.pdf | J51: 16.02.2026 | K51: 038_07_Digitales_Selbstverstaendnis_160226.pdf | L51: Inkludiert | O51: X
A52: 39 | B52: 7 | C52: We Are Compliance – BMW Group Code of Conduct (2025 edition) | D52: Code of Conduct | E52: BMW Group | F52: Dezember 2025 | G52: n.n. | H52: EN | I52: https://www.bmwgroup.com/content/dam/grpw/websites/bmwgroup_com/company/downloads/en/2025/BMW_Group_Compliance_Code_of_Conduct_EN.pdf | J52: 16.02.2026 | K52: 039_07_Compliance_Code_of_Conduct_160226.pdf | L52: Nicht inkudiert | M52: Keine KI Relevanz
A53: 40 | B53: 7 | C53: BMW Group Report 2024 – Sustainability Statement (selected sections) | D53: Code of Conduct | E53: BMW Group | F53: Dezember 2025 | G53: n.n. | H53: EN | I53: https://www.bmwgroup-werke.com/content/dam/grpw/websites/bmwgroup_com/company/downloads/en/2025/BMW_Group_Compliance_HumanRights_Code_EN.pdf | J53: 16.02.2026 | K53: 040_07_Compliance_HumanRights_Code_160226.pdf | L53: Nicht inkudiert | M53: Keine KI Relevanz
A54: 41 | B54: 7 | C54: BMW Group Code on Human Rights and Working Conditions (2025) | D54: ESG/CSR Report | E54: BMW Group | F54: n.n. | G54: n.n. | H54: EN | I54: https://www.bmwgroup.com/en/report/2024/downloads/BMW-Group-Report-2024-en.pdf | J54: 16.02.2026 | K54: 041_07_ESG-Report-2024_160226.pdf | L54: Nicht inkudiert | M54: Keine KI Relevanz
B55: 7 | D55: AI Policy | E55: BMW Group | L55: Nicht gefunden | N55: No public AI policy found (as of 2026‑02‑16)
A56: 42 | B56: 8 | C56: Code of Business Conduct and Ethics | D56: Code of Conduct | E56: Brenntag SE | F56: 2024 | G56: n.n. | H56: EN | I56: https://brenntagprod-media.e-spirit.cloud/06432017-be1f-41ce-8d1d-564e2a66d213/documents/global/compliance/brenntag_code-of-conduct_en.pdf | J56: 17.02.2026 | K56: 042_08_code-of-conduct_170226.pdf | L56: Nicht inkudiert | M56: Keine KI Relevanz | N56: Obwohl keine KI‑spezifischen Prinzipien erwähnt werden, legt der Verhaltenskodex den ethischen Rahmen und die organisatorischen Mechanismen (Compliance‑Management, Trainings, Whistleblowing) fest, die auch für KI‑Governance relevant sind.
A57: 43 | B57: 8 | C57: Supplier Code of Conduct | D57: Code of Conduct | E57: Brenntag SE | F57: 2023 | G57: n.n. | H57: EN | I57: https://brenntagprod-media.e-spirit.cloud/06432017-be1f-41ce-8d1d-564e2a66d213/documents/global/compliance/global_brenntag-supplier-code-of-conduct-2023_en.pdf | J57: 17.02.2026 | K57: 043_08_supplier-code-of-conduct_170226.pdf | L57: Nicht inkudiert | M57: Keine KI Relevanz | N57: Die Richtlinie ist zwar nicht KI‑spezifisch, bildet aber einen wichtigen Governance‑Baustein für verantwortungsvolle Beschaffung und könnte im Kontext von Datenlieferanten und KI‑Systemen relevant sein.
A58: 44 | B58: 8 | C58: Group Sustainability Statement (FY 2024) | D58: Sustainability Report | E58: Brenntag SE | F58: n.n. | G58: n.n. | H58: EN | I58: https://brenntagprod-media.e-spirit.cloud/06432017-be1f-41ce-8d1d-564e2a66d213/documents/corporate/investor-relations/2024/annual-report-2024/brenntag_ar2024_group-sustainability-statement_en.pdf | J58: 17.02.2026 | K58: 044_08_sustainability-statement_170226.pdf | L58: Nicht inkudiert | M58: Keine KI Relevanz | N58: Obwohl keine expliziten AI‑Richtlinien vorhanden sind, liefert der Bericht Kontext zu Compliance, Datenschutz und Business‑Conduct‑Strategien, die als Umfeld für KI‑Regeln dienen können.
A59: 45 | B59: 8 | C59: Press Release: “Brenntag implements autonomous AI agents on its Salesforce platform as first customer in Germany” | D59: Press Release | E59: Brenntag SE | F59: 05.11.2024 | G59: n.n. | H59: EN | I59: https://corporate.brenntag.com/en/media/news/brenntag-implements-autonomous-ai-agents-on-its-salesforce-platform-as-first-customer-in-germany.html | J59: 17.02.2026 | K59: 045_08_Salesforce_Brenntag_170226.pdf | L59: Nicht inkudiert | M59: PR ohne normative Substanz
B60: 8 | D60: AI Principles | E60: Brenntag SE | L60: Nicht gefunden | N60: No public AI/Responsible AI guideline, policy or principles found (as of 2026‑02‑17)
B61: 8 | D61: AI Policy | E61: Brenntag SE | L61: Nicht gefunden | N61: No public AI/Responsible AI guideline, policy or principles found (as of 2026‑02‑17)
B62: 8 | D62: Responsible AI / Ethics | E62: Brenntag SE | L62: Nicht gefunden | N62: No public AI/Responsible AI guideline, policy or principles found (as of 2026‑02‑17)
A63: 46 | B63: 9 | C63: „KI‑Grundsätze im Commerzbank‑Konzern“ (Artificial Intelligence Principles) | D63: AI Principles | E63: Commerzbank AG | F63: 19.10.2023 | G63: n.n | H63: DE/EN | I63: https://www.commerzbank.de/group/what-moves-us/2024-article-media/24-03/ki-grundsaetze.pdf | J63: 17.02.2026 | K63: 046_09_ki-grundsaetze_170226.pdf | L63: Inkludiert | N63: Also includes Responsible AI / Ethics
A64: 47 | B64: 9 | C64: Artikel „AI principles – principle agreement will strengthen trust in AI“ | D64: Press Release | E64: Commerzbank AG | F64: 08.05.2025 | G64: n.n. | H64: DE/EN | I64: https://www.commerzbank.de/group/what-drives-us/innovation-digital-transformation/2024-ai-principles.html | J64: 17.02.2026 | K64: 047_09_Principle agreement_170226.pdf | L64: Nicht inkudiert | M64: PR ohne normative Substanz
A65: 48 | B65: 9 | C65: Whitepaper „Risk‑based approach to AI and Machine Learning“ | D65: AI Policy | E65: Commerzbank AG | F65: 15.03.2023 | G65: n.n | H65: DE/EN | I65: https://www.commerzbank.de/group/newsroom/publications/2023/position-paper-ai-act.pdf | J65: 17.02.2026 | K65: 048_09_whitepaper-ai-act_170226.pdf | L65: Inkludiert
A66: 49 | B66: 9 | C66: Code of Conduct („Yellow Compass“) – Version 2024 | D66: Code of Conduct | E66: Commerzbank AG | F66: 2024 | G66: V2024 | H66: DE/EN | I66: https://core-p-001.sitecorecontenthub.cloud/api/public/content/8008521917234a78a40d4f10b91c2806?v=c4b71f08 | J66: 17.02.2026 | K66: 049_09_Code of Conduct_170226.pdf | L66: Nicht inkudiert | M66: Keine KI Relevanz
A67: 50 | B67: 9 | C67: ESG Framework – Acting responsibly, growing sustainably | D67: ESG/CSR Report | E67: Commerzbank AG | F67: n.n. | G67: n.n. | H67: EN | I67: https://www.commerzbank.de/ms/documents/en/esg-framework-pdf.pdf | J67: 17.02.2026 | K67: 050_09_esg-framework_170226.pdf | L67: Nicht inkudiert | M67: Keine KI Relevanz
A68: 51 | B68: 10 | C68: Ethics regulations for artificial intelligence (press release) | D68: Press Release | E68: Continental AG | F68: 08.06.2020 | G68: n.n. | H68: EN | I68: https://www.continental.com/en/press/press-releases/ai-code-of-ethics/ | J68: 17.02.2026 | K68: 051_10_Ethics Regulations for Artificial Intelligence_170226.pdf | L68: Nicht inkudiert | M68: PR ohne normative Substanz
A69: 52 | B69: 10 | C69: Continental Code of Conduct | D69: Code of Conduct | E69: Continental AG | F69: 46023 | G69: Version 01/01/2026 | H69: EN | I69: https://cdn.continental.com/fileadmin/__imported/sites/corporate/_international/english/hubpages/60_20company/20_20corporate_20governance/50_20compliance/coc_en.pdf | J69: 17.02.2026 | K69: 052_10_coc_170226.pdf | L69: Inkludiert
A70: 53 | B70: 10 | C70: Continental Business Partner Code of Conduct | D70: Code of Conduct | E70: Continental AG | F70: n.n. | G70: Veersion Juli 2023 | H70: EN | I70: https://cdn.continental.com/fileadmin/__imported/sites/corporate/_international/german/hubpages/60_20unternehmen/20_20corporate_20governance/50_20compliance/brochure_bpcoc_en_with_signature.pdf | J70: 17.02.2026 | K70: 053_10_bpcoc_170226.pdf | L70: Inkludiert | N70: Hat eine kleine AI Sektion
A71: 54 | B71: 10 | C71: Survey: Germans fear job losses due to artificial intelligence (press release) | D71: Press Release | E71: Continental AG | F71: 28.03.2023 | G71: n.n. | H71: EN | I71: https://www.continental.com/en/press/press-releases/germans-fear-job-losses-due-to-artificial-intelligence/ | J71: 17.02.2026 | K71: 054_10_Survey_170226.pdf | L71: Nicht inkudiert | M71: PR ohne normative Substanz
A72: 55 | B72: 10 | C72: Turn Change Into Opportunity – Embrace Sustainability: Integrated Sustainability Report 2022 | D72: Sustainability Report | E72: Continental AG | F72: 2022 | G72: n.n. | H72: EN | I72: https://www.continental.com/fileadmin/__imported/sites/corporate/_international/german/hubpages/10_20presse/studien_und_publikationen/continental_sustainability_report_2022.pdf | J72: 17.02.2026 | K72: 055_10_sustainability_report_170226.pdf | L72: Nicht inkudiert | M72: Duplikat / Veraltete Version | N72: Referenzieren nur die AI Code of Ethics, aber geben selbst keine Inhalte über die Themen des CoE hinaus wieder: › Compliance with laws, regulations, Continental’s rules, standards and instructions › Workplace and fair working conditions › Health, safety, the environment, and product integrity › Employee diversity, anti-discrimination, fairness in the use of AI › Data protection and cybersecurity when using AI › Confidential information, intellectual property
B73: 10 | D73: AI Principles | E73: Continental AG | L73: Nicht gefunden | N73: No public AI/Responsible AI guideline, policy or principles found (as of 2026‑02‑17)
B74: 10 | D74: AI Policy | E74: Continental AG | L74: Nicht gefunden | N74: No public AI/Responsible AI guideline, policy or principles found (as of 2026‑02‑17)
B75: 10 | D75: Responsible AI / Ethics | E75: Continental AG | L75: Nicht gefunden | N75: No public AI/Responsible AI guideline, policy or principles found (as of 2026‑02‑17)
A76: 56 | B76: 11 | C76: Daimler Truck Code of Conduct – Guideline to doing the right thing | D76: Code of Conduct | E76: Daimler Truck Holding AG | F76: n.n. | G76: n.n. | H76: EN | I76: https://www.daimlertruck.com/fileadmin/user_upload/documents/company/compliance/Daimler-Truck-Code-of-Conduct-english.pdf | J76: 17.02.2026 | K76: 056_11_Code-of-Conduct_170226.pdf | L76: Inkludiert | N76: Dieses zentrale Compliance‑Dokument enthält ein eigenes Kapitel zu künstlicher Intelligenz. Es verpflichtet alle Beschäftigten zur verantwortungsvollen Nutzung von AI und formuliert konkrete Prinzipien wie Erklärbarkeit, Datenschutz, Sicherheit, Fairness und den Schutz von Beschäftigtenrechten. Die breite Verbindlichkeit und klare Verpflichtungen machen dieses Dokument zur wichtigsten Quelle
A77: 57 | B77: 11 | C77: Our Integrity Code (IC 0.2) | D77: AI Principles | E77: Daimler Truck Holding AG | F77: 1.4.2022 | G77: n.n. | H77: EN | I77: https://dtsa.daimlertruck.com/assets/files/king_vi/Our%20Integrity%20Code_1%20April%202022.pdf | J77: 17.02.2026 | K77: 057_11_Our Integrity Code_170226.pdf | L77: Inkludiert | N77: Der Integritätskodex gilt konzernweit und erläutert in Abschnitt 3.5.3 „Artificial intelligence“ die AI‑Grundsätze. Er betont die Umsetzung „fordernder AI‑Prinzipien“ für verantwortungsvolle Entwicklung und Nutzung von AI, einschliesslich Erklärbarkeit, Datenschutz, Sicherheit und Verlässlichkeit
A78: 58 | B78: 11 | C78: Declaration of Principles on Social Responsibility and Human Rights at Daimler Truck | D78: Other | E78: Daimler Truck Holding AG | F78: 44866 | G78: n.n. | H78: EN | I78: https://www.daimlertruck.com/fileadmin/user_upload/documents/sustainability/social/2022_12_07_Broschuere_Grundsatzerklaerung-Menschenrechte-EN.pdf | J78: 17.02.2026 | K78: 058_11_Grundsatzerklaerung-Menschenrechte_170226.pdf | L78: Nicht inkudiert | M78: Duplikat / Veraltete Version
A79: 59 | B79: 11 | C79: Business Partner Standards – Doing the Right Thing Together | D79: Code of Conduct | E79: Daimler Truck Holding AG | F79: n.n. | G79: n.n. | H79: EN | I79: https://www.daimlertruck.com/fileadmin/user_upload/dokumente/unternehmen/compliance/Business_Partner_Standards.pdf | J79: 17.02.2026 | K79: 059_11_Business_Partner_Standards_170226.pdf | L79: Nicht inkudiert | M79: Keine KI Relevanz
A80: 60 | B80: 11 | C80: Data Compliance Management System – Our commitment to data responsibility | D80: Other | E80: Daimler Truck Holding AG | F80: n.n. | G80: n.n. | H80: EN | I80: https://www.daimlertruck.com/en/company/compliance/data-compliance | J80: 17.02.2026 | K80: 060_11_Data Compliance Management System _170226.pdf | L80: Nicht inkudiert | M80: Keine KI Relevanz
A81: 61 | B81: 11 | C81: Daimler Truck Sustainability Report 2021 – Selected sections (automated driving & AI) | D81: ESG/CSR Report | E81: Daimler Truck Holding AG | F81: n.n. | G81: 2024 | H81: EN | I81: https://www.daimlertruck.com/en/sustainability/reportings | J81: 17.02.2026 | K81: 061_11_annual report-incl-esg_170226.pdf | L81: Nicht inkudiert | M81: Keine KI Relevanz
B82: 11 | D82: AI Policy | E82: Daimler Truck Holding AG | L82: Nicht gefunden | N82: No public AI policy or ethics found (as of 2026‑02‑17)
B83: 11 | D83: Responsible AI / Ethics | E83: Daimler Truck Holding AG | L83: Nicht gefunden | N83: No public AI policy or ethics found (as of 2026‑02‑17)
A84: 62 | B84: 12 | C84: Deutsche Bank Group Supplier Code of Conduct | D84: Code of Conduct | E84: Deutsche Bank AG | F84: 45778 | G84: n.n. | H84: EN | I84: https://vendor-portal.db.com/Files/Documents1/SupplierCodeofConductMay2025.pdf | J84: 17.02.2026 | K84: 062_12_SupplierCodeofConduct_170226.pdf | L84: Inkludiert | N84: Includes Responsible AI / AI Principles | O84: X
A85: 63 | B85: 12 | C85: Deutsche Bank Code of Conduct – Our duty for a long‑term success | D85: Code of Conduct | E85: Deutsche Bank AG | F85: n.n. | G85: n.n. | H85: EN | I85: https://investor-relations.db.com/files/documents/documents/code-of-business-conduct-and-ethics-for-deutsche-bank-group.pdf?language_id=1 | J85: 17.02.2026 | K85: 063_12_code-of-business-conduct-and-ethics-_170226.pdf | L85: Nicht inkudiert | M85: Keine KI Relevanz
A86: 64 | B86: 12 | C86: Non‑Financial Report 2023 (Deutsche Bank Group) | D86: ESG/CSR Report | E86: Deutsche Bank AG | F86: 2023 | G86: n.n. | H86: EN | I86: https://investor-relations.db.com/files/documents/annual-reports/2024/Non-Financial-Report-2023.pdf | J86: 17.02.2026 | K86: 064_12_Non-Financial-Report_170226.pdf | L86: Inkludiert | N86: Short Section on AI Oversight Forum
A87: 65 | B87: 12 | C87: Statement on Human Rights | D87: ESG/CSR Report | E87: Deutsche Bank AG | F87: n.n. | G87: n.n. | H87: EN | I87: https://www.db.com/what-we-do/responsibility/sustainability/documents/2025-06-june/DB-Statement-on-Human-Rights-EN.pdf | J87: 17.02.2026 | K87: 065_12_Statement-on-Human-Rights_170226.pdf | L87: Nicht inkudiert | M87: Keine KI Relevanz
A88: 66 | B88: 12 | C88: Artificial Intelligence: seizing opportunities and recognizing risks | D88: Website Page | E88: Deutsche Bank AG | F88: n.n. | G88: n.n. | H88: EN | I88: https://security.db.com/knowledge-bases/artificial-intelligence | J88: 17.02.2026 | K88: 066_12_Artificial Intelligence Overview_170226.pdf | L88: Nicht inkudiert | M88: Zu Vage (keine Kriterien, Regeln) | N88: Nur technische Erklärung, was KI eigentlich ist
A89: 67 | B89: 12 | C89: How Artificial Intelligence is changing banking | D89: Website Page | E89: Deutsche Bank AG | F89: n.n. | G89: n.n. | H89: EN | I89: https://www.db.com/what-next/digital-disruption/better-than-humans/how-artificial-intelligence-is-changing-banking/index?language_id=1 | J89: 17.02.2026 | K89: 067_12_How Artificial Intelligence is changing banking_170226.pdf | L89: Nicht inkudiert | M89: Zu Vage (keine Kriterien, Regeln) | N89: Kein Bezug zur Ethik oÄ
A90: 68 | B90: 12 | C90: The responsible use of AI in financial services – From principles to practice (News article) | E90: Deutsche Bank AG | F90: 12.11.2029 | G90: n.n. | H90: EN | I90: https://www.db.com/news/detail/20191112-the-responsible-use-of-ai-in-financial-services-from-principles-to-practice?language_id=1 | J90: 17.02.2026 | K90: 068_12_The responsible use of AI in Financial services_170226.pdf | L90: Nicht inkudiert | M90: Zu Vage (keine Kriterien, Regeln)
A91: 69 | B91: 12 | C91: Unleashing the potential of AI in securities services | D91: AI Policy | E91: Deutsche Bank AG | F91: 44348 | G91: n.n. | H91: EN | I91: https://flow.db.com/files/documents/more/publications/white-papers-guides/Unleashing-the-potential-of-AI-in-securities-services.pdf | J91: 17.02.2026 | K91: 069_12_Unleashing-the-potential-of-AI-in-securities-services_170226.pdf | L91: Inkludiert | O91: X
A92: 70 | B92: 12 | C92: Adopting generative AI in banking (white paper with Kodex AI) | D92: AI Policy | E92: Deutsche Bank AG | F92: n.n. | G92: n.n. | H92: EN | I92: https://flow.db.com/files/documents/more/publications/white-papers-guides/whitepaper-Adopting-Generative-AI-in-Banking.pdf | J92: 17.02.2026 | K92: 070_12_whitepaper-Adopting-Generative-AI-in-Banking_170226.pdf | L92: Inkludiert
A93: 71 | B93: 13 | C93: Response to European Commission’s White Paper on artificial intelligence | D93: Other | E93: Deutsche Börse Group | F93: 43983 | G93: n.n. | H93: EN | I93: https://www.deutsche-boerse.com/resource/blob/2095828/1649f1a7f54a924a0fb99f1b9bdd1694/data/20200610-db-response_en.pdf | J93: 17.02.2026 | K93: 071_13_db-response_170226.pdf | L93: Nicht inkudiert | M93: Duplikat / Veraltete Version
A94: 72 | B94: 13 | C94: Response to IOSCO consultation on AI in capital markets | D94: Other | E94: Deutsche Börse Group | F94: 10.04.2025 | G94: n.n. | H94: EN | I94: https://www.deutsche-boerse.com/resource/blob/4300280/dc0bd81c97cf978b924e43234f56f03d/data/20240426_DBG_response_IOSCO_AI_consultation.pdf | J94: 17.02.2026 | K94: 072_13_DBG_response_IOSCO Consultation_170226.pdf | L94: Nicht inkudiert
A95: 73 | B95: 13 | C95: Targeted consultation on artificial intelligence in the financial sector – contribution by Deutsche Börse Group | D95: Other | E95: Deutsche Börse Group | F95: 13.09.2024 | G95: n.n. | H95: EN | I95: https://www.deutsche-boerse.com/resource/blob/4344538/c7fb1c04440815b6ea29f17d9d7d62f1/data/20240912_DBG_response_EC%20Targeted%20consultation%20on%20artificial%20intelligence%20in%20the%20financial%20sector.pdf | J95: 17.02.2026 | K95: 073_13_DBG_response_EC_170226.pdf | L95: Inkludiert | N95: Die Deutsche Börse beschreibt ihren Ansatz, AI graduell und in getesteten Proof‑of‑Concept‑Phasen einzuführen, um Transparenz, Stabilität und Anlegerschutz zu gewährleisten. Sie benennt konkrete Risiken (Bias, Black‑Box‑Eigenschaften, Halluzinationen) und betont die Bedeutung solider Daten‑Governance und eines eigenen AI‑Governance‑Rahmens. Diese Aussagen liefern Hinweise für verantwortungsvolle KI‑Einführung, auch wenn das Dokument keine formale Policy darstellt.
A96: 74 | B96: 13 | C96: Market Data Policy Guidelines and FAQ – Section 10: Use of DBAG information in AI solutions (Version 2_8) | D96: Other | E96: Deutsche Börse Group | F96: 24.09.2025 | G96: V2.8 | H96: EN | I96: https://www.mds.deutsche-boerse.com/resource/blob/4028410/ee46a8181b463a0f413d0faa695c0001/data/Market%20Data%20Policy%20Guidelines%20and%20FAQ_V2_7.pdf | J96: 17.02.2026 | K96: 074_13_Market Data Policy Guidelines_170226.pdf | L96: Inkludiert | N96: ieses Regelwerk ist das einzige formale Dokument der Deutsche‑Börse‑Gruppe, das den Einsatz von KI explizit adressiert. Abschnitt 10 definiert, was als „AI Solution“ gilt (z. B. Deep‑Learning‑Modelle, generative KI und LLMs) und verpflichtet Kunden, eine passende Non‑Display‑Data‑Usage‑Lizenz zu erwerben und robuste interne Kontrollsysteme zur Nachverfolgung der Datennutzung über alle Nutzungsebenen hinweg zu unterhalten
A97: 75 | B97: 13 | C97: Code of Business Conduct | D97: Code of Conduct | E97: Deutsche Börse Group | F97: n.n. | G97: n.n. | H97: EN | I97: https://www.deutsche-boerse.com/resource/blob/45222/a244f5d7ff9f341689489b58f65a1dc0/data/code-of-business-conduct_en.pdf | J97: 17.02.2026 | K97: 075_13_code-of-business-conduct_170226.pdf | L97: Nicht inkudiert | M97: Keine KI Relevanz
A98: 76 | B98: 13 | C98: Code of Conduct for Suppliers | D98: Code of Conduct | E98: Deutsche Börse Group | F98: 12.11.2025 | G98: n.n. | H98: EN | I98: https://www.deutsche-boerse.com/resource/blob/160140/f940243aedc8611ac81e5c012777c7bd/data/code-of-coduct-suppliers_en.pdf | J98: 17.02.2026 | K98: 076_13_code-of-coduct-suppliers_170226.pdf | L98: Nicht inkudiert | M98: Keine KI Relevanz
A99: 77 | B99: 13 | C99: Human Rights Strategy Policy Statement | D99: ESG/CSR Report | E99: Deutsche Börse Group | F99: 09.12.2025 | G99: n.n. | H99: EN | I99: https://www.deutsche-boerse.com/resource/blob/3800562/9f347e74f9934e23edda9ecb28c85bc7/data/dbg-menschenrechtserklaerung_en.pdf | J99: 17.02.2026 | K99: 077_13_dbg-menschenrechtserklaerung_170226.pdf | L99: Nicht inkudiert | M99: Keine KI Relevanz
A100: 78 | B100: 13 | C100: Digital Finance – Deutsche Börse Group | D100: Website Page | E100: Deutsche Börse Group | F100: n.n. | G100: n.n. | H100: DE | I100: https://www.deutsche-boerse.com/dbg-de/ueber-uns/regulierung/regulation-df | J100: 17.02.2026 | K100: 078_13_Digital Finance_170226.pdf | L100: Nicht inkudiert | M100: Keine KI Relevanz
A101: 79 | B101: 13 | C101: Press release: More than two-thirds of investment managers use AI | D101: Press Release | E101: Deutsche Börse Group | F101: 19.01.2026 | G101: n.n. | H101: EN | I101: https://www.deutsche-boerse.com/dbg-en/media/news-stories/press-releases/More-than-Two-thirds-of-Investment-Managers-Prominently-Using-AI-to-Support-Front-Office-SimCorp-Study-Reveals-4910704 | J101: 17.02.2026 | K101: 079_13_SimCorp Study_170226.pdf | L101: Nicht inkudiert | M101: PR ohne normative Substanz
...

Sheet 02_Values_Codebook
A1: value_id | B1: value_name | C1: definition_short | D1: include_rules | E1: exclude_rules | F1: synonyms_terms | G1: example_phrases | H1: notes_boundary_cases
A2: VAL_01 | B2: Human Agency & Oversight | C2: Menschen behalten Kontrolle/Überwachung über KI | D2: Wenn menschliche Kontrolle/Override/Review explizit gefordert | E2: Reine Floskel „human-centered“ ohne Mechanik | F2: human oversight; human-in-the-loop; human control; override; review | G2: human review; override; escalation to humans | H2: Unterscheide Wert vs Governance-Kriterium 'Eskalationswege'
A3: VAL_02 | B3: Accountability & Responsibility | C3: Zuständigkeit/Verantwortung für KI-Entscheidungen/Outcomes | D3: Wenn Verantwortliche Rollen/Verantwortungsprinzip genannt | E3: Reines „we take responsibility“ ohne Bezug zu KI | F3: responsibility; accountability; ownership; governance | G3: clear accountability; responsible for AI | H3: Kann mit GOV_01 (Zuständigkeiten) kollidieren – hier nur als Wert codieren
A4: VAL_03 | B4: Transparency | C4: Nachvollziehbarkeit über Einsatz/Zweck/Entscheidungslogik | D4: Wenn Transparenzpflichten oder Offenlegung zu KI erwähnt | E4: Transparenz nur im Sinne von „Kommunikation“ ohne KI-Bezug | F4: transparency; disclosure; openness | G4: transparent use of AI; disclose AI involvement | H4: VAL_03 codieren, wenn Offenlegung, Identifizierbarkeit oder der Einsatz von KI gemeint ist (z. B. disclose AI involvement, AI system identifiable). Nicht als VAL_04 codieren, solange keine Erklärung/Interpretierbarkeit von Output, Modell oder Entscheidungslogik gefordert wird.
A5: VAL_04 | B5: Explainability | C5: Erklärbarkeit von KI-Entscheidungen/Outputs | D5: Wenn Erklärbarkeit, Interpretierbarkeit oder Verständlichkeit von KI-Output oder Entscheidungslogik gefordert wird; dazu zählen auch Formulierungen wie "comprehensible decision-making processes" oder die Vermeidung von "black boxes", sofern sie auf Verstehbarkeit/Erklärung und nicht nur auf Offenlegung zielen. | E5: „transparent“ ohne Erklärkomponente | F5: explainability; interpretability; explanation | G5: provide explanations; explain model outputs | H5: Technisch vs kommunikativ – beide zählen
A6: VAL_05 | B6: Fairness & Non-Discrimination | C6: Vermeidung unfairer Benachteiligung/Bias | D6: Wenn Bias/Benachteiligung/Anti-Diskriminierung bei KI genannt | E6: Allgemeine Diversity-Statements ohne KI-Bezug | F6: fairness; bias mitigation; non-discrimination; equity | G6: avoid bias; non-discriminatory outcomes | H6: Achtung: Legal Compliance ist VAL_14, nicht hier
A7: VAL_06 | B7: Privacy & Data Protection | C7: Schutz personenbezogener Daten/Datensparsamkeit | D7: Wenn Datenschutz bei KI/Training/Use erwähnt | E7: Datenschutz rein allgemein ohne KI-Kontext | F7: privacy; data protection; GDPR; data minimization | G7: privacy by design; data minimization | H7: Kann auch als Governance (Tools/Checks) auftauchen – hier Wert
A8: VAL_07 | B8: Security & Cybersecurity | C8: Schutz vor Angriffen/Manipulation/Leakage | D8: Wenn Security für KI-Systeme oder Daten betont | E8: Allgemeine IT-Security ohne KI-Kontext (Grenzfall) | F8: security; cybersecurity; adversarial; secure-by-design | G8: protect against attacks; secure systems | H8: Grenzfall: Wenn nur IT allgemein -> evtl. nicht codieren
A9: VAL_08 | B9: Safety & Harm Prevention | C9: Vermeidung von Schäden (physisch, psychisch, sozial) | D9: Wenn Risiko/Schadensvermeidung durch KI erwähnt | E9: Nur „safe“ als Marketingwort | F9: safety; harm prevention; risk reduction | G9: avoid harm; safe AI | H9: VAL_08 zusätzlich zu VAL_09 codieren, wenn Schäden, unbeabsichtigte Folgen, Missbrauch oder Safety explizit benannt sind. Reine Robustheits-/Zuverlässigkeitsrhetorik ohne Harm-/Safety-Anker bleibt nur VAL_09.
A10: VAL_09 | B10: Technical Robustness & Reliability | C10: Zuverlässigkeit, Stabilität, Fehlerresistenz | D10: Wenn Robustheit, Zuverlässigkeit, Genauigkeit, Testing oder Monitoring ausdrücklich auf das Erreichen intendierter Ergebnisse, Fehlerresistenz oder stabile Funktion von KI zielen. Bloßes Monitoring/Feedback ohne Bezug zu Output-Qualität oder intended outcome reicht nicht. | E10: Reine Qualitätsfloskel ohne Bezug | F10: robustness; reliability; resilience; testing | G10: robust and reliable; tested systems | H10: Kann in GOV_03 (Tools/Checks) konkret werden
A11: VAL_10 | B11: Contestability & Redress | C11: Anfechtbarkeit, Beschwerde, Wiedergutmachung | D11: Wenn Betroffene Einspruch/Review/Redress bei KI-Entscheidungen haben | E11: Reine Customer-Service Aussagen ohne KI | F11: appeal; contest; redress; complaint | G11: right to contest; grievance mechanism | H11: Stark verwandt mit GOV_06 (Eskalation) – hier Wert
A12: VAL_11 | B12: Inclusiveness & Accessibility | C12: Einbezug/Barrierefreiheit/Teilhabe | D12: Wenn KI inklusiv/zugänglich gestaltet werden soll | E12: Allgemeine DEI-/HR-Aussagen ohne KI-Bezug ausschließen. Ebenfalls ausschließen: "inclusion in data sets", repräsentative Daten oder Bias-Minderung ohne Bezug zu Accessibility, Teilhabe oder inklusivem Design; diese Fälle primär unter VAL_05 und/oder VAL_16 prüfen. | F12: accessibility; inclusiveness; participation | G12: inclusive design; accessible AI | H12: Wenn nur HR-DEI -> eher raus
... A19: VAL_18 | B19: Human Rights | C19: Menschenrechte als Rahmen (UNGP etc.) | D19: Wenn Menschenrechte, dignity, UDHR/UNGP oder einzelne Rechte ausdrücklich als Menschenrechtsrahmen für KI genannt werden; Privacy zählt zusätzlich als VAL_18 nur dann, wenn sie explizit als human right oder im Human-Rights-Framework verankert wird. | E19: Allgemeine Werte ohne Human-Rights-Bezug | F19: human rights; dignity; UNGP | G19: respect human rights; protect dignity | H19: Nicht jedes Doc wird das haben – ok

Sheet 03c_Values_Coding_PILOT
A1: company_id | B1: doc_id | C1: value_id | D1: value_present | E1: binding_level | F1: binding_justification | G1: evidence_quote | H1: evidence_location | I1: coder_confidence | J1: notes | K1: value_points
A2: 3 | B2: 16 | C2: VAL_01 | D2: 1 | E2: 2 | F2: KI-Nutzung muss Kundenautonomie respektieren, Risikobasierte menschliche Kontrolle wird zugesichert | G2: “Each usage of AI systems must respect customers’ autonomy and decision-making.”; “We ensure an appropriate, risk-based level of human control.” | H2: S. 5, 8 | I2: Hoch | J2: Deontisch („must respect…“) + human control. | K2: =Tabelle52[[#This Row],[value_present]]*Tabelle52[[#This Row],[binding_level]] -> 2
A3: 3 | B3: 16 | C3: VAL_02 | D3: 1 | E3: 1 | F3: AI-Systeme werden in Produktion überwacht, inkl. Feedback | G3: “We monitor AI systems in production… integrating user feedback.” | H3: S. 3 | I3: Hoch | J3: Monitoring/Feedback als Accountability-Indiz. | K3: =Tabelle52[[#This Row],[value_present]]*Tabelle52[[#This Row],[binding_level]] -> 1
A4: 3 | B4: 16 | C4: VAL_03 | D4: 1 | E4: 1 | F4: Kunden werden bei direkter KI-Interaktion informiert | G4: “We inform customers whenever they interact directly with an AI system, such as a chatbot.” | H4: S. 3 | I4: Hoch | J4: Kunden-Disclosure bei KI-Interaktion | K4: =Tabelle52[[#This Row],[value_present]]*Tabelle52[[#This Row],[binding_level]] -> 1
A5: 3 | B5: 16 | C5: VAL_04 | D5: 1 | E5: 1 | F5: Interpretierbarkeit wird risikobasiert angestrebt | G5: “We follow a risk-based approach to attain suitable levels of interpretability.” | H5: S. 3 | I5: Hoch | J5: Interpretability explizit (risk-based). | K5: =Tabelle52[[#This Row],[value_present]]*Tabelle52[[#This Row],[binding_level]] -> 1
A6: 3 | B6: 16 | C6: VAL_05 | D6: 1 | E6: 1 | F6: Vermeidung direkter/indirekter Diskriminierung; Bias wird in Daten und Modellen adressiert | G6: “We commit to avoiding… discrimination… in line with applicable non-discrimination law.”; “We mitigate potential bias both in the data itself… as well as… in each individual model.” | H6: S. 4, 5 | I6: Hoch | J6: Anti-Discrimination + Bias-Mitigation. | K6: =Tabelle52[[#This Row],[value_present]]*Tabelle52[[#This Row],[binding_level]] -> 1
A7: 3 | B7: 16 | C7: VAL_06 | D7: 1 | E7: 3 | F7: KI-Nutzung nur im Rahmen von Privacy Laws/Standards;Privacy Risk Assessment als Pflicht-Check bei Personal Data | G7: “AI systems may only be used… including the Allianz Privacy Standard.”; “perform a dedicated privacy risk assessment whenever personal data are utilised in an AI system.” | H7: S. 4, 6 | I7: Mittel | J7: Privacy + konkreter Pflicht-Check (Risk Assessment). | K7: =Tabelle52[[#This Row],[value_present]]*Tabelle52[[#This Row],[binding_level]] -> 3
A8: 3 | B8: 16 | C8: VAL_07 | D8: 1 | E8: 1 | F8: Cybersecurity & Resilience über den KI-Lifecycle | G8: “We ensure… cybersecurity and resilience measures… throughout the life-cycle of an AI System.” | H8: S. 4 | I8: Hoch | K8: =Tabelle52[[#This Row],[value_present]]*Tabelle52[[#This Row],[binding_level]] -> 1
A9: 3 | B9: 16 | C9: VAL_08 | D9: 0 | I9: Hoch | J9: Nicht nachweisbar. | K9: =Tabelle52[[#This Row],[value_present]]*Tabelle52[[#This Row],[binding_level]] -> 0
A10: 3 | B10: 16 | C10: VAL_09 | D10: 1 | E10: 1 | F10: Monitoring zur Sicherstellung beabsichtigter Outcomes (Reliability) | G10: “We monitor AI systems in production… [to] match the intended outcome…” | H10: S. 3 | I10: Mittel | J10: Reliability/Accuracy über Monitoring, ohne Test-/Robustness-Details. | K10: =Tabelle52[[#This Row],[value_present]]*Tabelle52[[#This Row],[binding_level]] -> 1
A11: 3 | B11: 16 | C11: VAL_10 | D11: 0 | I11: Hoch | J11: Nicht nachweisbar. | K11: =Tabelle52[[#This Row],[value_present]]*Tabelle52[[#This Row],[binding_level]] -> 0
A12: 3 | B12: 16 | C12: VAL_11 | D12: 0 | I12: Hoch | J12: Nicht nachweisbar. | K12: =Tabelle52[[#This Row],[value_present]]*Tabelle52[[#This Row],[binding_level]] -> 0
A13: 3 | B13: 16 | C13: VAL_12 | D13: 0 | I13: Hoch | J13: Nicht nachweisbar. | K13: =Tabelle52[[#This Row],[value_present]]*Tabelle52[[#This Row],[binding_level]] -> 0
A14: 3 | B14: 16 | C14: VAL_13 | D14: 0 | I14: Hoch | J14: Nicht nachweisbar. | K14: =Tabelle52[[#This Row],[value_present]]*Tabelle52[[#This Row],[binding_level]] -> 0
A15: 3 | B15: 16 | C15: VAL_14 | D15: 1 | E15: 2 | F15: AI-Use Cases an Gesetze/Standards gebunden; Illegale KI-Systeme werden nicht entwickelt/genutzt | G15: “AI systems and use cases may only be used in line with applicable laws and Allianz standards.”; “We do not develop or use AI Systems, which are in violation of the law.” | H15: S. 1,3 | I15: Hoch | J15: „may only“ + Verbot illegaler KI. | K15: =Tabelle52[[#This Row],[value_present]]*Tabelle52[[#This Row],[binding_level]] -> 2
A16: 3 | B16: 16 | C16: VAL_15 | D16: 0 | I16: Mittel | J16: „Prohibited AI“ wird hier nur als Gesetzesverstoß formuliert (keine expliziten ethischen Leitplanken jenseits Compliance). | K16: =Tabelle52[[#This Row],[value_present]]*Tabelle52[[#This Row],[binding_level]] -> 0
A17: 3 | B17: 16 | C17: VAL_16 | D17: 1 | E17: 2 | F17: Datenqualität wird als Voraussetzung für Training/Use gefordert | G17: “data quality has to be ensured when training and using AI Systems… through… data governance.” | H17: S. 5 | I17: Hoch | J17: Data Quality/Governance explizit für KI. | K17: =Tabelle52[[#This Row],[value_present]]*Tabelle52[[#This Row],[binding_level]] -> 2
A18: 3 | B18: 16 | C18: VAL_17 | D18: 0 | I18: Hoch | J18: Nicht nachweisbar. | K18: =Tabelle52[[#This Row],[value_present]]*Tabelle52[[#This Row],[binding_level]] -> 0
A19: 3 | B19: 16 | C19: VAL_18 | D19: 0 | I19: Hoch | J19: Nicht nachweisbar. | K19: =Tabelle52[[#This Row],[value_present]]*Tabelle52[[#This Row],[binding_level]] -> 0
A20: 4 | B20: 22 | C20: VAL_01 | D20: 1 | E20: 1 | F20: Human oversight + Accountability-Mechanismen;Keine autonomen KI-Entscheidungen mit materiellem Impact auf Mitarbeitende | G20: “...subject to human oversight and accountability mechanisms.”; “AI is not used to make autonomous decisions that have a material impact on employees.” | H20: S.2 – Prinzip 3 „Accountable“ | I20: hoch | J20: Human oversight + Verbot autonomer Entscheidungen mit materiellem Impact (Employees). | K20: =Tabelle52[[#This Row],[value_present]]*Tabelle52[[#This Row],[binding_level]] -> 1
A21: 4 | B21: 22 | C21: VAL_02 | D21: 1 | E21: 1 | F21: Verantwortung für Impact der KI-Anwendungen | G21: “We take responsibility for the impact of our AI applications…” | H21: S.2 – Prinzip 3 „Accountable“ | I21: hoch | J21: Verantwortung für Impact explizit. | K21: =Tabelle52[[#This Row],[value_present]]*Tabelle52[[#This Row],[binding_level]] -> 1
A22: 4 | B22: 22 | C22: VAL_03 | D22: 1 | E22: 1 | F22: Transparenz + nachvollziehbare Entscheidungsprozesse | G22: “We ensure that our AI applications are transparent…” | H22: S.2 – Prinzip 2 „Transparent“ | I22: hoch | J22: „transparent“ für AI applications. | K22: =Tabelle52[[#This Row],[value_present]]*Tabelle52[[#This Row],[binding_level]] -> 1
A23: 4 | B23: 22 | C23: VAL_04 | D23: 1 | E23: 1 | F23: Entscheidungsprozesse sollen für Stakeholder „comprehensible“ sein | G23: “...decision-making processes that are comprehensible to stakeholders.” | H23: S.2 – Prinzip 2 „Transparent“ | I23: mittel | J23: „comprehensible decision-making processes“ → interpretierbar/erklärnah (Grenzfall zu VAL_03). | K23: =Tabelle52[[#This Row],[value_present]]*Tabelle52[[#This Row],[binding_level]] -> 1
A24: 4 | B24: 22 | C24: VAL_05 | D24: 1 | E24: 1 | F24: Fairness, Equal opportunity, Anti-Discrimination | G24: “...reject discrimination.” | H24: S.2 – Prinzip 4 „Fair and Unbiased“ | I24: hoch | J24: Anti-Discrimination klar. | K24: =Tabelle52[[#This Row],[value_present]]*Tabelle52[[#This Row],[binding_level]] -> 1
A25: 4 | B25: 22 | C25: VAL_06 | D25: 1 | E25: 1 | F25: Privacy als „essential human right“ über gesamten Lifecycle | G25: “...protect the essential human right of an individual’s privacy throughout the entire life cycle…” | H25: S.2 – Prinzip 6 „Privacy Preserving“ | I25: hoch | J25: Privacy über gesamten Lifecycle. | K25: =Tabelle52[[#This Row],[value_present]]*Tabelle52[[#This Row],[binding_level]] -> 1
A26: 4 | B26: 22 | C26: VAL_07 | D26: 1 | E26: 1 | F26: Security: Integrität/Vertraulichkeit/Verfügbarkeit/Authentizität | G26: “...maintaining the integrity, confidentiality, availability and authenticity…” | H26: S.2 – Prinzip 5 „Secure“ | I26: hoch | J26: Schutzziele inkl. confidentiality/authenticity. | K26: =Tabelle52[[#This Row],[value_present]]*Tabelle52[[#This Row],[binding_level]] -> 1
A27: 4 | B27: 22 | C27: VAL_08 | D27: 1 | E27: 1 | F27: Wohlbefinden & Sicherheit von Individuen/Communities priorisiert; Robust & Safe: reliability, accuracy, safety | G27: “...prioritizing the well-being and safety of individuals and communities.”; “...focus on reliability, accuracy, and safety.” | H27: S.2 – Prinzip 1 & 7 | I27: mittel | J27: „safety“ (well-being/safety; robust & safe) vorhanden, aber ohne konkrete Harm-Controls. | K27: =Tabelle52[[#This Row],[value_present]]*Tabelle52[[#This Row],[binding_level]] -> 1
A28: 4 | B28: 22 | C28: VAL_09 | D28: 1 | E28: 1 | F28: Robust & Safe: reliability, accuracy, safety | G28: “...focus on reliability, accuracy, and safety.” | H28: S.2 – Prinzip 7 „Robust & Safe“ | I28: hoch | J28: reliability/accuracy explizit. | K28: =Tabelle52[[#This Row],[value_present]]*Tabelle52[[#This Row],[binding_level]] -> 1
A29: 4 | B29: 22 | C29: VAL_10 | D29: 0 | I29: hoch | J29: Nicht nachweisbar. | K29: =Tabelle52[[#This Row],[value_present]]*Tabelle52[[#This Row],[binding_level]] -> 0
A30: 4 | B30: 22 | C30: VAL_11 | D30: 0 | I30: hoch | J30: Nicht nachweisbar. | K30: =Tabelle52[[#This Row],[value_present]]*Tabelle52[[#This Row],[binding_level]] -> 0
A31: 4 | B31: 22 | C31: VAL_12 | D31: 0 | I31: hoch | J31: Nicht nachweisbar. | K31: =Tabelle52[[#This Row],[value_present]]*Tabelle52[[#This Row],[binding_level]] -> 0
A32: 4 | B32: 22 | C32: VAL_13 | D32: 0 | I32: hoch | J32: „create value“ zu allgemein; keine wert-/KI-spezifische Evidenz. | K32: =Tabelle52[[#This Row],[value_present]]*Tabelle52[[#This Row],[binding_level]] -> 0
A33: 4 | B33: 22 | C33: VAL_14 | D33: 1 | E33: 2 | F33: Responsible AI an EU AI Act/GDPR und Werte gebunden; KI für „Prohibited Practices“ wird strikt verboten (Policy-Verweis); Zentrales Inventar + Assessments zur Compliance/Risikosteuerung | G33: “...following laws like the EU AI Act and GDPR...”; “...strictly prohibiting AI in applications related to ‘Prohibited Practices’...”; “BASF maintains a central inventory and conducts necessary assessments to ensure compliance…” | H33: S.1 – Intro & „Commitment…“ | I33: mittel | J33: Laws (EU AI Act/GDPR) + „strictly prohibiting“; Inventory/Assessments als mögliche Prozess-Operationalisierung (Grenzfall BIND 2 vs 3). | K33: =Tabelle52[[#This Row],[value_present]]*Tabelle52[[#This Row],[binding_level]] -> 2
A34: 4 | B34: 22 | C34: VAL_15 | D34: 1 | E34: 1 | F34: Responsible AI als ethisch & accountable definiert; KI-Nutzung an Code of Conduct & Human Rights Policy gekoppelt | G34: “Responsible AI means developing, deploying, and using AI systems ethically and accountably.”; “...in accordance with our company’s values and ethical standards as described in our Code of Conduct…” | H34: S.1 – Definition;S.2 – Prinzip 1 | I34: hoch | J34: „ethically“ + Werte/CoC-Verweis. | K34: =Tabelle52[[#This Row],[value_present]]*Tabelle52[[#This Row],[binding_level]] -> 1
A35: 4 | B35: 22 | C35: VAL_16 | D35: 1 | E35: 1 | F35: Fokus auf Data & AI Governance (Daten als Schlüsselressource) | G35: “Our data is crucial for AI solutions, so we focus on strong data and AI governance.” | H35: S.1 – Intro | I35: mittel | J35: „data and AI governance“ genannt, aber ohne konkrete Data-Quality-Mechanik. | K35: =Tabelle52[[#This Row],[value_present]]*Tabelle52[[#This Row],[binding_level]] -> 1
A36: 4 | B36: 22 | C36: VAL_17 | D36: 0 | I36: mittel | J36: „confidentiality“ erscheint im Security-Kontext (VAL_07); kein IP/Trade-secret/IPR-Bezug. | K36: =Tabelle52[[#This Row],[value_present]]*Tabelle52[[#This Row],[binding_level]] -> 0
A37: 4 | B37: 22 | C37: VAL_18 | D37: 1 | E37: 1 | F37: Human Rights Management Policy als Bezugspunkt; Privacy als „essential human right“ über gesamten Lifecycle | G37: “...protect the essential human right of an individual’s privacy throughout the entire life cycle…”; “...set forth in BASF’s Human Rights Management Policy…” | H37: S.2 – Prinzip 1 & 6 | I37: mittel | J37: Human Rights Policy + „essential human right“ (privacy) explizit. | K37: =Tabelle52[[#This Row],[value_present]]*Tabelle52[[#This Row],[binding_level]] -> 1
A38: 5 | B38: 27 | C38: VAL_01 | D38: 1 | E38: 1 | F38: Autonomie wird respektiert; Harm Prevention/Wellbeing als Ziel; Schutz menschlicher Autonomie in entwickelten/verkauften/genutzten AI-Lösungen | G38: “We respect personal autonomy, strive to promote individual and collective wellbeing and preventing harm.”; “We will protect human autonomy in AI solutions that we develop, sell or use. | H38: S.8 – AI (Guiding Principles) | I38: hoch | J38: Autonomie explizit („respect/protect human autonomy“). | K38: =Tabelle52[[#This Row],[value_present]]*Tabelle52[[#This Row],[binding_level]] -> 1
A39: 5 | B39: 27 | C39: VAL_02 | D39: 1 | E39: 1 | F39: Inklusion (Datensätze), Fairness und Accountability werden angestrebt | G39: “...striving for inclusion in our data sets, fairness and accountability.” | H39: S.8 – AI (Guiding Principles) | I39: mittel | J39: „accountability“ genannt (ohne Rollen/Mechanik). | K39: =Tabelle52[[#This Row],[value_present]]*Tabelle52[[#This Row],[binding_level]] -> 1
A40: 5 | B40: 27 | C40: VAL_03 | D40: 1 | E40: 1 | F40: KI soll transparent genutzt werden (Commitment) | G40: “At Bayer, we commit to use AI transparently and responsibly.” | H40: S.8 – AI (Guiding Principles) | I40: hoch | J40: „commit to use AI transparently“. | K40: =Tabelle52[[#This Row],[value_present]]*Tabelle52[[#This Row],[binding_level]] -> 1
A41: 5 | B41: 27 | C41: VAL_04 | D41: 0 | I41: hoch | J41: Keine Explainability/Interpretability nachweisbar. | K41: =Tabelle52[[#This Row],[value_present]]*Tabelle52[[#This Row],[binding_level]] -> 0
A42: 5 | B42: 27 | C42: VAL_05 | D42: 1 | E42: 1 | F42: Inklusion (Datensätze), Fairness und Accountability werden angestrebt | G42: “...striving for inclusion in our data sets, fairness and accountability.” | H42: S.8 – AI (Guiding Principles) | I42: mittel | J42: „fairness“ + „inclusion in our data sets“ (kein Anti-Discrimination-Detail). | K42: =Tabelle52[[#This Row],[value_present]]*Tabelle52[[#This Row],[binding_level]] -> 1
A43: 5 | B43: 27 | C43: VAL_06 | D43: 0 | I43: hoch | J43: Keine AI-bezogene Privacy-Evidenz im Text. | K43: =Tabelle52[[#This Row],[value_present]]*Tabelle52[[#This Row],[binding_level]] -> 0
A44: 5 | B44: 27 | C44: VAL_07 | D44: 0 | I44: hoch | J44: Nicht nachweisbar. | K44: =Tabelle52[[#This Row],[value_present]]*Tabelle52[[#This Row],[binding_level]] -> 0
A45: 5 | B45: 27 | C45: VAL_08 | D45: 1 | E45: 1 | F45: Autonomie wird respektiert; Harm Prevention/Wellbeing als Ziel | G45: “We respect personal autonomy, strive to promote individual and collective wellbeing and preventing harm.” | H45: S.8 – AI (Guiding Principles) | I45: hoch | J45: „preventing harm“ explizit. | K45: =Tabelle52[[#This Row],[value_present]]*Tabelle52[[#This Row],[binding_level]] -> 1
A46: 5 | B46: 27 | C46: VAL_09 | D46: 1 | E46: 1 | F46: Verbot schlechter/unverifizierter Daten zur Vermeidung falscher/bias Ergebnisse | G46: “We do not use poor, incomplete or non-verified data… incorrect or biased results… AI applications.” | H46: S.8 – AI (Guiding Principles) | I46: niedrig | J46: Indirekt über „incorrect results“/Datenverifikation; keine Tests/Robustness-Terms. | K46: =Tabelle52[[#This Row],[value_present]]*Tabelle52[[#This Row],[binding_level]] -> 1
A47: 5 | B47: 27 | C47: VAL_10 | D47: 0 | I47: hoch | J47: Nicht nachweisbar. | K47: =Tabelle52[[#This Row],[value_present]]*Tabelle52[[#This Row],[binding_level]] -> 0
A48: 5 | B48: 27 | C48: VAL_11 | D48: 0 | I48: mittel | J48: „inclusion in our data sets“ eher Fairness/Data Governance; keine Accessibility. | K48: =Tabelle52[[#This Row],[value_present]]*Tabelle52[[#This Row],[binding_level]] -> 0
A49: 5 | B49: 27 | C49: VAL_12 | D49: 0 | I49: hoch | J49: Nicht nachweisbar. | K49: =Tabelle52[[#This Row],[value_present]]*Tabelle52[[#This Row],[binding_level]] -> 0
A50: 5 | B50: 27 | C50: VAL_13 | D50: 1 | E50: 1 | F50: Autonomie wird respektiert; Harm Prevention/Wellbeing als Ziel | G50: “We respect personal autonomy, strive to promote individual and collective wellbeing and preventing harm.” | H50: S.8 – AI (Guiding Principles) | I50: hoch | J50: „promote… wellbeing“ im AI-Kontext. | K50: =Tabelle52[[#This Row],[value_present]]*Tabelle52[[#This Row],[binding_level]] -> 1
A51: 5 | B51: 27 | C51: VAL_14 | D51: 1 | E51: 2 | F51: Recht/Regeln werden im AI-Kontext immer eingehalten | G51: “We always comply with all applicable laws, regulations, and professional codes of conduct.” | H51: S.8 – AI (Guiding Principles) | I51: hoch | J51: „always comply… laws, regulations…“ deontisch. | K51: =Tabelle52[[#This Row],[value_present]]*Tabelle52[[#This Row],[binding_level]] -> 2
A52: 5 | B52: 27 | C52: VAL_15 | D52: 1 | E52: 1 | F52: KI soll transparent genutzt werden (Commitment) | G52: “At Bayer, we commit to use AI transparently and responsibly.” | H52: S.8 – AI (Guiding Principles) | I52: mittel | J52: „responsibly“ im direkten AI-Commitment; keine weiterführenden Guardrails im AI-Abschnitt. | K52: =Tabelle52[[#This Row],[value_present]]*Tabelle52[[#This Row],[binding_level]] -> 1
A53: 5 | B53: 27 | C53: VAL_16 | D53: 1 | E53: 2 | F53: Anforderungen an Datenquellen (Provenance/Diversity/Quality); Check: Trainingsdaten-Repräsentativität wird verifiziert; Verbot schlechter/unverifizierter Daten zur Vermeidung falscher/bias Ergebnisse | G53: “We strive for clear relevance, provenance, diversity, and sufficient quality in data sources.”;“We verify the data sets used for AI training are representative…”; “We do not use poor, incomplete or non-verified data… incorrect or biased results… AI applications.” | H53: S.8 – AI (Guiding Principles) | I53: hoch | J53: Konkrete Datenanforderungen + Verifikations-/Verbotssatz („do not use…“). | K53: =Tabelle52[[#This Row],[value_present]]*Tabelle52[[#This Row],[binding_level]] -> 2
A54: 5 | B54: 27 | C54: VAL_17 | D54: 0 | I54: hoch | J54: Nicht nachweisbar. | K54: =Tabelle52[[#This Row],[value_present]]*Tabelle52[[#This Row],[binding_level]] -> 0
A55: 5 | B55: 27 | C55: VAL_18 | D55: 0 | I55: hoch | J55: Keine AI-bezogene Human-Rights-Nennung (außer allgemeine Bioethik-Teile). | K55: =Tabelle52[[#This Row],[value_present]]*Tabelle52[[#This Row],[binding_level]] -> 0
A56: 6 | B56: 32 | C56: VAL_01 | D56: 0 | I56: hoch | J56: Kein KI-Kontext im Dokument nachweisbar. | K56: =Tabelle52[[#This Row],[value_present]]*Tabelle52[[#This Row],[binding_level]] -> 0
A57: 6 | B57: 32 | C57: VAL_02 | D57: 0 | I57: hoch | J57: Kein KI-Kontext im Dokument nachweisbar. | K57: =Tabelle52[[#This Row],[value_present]]*Tabelle52[[#This Row],[binding_level]] -> 0
A58: 6 | B58: 32 | C58: VAL_03 | D58: 0 | I58: hoch | J58: Kein KI-Kontext im Dokument nachweisbar. | K58: =Tabelle52[[#This Row],[value_present]]*Tabelle52[[#This Row],[binding_level]] -> 0
A59: 6 | B59: 32 | C59: VAL_04 | D59: 0 | I59: hoch | J59: Kein KI-Kontext im Dokument nachweisbar. | K59: =Tabelle52[[#This Row],[value_present]]*Tabelle52[[#This Row],[binding_level]] -> 0
A60: 6 | B60: 32 | C60: VAL_05 | D60: 0 | I60: hoch | J60: Fairness-Themen nur arbeitsrechtlich/allgemein, ohne KI-Bezug. | K60: =Tabelle52[[#This Row],[value_present]]*Tabelle52[[#This Row],[binding_level]] -> 0
A61: 6 | B61: 32 | C61: VAL_06 | D61: 0 | I61: hoch | J61: Datenschutz nur allgemein, ohne KI-Bezug. | K61: =Tabelle52[[#This Row],[value_present]]*Tabelle52[[#This Row],[binding_level]] -> 0
A62: 6 | B62: 32 | C62: VAL_07 | D62: 0 | I62: hoch | J62: IT-/Security nur allgemein, ohne KI-Bezug. | K62: =Tabelle52[[#This Row],[value_present]]*Tabelle52[[#This Row],[binding_level]] -> 0
A63: 6 | B63: 32 | C63: VAL_08 | D63: 0 | I63: hoch | J63: Safety nur Arbeitsplatz, ohne KI-Bezug. | K63: =Tabelle52[[#This Row],[value_present]]*Tabelle52[[#This Row],[binding_level]] -> 0
A64: 6 | B64: 32 | C64: VAL_09 | D64: 0 | I64: hoch | J64: Keine KI/Modelle/Robustness-Themen. | K64: =Tabelle52[[#This Row],[value_present]]*Tabelle52[[#This Row],[binding_level]] -> 0
A65: 6 | B65: 32 | C65: VAL_10 | D65: 0 | I65: hoch | J65: Nicht nachweisbar im KI-Kontext. | K65: =Tabelle52[[#This Row],[value_present]]*Tabelle52[[#This Row],[binding_level]] -> 0
... A73: 6 | B73: 32 | C73: VAL_18 | D73: 0 | I73: hoch | J73: Human-rights-ähnliche Themen nur allgemein, ohne KI-Bezug. | K73: =Tabelle52[[#This Row],[value_present]]*Tabelle52[[#This Row],[binding_level]] -> 0
A74: 7 | B74: 37 | C74: VAL_01 | D74: 1 | E74: 1 | F74: Human oversight inkl. Möglichkeit des menschlichen Overrules | G74: “implements appropriate human monitoring… and considers… humans can overrule algorithmic decisions.” | H74: S.2 – Human agency and oversight | I74: hoch | J74: Human monitoring + human overrule. | K74: =Tabelle52[[#This Row],[value_present]]*Tabelle52[[#This Row],[binding_level]] -> 1
A75: 7 | B75: 37 | C75: VAL_02 | D75: 1 | E75: 1 | F75: Risiken werden identifiziert/bewertet/berichtet/mitigiert | G75: “will identify, assess, report and mitigate risks…” | H75: S.3 – Accountability | I75: mittel | J75: Risk handling inkl. “report”, ohne Rollen/Mechanik. | K75: =Tabelle52[[#This Row],[value_present]]*Tabelle52[[#This Row],[binding_level]] -> 1
A76: 7 | B76: 37 | C76: VAL_03 | D76: 1 | E76: 1 | F76: Transparenz über Einsatz der Technologien + Kommunikation | G76: “aims… open communication where respective technologies are used.” | H76: S.2 – Transparency | I76: mittel | J76: Open communication über AI-Nutzung (ohne konkrete Disclosure-Regel). | K76: =Tabelle52[[#This Row],[value_present]]*Tabelle52[[#This Row],[binding_level]] -> 1
A77: 7 | B77: 37 | C77: VAL_04 | D77: 1 | E77: 1 | F77: Explainability als Ziel bei AI applications | G77: “aims for explainability of AI applications…” | H77: S.2 – Transparency | I77: hoch | J77: Explainability ausdrücklich genannt. | K77: =Tabelle52[[#This Row],[value_present]]*Tabelle52[[#This Row],[binding_level]] -> 1
A78: 7 | B78: 37 | C78: VAL_05 | D78: 1 | E78: 1 | F78: Fairness über Human Dignity; Ziel „fair AI“ | G78: “respects human dignity… sets out to build fair AI applications.” | H78: S.2 – Diversity… fairness | I78: hoch | J78: “fair AI applications” + human dignity. | K78: =Tabelle52[[#This Row],[value_present]]*Tabelle52[[#This Row],[binding_level]] -> 1
A79: 7 | B79: 37 | C79: VAL_06 | D79: 1 | E79: 1 | F79: Privacy & data security auf AI storage/processing erweitert | G79: “extends its… data privacy and data security measures to cover storage and processing in AI applications.” | H79: S.2 – Privacy and data governance | I79: hoch | J79: Privacy/processing/storage in AI applications. | K79: =Tabelle52[[#This Row],[value_present]]*Tabelle52[[#This Row],[binding_level]] -> 1
A80: 7 | B80: 37 | C80: VAL_07 | D80: 1 | E80: 1 | F80: Data security measures im AI-Kontext | G80: “data… security measures… in AI applications.” | H80: S.2 – Privacy and data governance | I80: mittel | J80: “data security measures” (security, nicht cyber-spezifisch). | K80: =Tabelle52[[#This Row],[value_present]]*Tabelle52[[#This Row],[binding_level]] -> 1
A81: 7 | B81: 37 | C81: VAL_08 | D81: 1 | E81: 1 | F81: Safety/Vermeidung unbeabsichtigter Folgen/Errors | G81: “decrease the risk of unintended consequences and errors.” | H81: S.2 – Technical robustness and safety | I81: mittel | J81: “risk of unintended consequences and errors” (Safety-Anker). | K81: =Tabelle52[[#This Row],[value_present]]*Tabelle52[[#This Row],[binding_level]] -> 1
A82: 7 | B82: 37 | C82: VAL_09 | D82: 1 | E82: 1 | F82: Robustheit/Safety-Standards zur Fehler-/Risiko-Reduktion | G82: “aims to develop robust AI applications and observes the applicable safety standards…” | H82: S.2 – Technical robustness and safety | I82: hoch | J82: Robust AI + safety standards. | K82: =Tabelle52[[#This Row],[value_present]]*Tabelle52[[#This Row],[binding_level]] -> 1
A83: 7 | B83: 37 | C83: VAL_10 | D83: 0 | I83: hoch | J83: Nicht nachweisbar. | K83: =Tabelle52[[#This Row],[value_present]]*Tabelle52[[#This Row],[binding_level]] -> 0
A84: 7 | B84: 37 | C84: VAL_11 | D84: 0 | I84: hoch | J84: Nicht nachweisbar. | K84: =Tabelle52[[#This Row],[value_present]]*Tabelle52[[#This Row],[binding_level]] -> 0
A85: 7 | B85: 37 | C85: VAL_12 | D85: 1 | E85: 1 | F85: AI soll Umwelt-/Societal Well-being fördern (inkl. Klima/Umweltschutz) | G85: “goals… human rights and sustainability… climate change and environmental protection.” | H85: S.2 – Environmental and societal well-being | I85: hoch | J85: Klima/Umweltschutz explizit. | K85: =Tabelle52[[#This Row],[value_present]]*Tabelle52[[#This Row],[binding_level]] -> 1
A86: 7 | B86: 37 | C86: VAL_13 | D86: 1 | E86: 1 | F86: AI soll Well-being von Stakeholdern fördern | G86: “AI applications that promote the well-being of customers, employees and partners.” | H86: S.2 – Environmental and societal well-being | I86: hoch | J86: Well-being für customers/employees/partners. | K86: =Tabelle52[[#This Row],[value_present]]*Tabelle52[[#This Row],[binding_level]] -> 1
A87: 7 | B87: 37 | C87: VAL_14 | D87: 1 | E87: 1 | F87: „Applicable safety standards“ als Compliance-Anker (indirekt) | G87: “observes the applicable safety standards…” | H87: S.2 – Technical robustness and safety | I87: niedrig | J87: Indirekt über “applicable safety standards” (Grenzfall). | K87: =Tabelle52[[#This Row],[value_present]]*Tabelle52[[#This Row],[binding_level]] -> 1
A88: 7 | B88: 37 | C88: VAL_15 | D88: 1 | E88: 1 | F88: Ethik als Zweck von Project AI (AI „ethically“) | G88: “Project AI… to ensure that AI technologies are used ethically and efficiently.” | H88: S.3 – Project AI (Launch 2018) | I88: mittel | J88: “used ethically” explizit, aber ohne weitere Guardrails. | K88: =Tabelle52[[#This Row],[value_present]]*Tabelle52[[#This Row],[binding_level]] -> 1
A89: 7 | B89: 37 | C89: VAL_16 | D89: 0 | I89: hoch | J89: Keine Data-quality/Governance-Mechanik nachweisbar (nur “privacy and data governance” als Überschrift). | K89: =Tabelle52[[#This Row],[value_present]]*Tabelle52[[#This Row],[binding_level]] -> 0
A90: 7 | B90: 37 | C90: VAL_17 | D90: 0 | I90: hoch | J90: Nicht nachweisbar. | K90: =Tabelle52[[#This Row],[value_present]]*Tabelle52[[#This Row],[binding_level]] -> 0
A91: 7 | B91: 37 | C91: VAL_18 | D91: 1 | E91: 1 | F91: Bezug zu Human Rights-Zielen | G91: “aligns with the BMW Group’s goals in the areas of human rights…” | H91: S.2 – Environmental and societal well-being | I91: mittel | J91: Human-rights-Ziele genannt, ohne Konkretisierung. | K91: =Tabelle52[[#This Row],[value_present]]*Tabelle52[[#This Row],[binding_level]] -> 1
A92: 12 | B92: 62 | C92: VAL_01 | D92: 1 | E92: 1 | F92: Human oversight über alle Lifecycle-Stages | G92: “appropriate level of human oversight in all lifecycle stages…” | H92: S.6 – Human Oversight & Monitoring | I92: hoch | J92: Human oversight über Lifecycle genannt. | K92: =Tabelle52[[#This Row],[value_present]]*Tabelle52[[#This Row],[binding_level]] -> 1
A93: 12 | B93: 62 | C93: VAL_02 | D93: 1 | E93: 1 | F93: Klare Ownership/Accountability über Lifecycle gefordert | G93: “Establish clear accountability and ownership for AI solutions at all points in the lifecycle.” | H93: S.5 – Accountability | I93: hoch | J93: Accountability/Ownership über Lifecycle. | K93: =Tabelle52[[#This Row],[value_present]]*Tabelle52[[#This Row],[binding_level]] -> 1
A94: 12 | B94: 62 | C94: VAL_03 | D94: 1 | E94: 1 | F94: Transparenz/Explainability wird angestrebt | G94: “Strive to achieve an appropriate level of transparency and Explainability…” | H94: S.6 – Transparency & Explainability | I94: hoch | J94: Transparenz explizit. | K94: =Tabelle52[[#This Row],[value_present]]*Tabelle52[[#This Row],[binding_level]] -> 1
A95: 12 | B95: 62 | C95: VAL_04 | D95: 1 | E95: 1 | F95: Explainability von AI Models/Workflows wird angestrebt | G95: “Explainability of AI Models and workflows.” | H95: S.6 – Transparency & Explainability | I95: hoch | J95: Explainability explizit. | K95: =Tabelle52[[#This Row],[value_present]]*Tabelle52[[#This Row],[binding_level]] -> 1
A96: 12 | B96: 62 | C96: VAL_05 | D96: 1 | E96: 1 | F96: Fairness als Ziel, um Benachteiligungen zu vermeiden; Unintended bias soll vermieden werden | G96: “Strive to make AI solutions fair to ensure groups or individuals are not unnecessarily deprived…”; “Strive to avoid unintended bias in our AI solutions.” | H96: S.5 – Fairness & Bias | I96: hoch | J96: Fairness + bias avoidance explizit. | K96: =Tabelle52[[#This Row],[value_present]]*Tabelle52[[#This Row],[binding_level]] -> 1
A97: 12 | B97: 62 | C97: VAL_06 | D97: 1 | E97: 1 | F97: Privacy: DP-Law-Compliance als Bestandteil; TOMs zum Schutz fundamentaler Rechte gefordert | G97: “complying with applicable data protection laws”; “implementing appropriate technical and organisational measures…” | H97: S.6 – Privacy | I97: hoch | J97: DP-law compliance + TOMs genannt. | K97: =Tabelle52[[#This Row],[value_present]]*Tabelle52[[#This Row],[binding_level]] -> 1
A98: 12 | B98: 62 | C98: VAL_07 | D98: 1 | E98: 1 | F98: InfoSec-Risiken sollen proaktiv verhindert werden | G98: “proactively prevent Information Security risks and threats, having corrective measures in place.” | H98: S.5 – Security, Safety & Technical Robustness | I98: hoch | J98: Information Security risks + corrective measures. | K98: =Tabelle52[[#This Row],[value_present]]*Tabelle52[[#This Row],[binding_level]] -> 1
A99: 12 | B99: 62 | C99: VAL_08 | D99: 1 | E99: 1 | F99: Safety/Abuse-Risiken sollen durch robusten Ansatz vermieden werden | G99: “manage AI solutions with a robust approach to avoid potential risks and issues around safety and abuse.” | H99: S.5 – Security, Safety & Technical Robustness | I99: mittel | J99: Safety/abuse genannt (überlappt mit Robustness). | K99: =Tabelle52[[#This Row],[value_present]]*Tabelle52[[#This Row],[binding_level]] -> 1
A100: 12 | B100: 62 | C100: VAL_09 | D100: 1 | E100: 1 | F100: Robuste Entwicklung/Management von AI-Lösungen (Robustness) | G100: “Design, build, and manage AI solutions with a robust approach…” | H100: S.5 – Security, Safety & Technical Robustness | I100: hoch | J100: „robust approach“ explizit. | K100: =Tabelle52[[#This Row],[value_present]]*Tabelle52[[#This Row],[binding_level]] -> 1
A101: 12 | B101: 62 | C101: VAL_10 | D101: 0 | I101: hoch | J101: Nicht nachweisbar im AI-Abschnitt. | K101: =Tabelle52[[#This Row],[value_present]]*Tabelle52[[#This Row],[binding_level]] -> 0
A102: 12 | B102: 62 | C102: VAL_11 | D102: 1 | E102: 1 | F102: Accessibility soll mitgedacht werden | G102: “to innovate responsibly and inclusively and to consider accessibility.” | H102: S.5 – Fairness & Bias | I102: mittel | J102: Accessibility erwähnt, aber nur als kurzer Nebensatz. | K102: =Tabelle52[[#This Row],[value_present]]*Tabelle52[[#This Row],[binding_level]] -> 1
A103: 12 | B103: 62 | C103: VAL_12 | D103: 0 | I103: hoch | J103: Nicht nachweisbar im AI-Abschnitt. | K103: =Tabelle52[[#This Row],[value_present]]*Tabelle52[[#This Row],[binding_level]] -> 0
A104: 12 | B104: 62 | C104: VAL_13 | D104: 0 | I104: mittel | J104: Stakeholder-Wording vorhanden, aber kein Social-Benefit/Well-being-Prinzip im AI-Teil. | K104: =Tabelle52[[#This Row],[value_present]]*Tabelle52[[#This Row],[binding_level]] -> 0
A105: 12 | B105: 62 | C105: VAL_14 | D105: 1 | E105: 2 | F105: Vendor Compliance mit AI-Regulierung wird erwartet | G105: “We expect our vendors to also comply with the same regulations…” | H105: S.5 – 10. Artificial Intelligence | I105: hoch | J105: Vendor-Compliance mit AI-Regulierung explizit erwartet. | K105: =Tabelle52[[#This Row],[value_present]]*Tabelle52[[#This Row],[binding_level]] -> 2
A106: 12 | B106: 62 | C106: VAL_15 | D106: 1 | E106: 1 | F106: Alignment mit Werten/CoC/Policies „at all times“ | G106: “aligned at all times with Deutsche Bank’s values, code of conduct, and applicable policies.” | H106: S.6 – Alignment | I106: hoch | J106: Alignment mit Werten/CoC/Policies „at all times“. | K106: =Tabelle52[[#This Row],[value_present]]*Tabelle52[[#This Row],[binding_level]] -> 1
A107: 12 | B107: 62 | C107: VAL_16 | D107: 0 | I107: hoch | J107: Keine Data-quality/Governance-Anforderungen im AI-Teil nachweisbar. | K107: =Tabelle52[[#This Row],[value_present]]*Tabelle52[[#This Row],[binding_level]] -> 0
...

Sheet 05b_Governance_Coding_PILOT
A1: company_id | B1: doc_id | C1: gov_crit_id | D1: doc_id_primary_evidence | E1: score_0_3 | F1: evidence_quote | G1: evidence_location | H1: why_not_higher | I1: coder_confidence | J1: notes
A2: 3 | B2: 16 | C2: GOV_01 | E2: 2 | F2: “Allianz has established… (DAITAB)… provides recommendations to the Board of Management…”;“The RAI Governance establishes the new role of an AI Trust Officer at both Group and local level.”; “The Group AI Office… providing… AI literacy, and oversight for AI…” | G2: S. 5-6 | H2: Rollen/Gremien + Aufgaben beschrieben. Kein Implementierungsnachweis | I2: Hoch
A3: 3 | B3: 16 | C3: GOV_02 | E3: 1 | F3: “Working cross-functionally, we consult relevant stakeholders… to ensure implementation of… Privacy and Ethics by Design.”; “The Allianz Standard… [and] Functional Rule… establish the… framework… [and] are currently being rolled out.” | G3: S. 2, 6 | H3: Prozessabsicht/Framework erwähnt, keine vollständige Prozesskette. | I3: Mittel
A4: 3 | B4: 16 | C4: GOV_03 | E4: 2 | F4: “perform a dedicated privacy risk assessment whenever personal data are utilised in an AI system.”;“conduct RAI-assessments with the CDO” | G4: S. 4 | H4: Konkrete Checks + Einsatzkontext (Trigger/Verortung). | I4: Hoch
A5: 3 | B5: 16 | C5: GOV_04 | E5: 0 | I5: Hoch
A6: 3 | B6: 16 | C6: GOV_05 | E6: 1 | F6: “The Group AI Office… providing… AI literacy, and oversight for AI…” | G6: S. 6 | H6: Literacy erwähnt, aber keine Pflicht/Programm-Details. | I6: Mittel
A7: 3 | B7: 16 | C7: GOV_06 | E7: 2 | F7: “…escalate unresolved risk disagreements to the DAITAB.” | G7: S. 6 | H7: Eskalationsmechanik benannt, kein Nachweis geübter Abläufe. | I7: Mittel
A8: 3 | B8: 16 | C8: GOV_07 | E8: 0 | I8: Hoch
A9: 4 | B9: 22 | C9: GOV_01 | E9: 1 | F9: “...please contact our Data & AI office.” | G9: S.3 – Contact | H9: „Data & AI office“ als Einheit genannt, aber ohne Aufgaben/RACI. | I9: Hoch
A10: 4 | B10: 22 | C10: GOV_02 | E10: 1 | F10: “BASF maintains a central inventory and conducts necessary assessments to ensure compliance…” | G10: S.1 – „Commitment…“ | H10: Inventory + „assessments“ erwähnt, jedoch ohne Trigger/Owner/Schrittfolge. | I10: Hoch
A11: 4 | B11: 22 | C11: GOV_03 | E11: 1 | F11: “BASF maintains a central inventory and conducts necessary assessments to ensure compliance…” | G11: S.1 – „Commitment…“ | H11: „central inventory“ + „necessary assessments“ (Checks allgemein, nicht spezifiziert). | I11: Hoch
A12: 4 | B12: 22 | C12: GOV_04 | E12: 0 | I12: Hoch | J12: Nicht nachweisbar.
A13: 4 | B13: 22 | C13: GOV_05 | E13: 0 | I13: Hoch | J13: Nicht nachweisbar.
A14: 4 | B14: 22 | C14: GOV_06 | E14: 0 | I14: Hoch | J14: Nicht nachweisbar.
A15: 4 | B15: 22 | C15: GOV_07 | E15: 0 | I15: Hoch | J15: Nicht nachweisbar.
A16: 5 | B16: 27 | C16: GOV_01 | E16: 1 | F16: “...seek advice… including our independent Bioethics Council members.” | G16: S.2 – Our commitments | H16: Bioethics Council erwähnt (Beratung), aber keine AI-spezifischen Rollen/RACI. | I16: Niedrig
A17: 5 | B17: 27 | C17: GOV_02 | E17: 1 | F17: “We regularly cooperate with researchers, regulatory bodies… to jointly develop trustworthy AI-enabled solutions.”; “We hold companies that Bayer partners with… or… procured to the same standard.” | G17: S.8 – AI (Guiding Principles) | H17: „regularly cooperate…“ + Partnerstandard (Prozessabsicht, keine Schrittfolge/Trigger/Owner). | I17: Mittel
A18: 5 | B18: 27 | C18: GOV_03 | E18: 2 | F18: “We verify the data sets used for AI training are representative…”; “We do not use poor, incomplete or non-verified data… incorrect or biased results… AI applications.” | G18: S.8 – AI (Guiding Principles) | H18: Konkrete Checks: Representativeness-Verifikation; Datenverifikation/„do not use“ (ohne Toolname). | I18: Mittel
A19: 5 | B19: 27 | C19: GOV_04 | E19: 1 | F19: “...put into practice… safeguards… internal oversight, inspections, and maintenance of AI solutions.” | G19: S.8 – AI (Guiding Principles) | H19: „inspections“ erwähnt, aber ohne Audit-Mechanik/Frequenz/Verantwortliche. | I19: Niedrig
A20: 5 | B20: 27 | C20: GOV_05 | E20: 0 | I20: Hoch | J20: Nicht nachweisbar.
A21: 5 | B21: 27 | C21: GOV_06 | E21: 0 | I21: Hoch | J21: Nicht nachweisbar.
A22: 5 | B22: 27 | C22: GOV_07 | E22: 0 | I22: Hoch | J22: Nicht nachweisbar.
A23: 6 | B23: 32 | C23: GOV_01 | E23: 0 | I23: hoch | J23: Rollen genannt, aber ohne KI/AI-Bezug → 0.
A24: 6 | B24: 32 | C24: GOV_02 | E24: 0 | I24: hoch | J24: Keine KI-spezifischen Prozesse nachweisbar.
A25: 6 | B25: 32 | C25: GOV_03 | E25: 0 | I25: hoch | J25: Keine KI-spezifischen Checks/Tools nachweisbar.
A26: 6 | B26: 32 | C26: GOV_04 | E26: 0 | I26: hoch | J26: Audit-Begriff nur allgemein/Finanzen, nicht KI/AI-Audits.
A27: 6 | B27: 32 | C27: GOV_05 | E27: 0 | I27: hoch | J27: Training nur allgemein, nicht KI-spezifisch.
A28: 6 | B28: 32 | C28: GOV_06 | E28: 0 | I28: hoch | J28: Meldewege nur allgemein, nicht KI-spezifisch.
A29: 6 | B29: 32 | C29: GOV_07 | E29: 0 | I29: hoch | J29: Kein KI-spezifisches Reporting nachweisbar.
A30: 7 | B30: 37 | C30: GOV_01 | E30: 2 | F30: “centre of competence… ensures rapid knowledge and technology sharing across the company.” | G30: S.3 – Project AI (centre of competence) | H30: Konkrete Einheit + Aufgaben (knowledge/tech sharing). | I30: mittel
A31: 7 | B31: 37 | C31: GOV_02 | E31: 1 | F31: “These will be continuously refined and adapted as required…” | G31: S.1 – continuously refined/adapted | H31: Update-/Review-Absicht, ohne Trigger/Owner/Schritte. | I31: mittel
A32: 7 | B32: 37 | C32: GOV_03 | E32: 2 | F32: “a portfolio tool… D³… portfolio currently spans 400 use cases.” | G32: S.3 – D³ portfolio tool | H32: Tool namentlich benannt (Portfolio/Inventory), “wann” nur implizit (laufend). | I32: mittel
A33: 7 | B33: 37 | C33: GOV_04 | E33: 0 | I33: hoch | J33: Nicht nachweisbar.
A34: 7 | B34: 37 | C34: GOV_05 | E34: 1 | F34: “increase awareness among its employees… sensitivity when working with AI technologies.” | G34: S.1 – increase awareness | H34: Awareness erwähnt, kein Trainingsprogramm/Verpflichtung. | I34: niedrig
A35: 7 | B35: 37 | C35: GOV_06 | E35: 0 | I35: hoch | J35: Nicht nachweisbar.
A36: 7 | B36: 37 | C36: GOV_07 | E36: 1 | F36: “will identify, assess, report and mitigate risks…” | G36: S.3 – Accountability (“report… risks”) | H36: Reporting-Absicht (“report”), ohne Empfänger/Frequenz/KPIs. | I36: mittel
A37: 12 | B37: 62 | C37: GOV_01 | E37: 0 | I37: hoch | J37: Nicht nachweisbar.
A38: 12 | B38: 62 | C38: GOV_02 | E38: 0 | I38: hoch | J38: Nicht nachweisbar.
A39: 12 | B39: 62 | C39: GOV_03 | E39: 1 | F39: “implement automated monitoring of the AI decision-making…” | G39: S.6 – Human Oversight & Monitoring | H39: Monitoring als Check genannt („good practice“), ohne Toolname/Verpflichtung/Einbettung. | I39: mittel
A40: 12 | B40: 62 | C40: GOV_04 | E40: 0 | I40: hoch | J40: Nicht nachweisbar.
A41: 12 | B41: 62 | C41: GOV_05 | E41: 1 | F41: “ensure that practitioners have the appropriate qualifications and access to continuous training.” | G41: S.5 – Education & Training | H41: Training/Qualifications/continuous training genannt, ohne Programm-/Pflichtnachweis. | I41: mittel
A42: 12 | B42: 62 | C42: GOV_06 | E42: 0 | I42: hoch | J42: Nicht nachweisbar.
A43: 12 | B43: 62 | C43: GOV_07 | E43: 0 | I43: hoch | J43: Nicht nachweisbar.
A44: 15 | B44: 86 | C44: GOV_01 | E44: 2 | F44: “we clarify which initiative or product owner has which responsibilities.”; “Group Compliance Management” | G44: S.3 (product owner); p.12 (Group Compliance Management) | H44: Rollen/Verankerung benannt; Aufgaben grob (responsibilities). | I44: mittel
A45: 15 | B45: 86 | C45: GOV_02 | E45: 1 | F45: “developed and enhanced on grounds of deep analysis and evaluation.” | G45: S.8 – deep analysis/evaluation | H45: Prozessabsicht/Schritt erwähnt; Trigger/Owner nicht vollständig. | I45: mittel
A46: 15 | B46: 86 | C46: GOV_03 | E46: 2 | F46: “stop AI systems at any time (kill switch).”; “In case of inconsistencies, we rather stop the AI system”; “reset… in order to remove false or biased data.” | G46: S.9 (kill switch/stop/reset); p.8 (privacy & security by design) | H46: Konkrete Kontrolltools + „wann“ teils klar („any time“, „in case of inconsistencies“). | I46: mittel
A47: 15 | B47: 86 | C47: GOV_04 | E47: 1 | F47: “transparent, auditable, fair, and fully documented.” | G47: S.8 – “auditable” | H47: Audit/Assessment nur als Eigenschaft erwähnt; keine Audit-Mechanik. | I47: niedrig
A48: 15 | B48: 86 | C48: GOV_05 | E48: 1 | F48: “We will engage in AI and ethics education.” | G48: S.11 – AI and ethics education | H48: Education zugesagt, ohne Programm-/Pflichtdetails. | I48: mittel
A49: 15 | B49: 86 | C49: GOV_06 | E49: 0 | I49: hoch | J49: Nicht nachweisbar.
A50: 15 | B50: 86 | C50: GOV_07 | E50: 0 | I50: hoch | J50: Nicht nachweisbar.
A51: 32 | B51: 188 | C51: GOV_01 | E51: 2 | F51: “Accountable for approving high-risk use cases.”; “independent and unbiased feedback and recommendations”; “Reviewing and updating the AI Ethics policy and guiding principles.”; “Providing education and training material” | G51: S.6–7 – Roles and Responsibilities | H51: Rollen/Gremien + Mandate beschrieben (Steering, Advisory, Office, Workstream). | I51: Hoch
A52: 32 | B52: 188 | C52: GOV_02 | E52: 2 | F52: “several checkpoints… required before releasing the AI system.”; “High risk… panels… decide… Forbidden… will not allow” | G52: S.12 – 7. Governance (Use case evaluation) | H52: Use-case Evaluation inkl. Checkpoints + Risk-Kategorien + Entscheidungspfad. | I52: Hoch
A53: 32 | B53: 188 | C53: GOV_03 | E53: 2 | F53: “impact and policy compliance assessments are in place”; “Tests cases and results should be documented”; “each AI system must be accompanied by a comprehensive set of documentation.” | G53: S.11 (assessments); p.8 (tests documented); p.10 (documentation) | H53: Assessments/Tests/Dokumentationspflicht als Checks, teils ohne Toolnamen. | I53: Mittel
A54: 32 | B54: 188 | C54: GOV_04 | E54: 2 | F54: “A periodic evaluation… must be performed and documented.” | G54: S.12 – periodic evaluation | H54: Periodische Evaluation „must be performed and documented“ (Review-Mechanismus). | I54: Mittel
A55: 32 | B55: 188 | C55: GOV_05 | E55: 2 | F55: “Providing education and training material” | G55: S.7 – Trustworthy AI Workstream | H55: Training-Material/Opportunities explizit (Beschreibung, nicht nur Schlagwort). | I55: Hoch
A56: 32 | B56: 188 | C56: GOV_06 | E56: 2 | F56: “they can use the Speak Out tool.”; “High risk… panels… decide… Forbidden… will not allow” | G56: S.12 – Speak Out; high-risk panels decide | H56: Anonymer Kanal + Expert Panels als Eskalations-/Entscheidungsinstanzen. | I56: Hoch
A57: 32 | B57: 188 | C57: GOV_07 | E57: 1 | F57: “shall be promptly documented… and shared with other actors.” | G57: S.11 – Documentation (High-risk) | H57: Abweichungen werden dokumentiert & geteilt; keine KPI-/Frequenz-/Empfängerlogik. | I57: Hoch

Sheet 07_Boundary_Cases
A1: case_id | B1: date | C1: company_id | D1: doc_id | E1: dimension(values/governance) | F1: value_id_or_gov_crit_id | G1: problem_description | H1: decision | I1: rule_added_to_codebook | J1: codebook_version
A2: C1 | B2: 02.03.26 | C2: 3 | D2: 16 | F2: VAL_06 (BIND) | G2: Reicht „privacy risk assessment whenever…“ als Standard/Prozessvorgabe (BIND=3) oder bleibt es Policy-Regel (BIND=2)? | H2: A: BIND=2 (deontisch „may only…“) B: BIND=3 (konkreter Pflicht-Check + Trigger). Gewählt: B, weil Check+Trigger explizit. | I2: nein | J2: V00.1
A3: C2 | B3: 02.03.26 | C3: 3 | D3: 16 | F3: VAL_09 | G3: Ist „monitor… ensure decisions match intended outcome“ ausreichend spezifisch für Technical Robustness & Reliability oder nur Accountability? | H3: A: VAL_09=1 (Reliability/Accuracy via Monitoring) B: VAL_09=0 (zu unspezifisch, eher VAL_02). Gewählt: A, aber konservativ mit BIND=1 und Confidence=mittel. | I3: ja | J3: V00.1
A4: C3 | B4: 02.03.26 | C4: 3 | D4: 16 | F4: GOV_02 | G4: Sind Stakeholder-Consultation + Corporate Rules bereits „dokumentierte Prozesse“ (Score=2) oder nur „benannt“ (Score=1)? | H4: A: Score=2 (Prozess-/Rahmen beschrieben) B: Score=1 (keine klare Prozesskette mit Trigger+Owner). Gewählt: B (konservativ). | I4: ja | J4: V00.1
A5: C4 | B5: 02.03.26 | C5: 3 | D5: 16 | F5: GOV_07 | G5: Zählt „provides recommendations to the Board“ als Reporting? | H5: A: Score=1/2 (Reporting-Struktur) B: Score=0 (keine KPI/Reportgegenstand+Frequenz). Gewählt: B, da Evidenzminimum für Reporting nicht erfüllt. | I5: nein | J5: V00.1
A6: C5 | B6: 02.03.26 | C6: 3 | D6: 16 | F6: VAL_15 | G6: Ist „Prohibited AI“ als ethische Leitplanke (VAL_15) zu werten, obwohl es nur als Gesetzesverstoß formuliert ist? | H6: A: VAL_15=1 (Guardrail/„do not“) B: VAL_15=0 (nur Compliance → VAL_14). Gewählt: B (konservativ). | I6: ja | J6: V00.1
A7: C6 | B7: 02.03.26 | C7: 3 | D7: 16 | F7: multiple | G7: Q&A enthält nur Fragen; mögliche Evidenz in (nicht sichtbaren) Antworten fehlt in der PDF. | H7: A: Codes evtl. aus Fragen ableiten B: Nur sichtbaren Text werten (Evidence-first). Gewählt: B. | I7: ja | J7: V00.1
A8: C7 | B8: 02.03.26 | C8: 4 | D8: 22 | F8: VAL_04 vs VAL_03 | G8: Ist „comprehensible decision-making processes“ Explainability (VAL_04) oder nur Transparenz (VAL_03)? | H8: A: VAL_04=0 (nur Transparenz) B: VAL_04=1 (Erklär-/Interpretierkomponente). Gewählt: B (konservativ BIND=1, Confidence=mittel), da „decision-making… comprehensible“ über reines Disclosure hinausgeht. | I8: ja | J8: V00.1
A9: C8 | B9: 02.03.26 | C9: 4 | D9: 22 | F9: VAL_14 (BIND) | G9: Erhöht „central inventory + assessments“ die Bindigkeit für Compliance auf BIND=3 (Prozessvorgabe) oder bleibt BIND=2 (Policy-Regel/Verbot)? | H9: A: BIND=2 (starkes Verbot, aber Prozess unkonkret) B: BIND=3 (Operationalisierung via Inventory/Assessments). Gewählt: A, weil Assessments nicht spezifiziert (keine definierten Kontrollschritte). | I9: ja | J9: V00.1
A10: C9 | B10: 02.03.26 | C10: 4 | D10: 22 | F10: GOV_02 / GOV_03 | G10: Sind Inventory/Assessments bereits „dokumentiert“ (Score=2) oder nur „benannt“ (Score=1)? | H10: A: Score=2 (konkretes Tool/Prozess genannt) B: Score=1 (ohne Trigger/Owner/Details). Gewählt: B (konservativ). | I10: ja | J10: V00.1
A11: C10 | B11: 02.03.26 | C11: 4 | D11: 22 | F11: VAL_16 | G11: Reicht „focus on strong data and AI governance“ für VAL_16 oder ist es zu allgemein? | H11: A: VAL_16=1 (Data Governance explizit im KI-Kontext) B: VAL_16=0 (zu unspezifisch, keine Mechanik). Gewählt: A (BIND=1, Confidence=mittel) wegen explizitem Governance-Bezug. | I11: ja | J11: V00.1
A12: C11 | B12: 02.03.26 | C12: 4 | D12: 22 | F12: VAL_08 | G12: Ist „well-being and safety“/„Robust & Safe“ ausreichend für VAL_08 (Safety & Harm Prevention) oder nur Robustness (VAL_09)? | H12: A: VAL_08=1 (Safety explizit) B: VAL_08=0 (keine Harm-Controls). Gewählt: A mit Confidence=mittel, da „safety“ wörtlich genannt. | I12: ja | J12: V00.1
A13: C12 | B13: 02.03.26 | C13: 4 | D13: 22 | F13: VAL_18 | G13: Zählt Privacy als „essential human right“ bereits als Human Rights (VAL_18) oder bleibt es nur VAL_06? | H13: A: VAL_18=1 (human right explizit + HR policy) B: VAL_18=0 (nur Datenschutzwert). Gewählt: A (Confidence=mittel) wegen HR policy + „human right“-Formulierung. | I13: nein | J13: V00.1
... A48: C47 | B48: 02.03.26 | C48: 32 | D48: 188 | F48: VAL_16 | G48: Ist Dokumentationspflicht eher Transparenz (VAL_03) oder Data Governance (VAL_16) oder beides? | H48: A: nur VAL_03 B: VAL_03 + VAL_16. Gewählt: B, da Doku explizit Datasets/Training/Validation umfasst (Data/Model Governance). | I48: ja | J48: V00.1

Sheet 08a_Regelkonsolidierung_Pilot
A1: Regel-ID | B1: Kategorie | C1: Regeltext | D1: Betroffene Codes | E1: Trigger | F1: Testfrage
A2: R01 | B2: (iii) In-/Exklusion | C2: Ohne expliziten KI-Anker wird weder ein Value noch ein Governance-Kriterium codiert. | D2: alle VAL, alle GOV | E2: C19–C24 | F2: „Steht AI/KI/algorithmic/model/ML o. ä. wirklich im codierten Satz/Abschnitt?“
A3: R02 | B3: (iii) In-/Exklusion | C3: Es zählt nur sichtbar belegter Text; aus fehlenden Antworten, impliziten Inhalten oder vermuteten Anhängen wird nichts abgeleitet. | D3: alle | E3: C6 | F3: „Kann ich die Evidenzstelle wörtlich zeigen?“
A4: R03 | B4: (iii) PR vs Substanz | C4: Reine Image-/Wohlklangsprache ohne Norm, Mechanik oder definierte KI-Aussage wird nicht codiert. | D4: alle | E4: C5, C24, C45 | F4: „Ist das mehr als PR – also Pflicht, Grenze oder Mechanik?“
A5: R04 | B5: (i) Value↔Value | C5: VAL_03 = Offenlegung/Identifizierbarkeit/Einsatztransparenz; VAL_04 = Erklärung/Interpretierbarkeit/Verstehbarkeit von Output oder Entscheidungslogik. | D5: VAL_03, VAL_04 | E5: C7, C36 | F5: „Geht es um disclosure – oder darum, dass man die Entscheidung erklären/verstehen kann?“
A6: R05 | B6: (i) Value↔Value | C6: VAL_08 und VAL_09 dürfen nebeneinander codiert werden: Safety/Harm/Misuse = VAL_08; Robustheit/Zuverlässigkeit/Testing = VAL_09. | D6: VAL_08, VAL_09 | E6: C11, C25, C35 | F6: „Steht explizit Schaden/Missbrauch drin – oder nur Robustheit?“
A7: R06 | B7: (i) Value↔Value | C7: Datensatz-Inklusion/Repräsentativität ist nicht automatisch VAL_11; meist primär VAL_05 und/oder VAL_16. | D7: VAL_11, VAL_05, VAL_16 | E7: C16 | F7: „Geht es um Accessibility/Teilhabe – oder um Datenqualität/Fairness?“
A8: R07 | B8: (i) Value↔Value | C8: VAL_14 codiert Rechts-/Standardkonformität; VAL_15 nur ethische Leitplanken, die über bloße Compliance hinausgehen. | D8: VAL_14, VAL_15 | E8: C5, C26 | F8: „Wird hier Recht eingehalten – oder eine eigenständige ethische Grenze gezogen?“
A9: R08 | B9: (i) Value↔Value | C9: Privacy zählt zusätzlich als VAL_18 nur bei explizitem Human-Rights-Framing. | D9: VAL_06, VAL_18 | E9: C12 | F9: „Steht privacy bloß als Datenschutz – oder ausdrücklich als human right?“
A10: R09 | B10: (i) Value↔Value | C10: Dokumentation mit Daten-/Dataset-/Training-/Validation-Bezug zählt zusätzlich als VAL_16; reine Offenlegung bleibt VAL_03. | D10: VAL_03, VAL_16 | E10: C47 | F10: „Dokumentiert der Satz Governance des Daten-/Modellinputs?“
A11: R10 | B11: (ii) Value↔Governance | C11: Verantwortungsprinzip als Norm = VAL_02; benannte Rollen/Einheiten/Approver = GOV_01. Einspruchsrecht = VAL_10; Eskalationsprozess = GOV_06. | D11: VAL_02/GOV_01, VAL_10/GOV_06 | E11: C15, C34, C44 | F11: „Ist das ein normativer Anspruch – oder ein organisatorischer Mechanismus?“
A12: R11 | B12: (iv) Bindigkeit | C12: BIND=2 bei deontischer Regel; BIND=3 nur bei konkretem Prozess-, Check-, Testing-, Dokumentations- oder Kontrollschritt. | D12: alle VAL mit BIND | E12: C1, C8, C18, C31, C38, C44, C46 | F12: „Steht hier nur must/shall – oder auch ein konkreter Vollzugsschritt?“
... A15: R14 | B15: (v) Mehrfachcodierung/Maximalprinzip | C15: Mehrfachcodierung ist zulässig, wenn zwei eigenständige normative Kerne vorliegen; innerhalb eines Codes gilt das höchste belastbar belegte Niveau. | D15: VAL_08/09, VAL_03/16, BIND | E15: C25, C35, C46, C47 | F15: „Beschreibt derselbe Satz zwei wirklich verschiedene Dinge?“

Sheet 03b_Values_Company_Level
A1: company_id | B1: value_id | C1: value_present_company | D1: binding_level_company | E1: value_points_company | F1: doc_id_strongest | G1: evidence_location_strongest
C2: =IF(Tabelle18[[#This Row],[binding_level_company]]>=1,1,0) -> 0 | D2: =_xlfn.MAXIFS(Tabelle5[[#This Row],[binding_level]], Tabelle5[[#This Row],[company_id]],Tabelle18[[#This Row],[company_id]], Tabelle5[[#This Row],[value_id]], Tabelle18[[#This Row],[value_id]], Tabelle5[[#This Row],[value_present]],"1") -> 0 | E2: =_xlfn.MAXIFS(Tabelle5[[#This Row],[value_points]], Tabelle5[[#This Row],[company_id]],Tabelle18[[#This Row],[company_id]], Tabelle5[[#This Row],[value_id]], Tabelle18[[#This Row],[value_id]], Tabelle5[[#This Row],[value_present]],"1") -> 0
C3: =IF(Tabelle18[[#This Row],[binding_level_company]]>=1,1,0) -> 0 | D3: =_xlfn.MAXIFS(Tabelle5[[#This Row],[binding_level]], Tabelle5[[#This Row],[company_id]],Tabelle18[[#This Row],[company_id]], Tabelle5[[#This Row],[value_id]], Tabelle18[[#This Row],[value_id]], Tabelle5[[#This Row],[value_present]],"1") -> 0 | E3: =_xlfn.MAXIFS(Tabelle5[[#This Row],[value_points]], Tabelle5[[#This Row],[company_id]],Tabelle18[[#This Row],[company_id]], Tabelle5[[#This Row],[value_id]], Tabelle18[[#This Row],[value_id]], Tabelle5[[#This Row],[value_present]],"1") -> 0
C4: =IF(Tabelle18[[#This Row],[binding_level_company]]>=1,1,0) -> 0 | D4: =_xlfn.MAXIFS(Tabelle5[[#This Row],[binding_level]], Tabelle5[[#This Row],[company_id]],Tabelle18[[#This Row],[company_id]], Tabelle5[[#This Row],[value_id]], Tabelle18[[#This Row],[value_id]], Tabelle5[[#This Row],[value_present]],"1") -> 0 | E4: =_xlfn.MAXIFS(Tabelle5[[#This Row],[value_points]], Tabelle5[[#This Row],[company_id]],Tabelle18[[#This Row],[company_id]], Tabelle5[[#This Row],[value_id]], Tabelle18[[#This Row],[value_id]], Tabelle5[[#This Row],[value_present]],"1") -> 0
C5: =IF(Tabelle18[[#This Row],[binding_level_company]]>=1,1,0) -> 0 | D5: =_xlfn.MAXIFS(Tabelle5[[#This Row],[binding_level]], Tabelle5[[#This Row],[company_id]],Tabelle18[[#This Row],[company_id]], Tabelle5[[#This Row],[value_id]], Tabelle18[[#This Row],[value_id]], Tabelle5[[#This Row],[value_present]],"1") -> 0 | E5: =_xlfn.MAXIFS(Tabelle5[[#This Row],[value_points]], Tabelle5[[#This Row],[company_id]],Tabelle18[[#This Row],[company_id]], Tabelle5[[#This Row],[value_id]], Tabelle18[[#This Row],[value_id]], Tabelle5[[#This Row],[value_present]],"1") -> 0
C6: =IF(Tabelle18[[#This Row],[binding_level_company]]>=1,1,0) -> 0 | D6: =_xlfn.MAXIFS(Tabelle5[[#This Row],[binding_level]], Tabelle5[[#This Row],[company_id]],Tabelle18[[#This Row],[company_id]], Tabelle5[[#This Row],[value_id]], Tabelle18[[#This Row],[value_id]], Tabelle5[[#This Row],[value_present]],"1") -> 0 | E6: =_xlfn.MAXIFS(Tabelle5[[#This Row],[value_points]], Tabelle5[[#This Row],[company_id]],Tabelle18[[#This Row],[company_id]], Tabelle5[[#This Row],[value_id]], Tabelle18[[#This Row],[value_id]], Tabelle5[[#This Row],[value_present]],"1") -> 0
C7: =IF(Tabelle18[[#This Row],[binding_level_company]]>=1,1,0) -> 0 | D7: =_xlfn.MAXIFS(Tabelle5[[#This Row],[binding_level]], Tabelle5[[#This Row],[company_id]],Tabelle18[[#This Row],[company_id]], Tabelle5[[#This Row],[value_id]], Tabelle18[[#This Row],[value_id]], Tabelle5[[#This Row],[value_present]],"1") -> 0 | E7: =_xlfn.MAXIFS(Tabelle5[[#This Row],[value_points]], Tabelle5[[#This Row],[company_id]],Tabelle18[[#This Row],[company_id]], Tabelle5[[#This Row],[value_id]], Tabelle18[[#This Row],[value_id]], Tabelle5[[#This Row],[value_present]],"1") -> 0
C8: =IF(Tabelle18[[#This Row],[binding_level_company]]>=1,1,0) -> 0 | D8: =_xlfn.MAXIFS(Tabelle5[[#This Row],[binding_level]], Tabelle5[[#This Row],[company_id]],Tabelle18[[#This Row],[company_id]], Tabelle5[[#This Row],[value_id]], Tabelle18[[#This Row],[value_id]], Tabelle5[[#This Row],[value_present]],"1") -> 0 | E8: =_xlfn.MAXIFS(Tabelle5[[#This Row],[value_points]], Tabelle5[[#This Row],[company_id]],Tabelle18[[#This Row],[company_id]], Tabelle5[[#This Row],[value_id]], Tabelle18[[#This Row],[value_id]], Tabelle5[[#This Row],[value_present]],"1") -> 0
C9: =IF(Tabelle18[[#This Row],[binding_level_company]]>=1,1,0) -> 0 | D9: =_xlfn.MAXIFS(Tabelle5[[#This Row],[binding_level]], Tabelle5[[#This Row],[company_id]],Tabelle18[[#This Row],[company_id]], Tabelle5[[#This Row],[value_id]], Tabelle18[[#This Row],[value_id]], Tabelle5[[#This Row],[value_present]],"1") -> 0 | E9: =_xlfn.MAXIFS(Tabelle5[[#This Row],[value_points]], Tabelle5[[#This Row],[company_id]],Tabelle18[[#This Row],[company_id]], Tabelle5[[#This Row],[value_id]], Tabelle18[[#This Row],[value_id]], Tabelle5[[#This Row],[value_present]],"1") -> 0
C10: =IF(Tabelle18[[#This Row],[binding_level_company]]>=1,1,0) -> 0 | D10: =_xlfn.MAXIFS(Tabelle5[[#This Row],[binding_level]], Tabelle5[[#This Row],[company_id]],Tabelle18[[#This Row],[company_id]], Tabelle5[[#This Row],[value_id]], Tabelle18[[#This Row],[value_id]], Tabelle5[[#This Row],[value_present]],"1") -> 0 | E10: =_xlfn.MAXIFS(Tabelle5[[#This Row],[value_points]], Tabelle5[[#This Row],[company_id]],Tabelle18[[#This Row],[company_id]], Tabelle5[[#This Row],[value_id]], Tabelle18[[#This Row],[value_id]], Tabelle5[[#This Row],[value_present]],"1") -> 0
C11: =IF(Tabelle18[[#This Row],[binding_level_company]]>=1,1,0) -> 0 | D11: =_xlfn.MAXIFS(Tabelle5[[#This Row],[binding_level]], Tabelle5[[#This Row],[company_id]],Tabelle18[[#This Row],[company_id]], Tabelle5[[#This Row],[value_id]], Tabelle18[[#This Row],[value_id]], Tabelle5[[#This Row],[value_present]],"1") -> 0 | E11: =_xlfn.MAXIFS(Tabelle5[[#This Row],[value_points]], Tabelle5[[#This Row],[company_id]],Tabelle18[[#This Row],[company_id]], Tabelle5[[#This Row],[value_id]], Tabelle18[[#This Row],[value_id]], Tabelle5[[#This Row],[value_present]],"1") -> 0
C12: =IF(Tabelle18[[#This Row],[binding_level_company]]>=1,1,0) -> 0 | D12: =_xlfn.MAXIFS(Tabelle5[[#This Row],[binding_level]], Tabelle5[[#This Row],[company_id]],Tabelle18[[#This Row],[company_id]], Tabelle5[[#This Row],[value_id]], Tabelle18[[#This Row],[value_id]], Tabelle5[[#This Row],[value_present]],"1") -> 0 | E12: =_xlfn.MAXIFS(Tabelle5[[#This Row],[value_points]], Tabelle5[[#This Row],[company_id]],Tabelle18[[#This Row],[company_id]], Tabelle5[[#This Row],[value_id]], Tabelle18[[#This Row],[value_id]], Tabelle5[[#This Row],[value_present]],"1") -> 0
C13: =IF(Tabelle18[[#This Row],[binding_level_company]]>=1,1,0) -> 0 | D13: =_xlfn.MAXIFS(Tabelle5[[#This Row],[binding_level]], Tabelle5[[#This Row],[company_id]],Tabelle18[[#This Row],[company_id]], Tabelle5[[#This Row],[value_id]], Tabelle18[[#This Row],[value_id]], Tabelle5[[#This Row],[value_present]],"1") -> 0 | E13: =_xlfn.MAXIFS(Tabelle5[[#This Row],[value_points]], Tabelle5[[#This Row],[company_id]],Tabelle18[[#This Row],[company_id]], Tabelle5[[#This Row],[value_id]], Tabelle18[[#This Row],[value_id]], Tabelle5[[#This Row],[value_present]],"1") -> 0
... C41: =IF(Tabelle18[[#This Row],[binding_level_company]]>=1,1,0) -> 0 | D41: =_xlfn.MAXIFS(Tabelle5[[#This Row],[binding_level]], Tabelle5[[#This Row],[company_id]],Tabelle18[[#This Row],[company_id]], Tabelle5[[#This Row],[value_id]], Tabelle18[[#This Row],[value_id]], Tabelle5[[#This Row],[value_present]],"1") -> 0 | E41: =_xlfn.MAXIFS(Tabelle5[[#This Row],[value_points]], Tabelle5[[#This Row],[company_id]],Tabelle18[[#This Row],[company_id]], Tabelle5[[#This Row],[value_id]], Tabelle18[[#This Row],[value_id]], Tabelle5[[#This Row],[value_present]],"1") -> 0

Sheet 05_Governance_Coding
A1: company_id | B1: gov_crit_id | C1: doc_id_primary_evidence | D1: score_0_3 | E1: evidence_quote | F1: evidence_location | G1: why_not_higher | H1: coder_confidence | I1: notes

Sheet 03_Values_Coding
A1: company_id | B1: doc_id | C1: value_id | D1: value_present | E1: binding_level | F1: binding_justification | G1: evidence_quote | H1: evidence_location | I1: coder_confidence | J1: notes | K1: value_points
K2: =Tabelle5[[#This Row],[value_present]]*Tabelle5[[#This Row],[binding_level]] -> 0
K3: =Tabelle5[[#This Row],[value_present]]*Tabelle5[[#This Row],[binding_level]] -> 0
K4: =Tabelle5[[#This Row],[value_present]]*Tabelle5[[#This Row],[binding_level]] -> 0
K5: =Tabelle5[[#This Row],[value_present]]*Tabelle5[[#This Row],[binding_level]] -> 0
K6: =Tabelle5[[#This Row],[value_present]]*Tabelle5[[#This Row],[binding_level]] -> 0
K7: =Tabelle5[[#This Row],[value_present]]*Tabelle5[[#This Row],[binding_level]] -> 0
K8: =Tabelle5[[#This Row],[value_present]]*Tabelle5[[#This Row],[binding_level]] -> 0
K9: =Tabelle5[[#This Row],[value_present]]*Tabelle5[[#This Row],[binding_level]] -> 0
K10: =Tabelle5[[#This Row],[value_present]]*Tabelle5[[#This Row],[binding_level]] -> 0
K11: =Tabelle5[[#This Row],[value_present]]*Tabelle5[[#This Row],[binding_level]] -> 0
K12: =Tabelle5[[#This Row],[value_present]]*Tabelle5[[#This Row],[binding_level]] -> 0
K13: =Tabelle5[[#This Row],[value_present]]*Tabelle5[[#This Row],[binding_level]] -> 0
... K572: =Tabelle5[[#This Row],[value_present]]*Tabelle5[[#This Row],[binding_level]] -> 0

Sheet 04_Governance_Codebook
A1: gov_crit_id | B1: criterion_name | C1: score_0_definition | D1: score_1_definition | E1: score_2_definition | F1: score_3_definition | G1: evidence_minimum | H1: typical_evidence_terms
A2: GOV_01 | B2: Zuständigkeiten | C2: Keine Rollen/Zuständigkeiten genannt | D2: AI-bezogene Rolle, Einheit oder Ownership grob benannt (z. B. AI office, ethics committee, clear accountability/ownership), aber ohne ausdifferenzierte Aufgaben- oder Freigabelogik. | E2: Konkrete Rollen+Aufgaben beschrieben (Owner, Approver, RACI) | F2: Implementiert: Verantwortlichkeiten mit Reporting/Regelterminen/Belegen | G2: Rollentitel + klarer Bezug zu KI/AI-Governance | H2: owner; accountability; committee; board; RACI
A3: GOV_02 | B3: Prozesse | C3: Kein Prozess erwähnt | D3: Prozessabsicht erwähnt (z.B. 'we review AI') | E3: Prozessschritte beschrieben (Lifecycle, Gateways, Freigaben) | F3: Implementiert: Prozess mit Nachweisen (KPIs, regelmäßige Reviews, Prozessdokumente) | G3: Mind. ein Prozessschritt + Trigger + Verantwortliche | H3: AI lifecycle; approval; review; gating; SOP
A4: GOV_03 | B4: Tools/Checks | C4: Keine Checks/Tools | D4: Checks allgemein erwähnt (z.B. 'risk assessment') | E4: Konkreter Check/Mechanismus dokumentiert; der Toolname ist nicht zwingend, wenn Checktyp, Prüfgegenstand und Einsatzzeitpunkt/Anlass erkennbar sind (z. B. representativeness verification, impact assessment, extensive testing, documented monitoring). | F4: Implementiert: Tooling im Betrieb + Pflicht/Protokoll + Ergebnisse berichtet | G4: Name des Tools ODER klar benannter Checktyp/Assessment + Prüfgegenstand + wann/wofür eingesetzt. | H4: bias test; model card; DPIA; validation; monitoring
A5: GOV_04 | B5: Audits | C5: Keine Audits | D5: Audit, Assessment, inspection oder evaluation als Aktivität erwähnt, aber ohne Mechanik/Frequenz/Verantwortliche. Ein bloßes Qualitätsattribut wie "auditable" reicht nicht. | E5: Audit-Mechanik beschrieben (intern/extern, Frequenz) | F5: Implementiert: Auditberichte/KPIs/Review-Zyklen nachweisbar | G5: Auditart + Frequenz oder Verantwortliche | H5: audit; assurance; internal control; external review
A6: GOV_05 | B6: Schulungen | C6: Keine Trainings | D6: Awareness, education oder training ausdrücklich angekündigt, empfohlen oder bereitgestellt; ohne Zielgruppe, Pflichtgrad oder Programmstruktur bleibt Score 1. | E6: Trainingsprogramm beschrieben (Zielgruppe, Inhalte, Pflichtgrad) | F6: Implementiert: Pflichttrainings + Nachweis (Completion, LMS, KPIs) | G6: Mind. Zielgruppe + Pflicht/Regelmäßigkeit | H6: training; awareness; mandatory; LMS; certification
A7: GOV_06 | B7: Eskalationswege | C7: Keine Eskalation | D7: Kontakt/Ansprechpartner genannt | E7: Konkreter Eskalationsprozess beschrieben (Stufen, Fristen) | F7: Implementiert: geübter Prozess/Case-Handling/Reporting | G7: Stufenlogik oder Mechanik (Ticket, Hotline, Committee) | H7: escalation; grievance; hotline; incident; ticket
A8: GOV_07 | B8: Reporting | C8: Kein Reporting | D8: Explizite Reporting-/Disclosure-Absicht zu AI-Risiken, Kontrollen oder Vorfällen erwähnt. Bloße Beratungsempfehlungen an ein Gremium ohne Reportgegenstand zählen nicht. | E8: Reporting-Struktur beschrieben (Was, an wen, wie oft) | F8: Implementiert: regelmäßige Reports/KPIs öffentlich oder intern belegt | G8: KPI/Reportgegenstand + Empfänger + Frequenz | H8: reporting; KPI; dashboard; disclosure; metrics

Sheet 06_Derived_Indices
A1: company_id | B1: sector_cluster | C1: values_raw_points | D1: values_max_points | E1: convergence_index_0_1 | F1: gov_points_sum | G1: gov_index_0_100
C2: =SUMIF(Tabelle18[[#This Row],[value_points_company]],Tabelle5[[#This Row],[company_id]],Tabelle8[[#This Row],[company_id]]) -> 0 | D2: =(COUNTA('02_Values_Codebook'!A:A)-1)*3 -> 54 | E2: =Tabelle8[[#This Row],[values_raw_points]]/Tabelle8[[#This Row],[values_max_points]] -> 0 | F2: =SUMIF(Tabelle7[[#This Row],[score_0_3]],Tabelle7[[#This Row],[company_id]],Tabelle8[[#This Row],[company_id]]) -> 0 | G2: =(Tabelle8[[#This Row],[gov_points_sum]]/21)*100 -> 0
C3: =SUMIF(Tabelle18[[#This Row],[value_points_company]],Tabelle5[[#This Row],[company_id]],Tabelle8[[#This Row],[company_id]]) -> 0 | D3: =(COUNTA('02_Values_Codebook'!A:A)-1)*3 -> 54 | E3: =Tabelle8[[#This Row],[values_raw_points]]/Tabelle8[[#This Row],[values_max_points]] -> 0 | F3: =SUMIF(Tabelle7[[#This Row],[score_0_3]],Tabelle7[[#This Row],[company_id]],Tabelle8[[#This Row],[company_id]]) -> 0 | G3: =(Tabelle8[[#This Row],[gov_points_sum]]/21)*100 -> 0
C4: =SUMIF(Tabelle18[[#This Row],[value_points_company]],Tabelle5[[#This Row],[company_id]],Tabelle8[[#This Row],[company_id]]) -> 0 | D4: =(COUNTA('02_Values_Codebook'!A:A)-1)*3 -> 54 | E4: =Tabelle8[[#This Row],[values_raw_points]]/Tabelle8[[#This Row],[values_max_points]] -> 0 | F4: =SUMIF(Tabelle7[[#This Row],[score_0_3]],Tabelle7[[#This Row],[company_id]],Tabelle8[[#This Row],[company_id]]) -> 0 | G4: =(Tabelle8[[#This Row],[gov_points_sum]]/21)*100 -> 0
C5: =SUMIF(Tabelle18[[#This Row],[value_points_company]],Tabelle5[[#This Row],[company_id]],Tabelle8[[#This Row],[company_id]]) -> 0 | D5: =(COUNTA('02_Values_Codebook'!A:A)-1)*3 -> 54 | E5: =Tabelle8[[#This Row],[values_raw_points]]/Tabelle8[[#This Row],[values_max_points]] -> 0 | F5: =SUMIF(Tabelle7[[#This Row],[score_0_3]],Tabelle7[[#This Row],[company_id]],Tabelle8[[#This Row],[company_id]]) -> 0 | G5: =(Tabelle8[[#This Row],[gov_points_sum]]/21)*100 -> 0
C6: =SUMIF(Tabelle18[[#This Row],[value_points_company]],Tabelle5[[#This Row],[company_id]],Tabelle8[[#This Row],[company_id]]) -> 0 | D6: =(COUNTA('02_Values_Codebook'!A:A)-1)*3 -> 54 | E6: =Tabelle8[[#This Row],[values_raw_points]]/Tabelle8[[#This Row],[values_max_points]] -> 0 | F6: =SUMIF(Tabelle7[[#This Row],[score_0_3]],Tabelle7[[#This Row],[company_id]],Tabelle8[[#This Row],[company_id]]) -> 0 | G6: =(Tabelle8[[#This Row],[gov_points_sum]]/21)*100 -> 0
C7: =SUMIF(Tabelle18[[#This Row],[value_points_company]],Tabelle5[[#This Row],[company_id]],Tabelle8[[#This Row],[company_id]]) -> 0 | D7: =(COUNTA('02_Values_Codebook'!A:A)-1)*3 -> 54 | E7: =Tabelle8[[#This Row],[values_raw_points]]/Tabelle8[[#This Row],[values_max_points]] -> 0 | F7: =SUMIF(Tabelle7[[#This Row],[score_0_3]],Tabelle7[[#This Row],[company_id]],Tabelle8[[#This Row],[company_id]]) -> 0 | G7: =(Tabelle8[[#This Row],[gov_points_sum]]/21)*100 -> 0
C8: =SUMIF(Tabelle18[[#This Row],[value_points_company]],Tabelle5[[#This Row],[company_id]],Tabelle8[[#This Row],[company_id]]) -> 0 | D8: =(COUNTA('02_Values_Codebook'!A:A)-1)*3 -> 54 | E8: =Tabelle8[[#This Row],[values_raw_points]]/Tabelle8[[#This Row],[values_max_points]] -> 0 | F8: =SUMIF(Tabelle7[[#This Row],[score_0_3]],Tabelle7[[#This Row],[company_id]],Tabelle8[[#This Row],[company_id]]) -> 0 | G8: =(Tabelle8[[#This Row],[gov_points_sum]]/21)*100 -> 0
C9: =SUMIF(Tabelle18[[#This Row],[value_points_company]],Tabelle5[[#This Row],[company_id]],Tabelle8[[#This Row],[company_id]]) -> 0 | D9: =(COUNTA('02_Values_Codebook'!A:A)-1)*3 -> 54 | E9: =Tabelle8[[#This Row],[values_raw_points]]/Tabelle8[[#This Row],[values_max_points]] -> 0 | F9: =SUMIF(Tabelle7[[#This Row],[score_0_3]],Tabelle7[[#This Row],[company_id]],Tabelle8[[#This Row],[company_id]]) -> 0 | G9: =(Tabelle8[[#This Row],[gov_points_sum]]/21)*100 -> 0
C10: =SUMIF(Tabelle18[[#This Row],[value_points_company]],Tabelle5[[#This Row],[company_id]],Tabelle8[[#This Row],[company_id]]) -> 0 | D10: =(COUNTA('02_Values_Codebook'!A:A)-1)*3 -> 54 | E10: =Tabelle8[[#This Row],[values_raw_points]]/Tabelle8[[#This Row],[values_max_points]] -> 0 | F10: =SUMIF(Tabelle7[[#This Row],[score_0_3]],Tabelle7[[#This Row],[company_id]],Tabelle8[[#This Row],[company_id]]) -> 0 | G10: =(Tabelle8[[#This Row],[gov_points_sum]]/21)*100 -> 0
C11: =SUMIF(Tabelle18[[#This Row],[value_points_company]],Tabelle5[[#This Row],[company_id]],Tabelle8[[#This Row],[company_id]]) -> 0 | D11: =(COUNTA('02_Values_Codebook'!A:A)-1)*3 -> 54 | E11: =Tabelle8[[#This Row],[values_raw_points]]/Tabelle8[[#This Row],[values_max_points]] -> 0 | F11: =SUMIF(Tabelle7[[#This Row],[score_0_3]],Tabelle7[[#This Row],[company_id]],Tabelle8[[#This Row],[company_id]]) -> 0 | G11: =(Tabelle8[[#This Row],[gov_points_sum]]/21)*100 -> 0
C12: =SUMIF(Tabelle18[[#This Row],[value_points_company]],Tabelle5[[#This Row],[company_id]],Tabelle8[[#This Row],[company_id]]) -> 0 | D12: =(COUNTA('02_Values_Codebook'!A:A)-1)*3 -> 54 | E12: =Tabelle8[[#This Row],[values_raw_points]]/Tabelle8[[#This Row],[values_max_points]] -> 0 | F12: =SUMIF(Tabelle7[[#This Row],[score_0_3]],Tabelle7[[#This Row],[company_id]],Tabelle8[[#This Row],[company_id]]) -> 0 | G12: =(Tabelle8[[#This Row],[gov_points_sum]]/21)*100 -> 0
C13: =SUMIF(Tabelle18[[#This Row],[value_points_company]],Tabelle5[[#This Row],[company_id]],Tabelle8[[#This Row],[company_id]]) -> 0 | D13: =(COUNTA('02_Values_Codebook'!A:A)-1)*3 -> 54 | E13: =Tabelle8[[#This Row],[values_raw_points]]/Tabelle8[[#This Row],[values_max_points]] -> 0 | F13: =SUMIF(Tabelle7[[#This Row],[score_0_3]],Tabelle7[[#This Row],[company_id]],Tabelle8[[#This Row],[company_id]]) -> 0 | G13: =(Tabelle8[[#This Row],[gov_points_sum]]/21)*100 -> 0
... C41: =SUMIF(Tabelle18[[#This Row],[value_points_company]],Tabelle5[[#This Row],[company_id]],Tabelle8[[#This Row],[company_id]]) -> 0 | D41: =(COUNTA('02_Values_Codebook'!A:A)-1)*3 -> 54 | E41: =Tabelle8[[#This Row],[values_raw_points]]/Tabelle8[[#This Row],[values_max_points]] -> 0 | F41: =SUMIF(Tabelle7[[#This Row],[score_0_3]],Tabelle7[[#This Row],[company_id]],Tabelle8[[#This Row],[company_id]]) -> 0 | G41: =(Tabelle8[[#This Row],[gov_points_sum]]/21)*100 -> 0

Sheet 08_Codebook_Changelog
A1: codebook_version | B1: date | C1: change_type(add/modify/remove) | D1: item_id(value_id/gov_crit_id) | E1: what_changed | F1: why_changed | G1: impact_on_previous_coding(recode_needed yes/no)
A2: V0 | B2: 04.01.2026 | C2: Initial Setup
A3: V0.1 | B3: 21.02.2026 | C3: Remove: Document Log Change Columns | E3: Deleted Columns "Version" & "Publishing Date" | F3: Often times hard to acquire -> slows down research progress without adding substandtial information | G3: no
A4: V0.2 | B4: 07.03.2026 | C4: modify | D4: VAL_03 | E4: 02_Values_Codebook → notes_boundary_cases | F4: Trennschärfe aus C7, C27, C47; verhindert Vermischung von disclosure und explanation. | G4: no
A5: V0.2 | B5: 07.03.2026 | C5: modify | D5: VAL_04 | E5: 02_Values_Codebook → include_rules | F5: Direkt aus C7 und C36; schärft Explainability jenseits reiner Terminus-Treue. | G5: no
A6: V0.2 | B6: 07.03.2026 | C6: modify | D6: VAL_08 | E6: 02_Values_Codebook → notes_boundary_cases | F6: C11, C25, C35 zeigen wiederkehrende Doppelcodierungslogik. | G6: no
A7: V0.2 | B7: 07.03.2026 | C7: modify | D7: VAL_09 | E7: 02_Values_Codebook → include_rules | F7: C2, C17, C46: Monitoring darf nur mit Qualitätsanker zu VAL_09 führen. | G7: no
A8: V0.2 | B8: 07.03.2026 | C8: modify | D8: VAL_11 | E8: 02_Values_Codebook → exclude_rules | F8: C16 und C32 machen dieselbe Grenze aus zwei Richtungen sichtbar. | G8: no
A9: V0.2 | B9: 07.03.2026 | C9: modify | D9: VAL_13 | E9: 02_Values_Codebook → include_rules | F9: C40 vs. C45: erlaubt DTE, schließt SAP-Opportunity-Rhetorik aus. | G9: no
A10: V0.2 | B10: 07.03.2026 | C10: modify | D10: VAL_14 | E10: 02_Values_Codebook → notes_boundary_cases | F10: C8, C18, C26 systematisieren BIND-Logik für Compliance. | G10: no
A11: V0.2 | B11: 07.03.2026 | C11: modify | D11: VAL_15 | E11: 02_Values_Codebook → exclude_rules | F11: C5 trennt ethische Leitplanke von reiner Rechtsbindung. | G11: no
A12: V0.2 | B12: 07.03.2026 | C12: modify | D12: VAL_16 | E12: 02_Values_Codebook → include_rules | F12: C10, C38, C47 erweitern VAL_16 belastbar in Richtung Dataset-/Dokumentationsgovernance. | G12: no
A13: V0.2 | B13: 07.03.2026 | C13: modify | D13: VAL_16 | E13: 02_Values_Codebook → exclude_rules | F13: C10/C47 verlangen explizite Grenze zu VAL_03 und zu bloßer Governance-Rhetorik. | G13: no
A14: V0.2 | B14: 07.03.2026 | C14: modify | D14: VAL_18 | E14: 02_Values_Codebook → include_rules | F14: C12 macht die Bedingung explizit. | G14: no
A15: V0.2 | B15: 07.03.2026 | C15: modify | D15: GOV_01 | E15: 04_Governance_Codebook → score_1_definition | F15: C15 und C34 zeigen, dass Score 1 einen AI-Bezug braucht, aber noch keine RACI-Logik. | G15: no
... A20: V0.2 | B20: 07.03.2026 | C20: modify | D20: GOV_07 | E20: 04_Governance_Codebook → score_1_definition | F20: C4 vs. C30 verlangt saubere Trennung zwischen reporting und advisory function. | G20: no
A21: V0.02-V1.0 | B21: 07.03.2026 | C21: FREEZE NACH ERFOLGREICHEM RE-CODING

Sheet 09_Coding_Memos
A1: company_id | B1: overall_notes | C1: key_documents_used | D1: areas_of_uncertainty | E1: follow_up_needed

Sheet 99_Lookups
A1: Sektoren | C1: Dokumententyp | E1: Sprache | G1: Inkludierungsstatus | I1: Ausschlussgrund | K1: Kodierungskonfidenz | M1: Bindigkeitsniveau | O1: Value_present | Q1: Score_0_3
A2: Industrie | C2: AI Principles | E2: DE | G2: Inkludiert | I2: PR ohne normative Substanz | K2: Hoch | M2: 1 | O2: 0 | Q2: 0
A3: Finance | C3: AI Policy | E3: EN | G3: Nicht inkudiert | I3: Keine KI Relevanz | K3: Mittel | M3: 2 | O3: 1 | Q3: 1
A4: Tech | C4: Responsible AI / Ethics | E4: DE/EN | G4: Nicht gefunden | I4: Duplikat / Veraltete Version | K4: Niedrig | M4: 3 | Q4: 2
A5: Health | C5: Code of Conduct | E5: Andere | I5: Paywalled / kein Zugriff | Q5: 3
A6: Consumer | C6: ESG/CSR Report | I6: Zu Vage (keine Kriterien, Regeln)
A7: Utilities | C7: Sustainability Report | I7: Andere
A8: Materials/Chemicals | C8: Annual Report
A9: Other/Hybrid | C9: Website Page
C10: Press Release
C11: Other
