Workbook

Sheet 00_DAX_Master
A1: company_id | B1: company_name_official | C1: brand_short | D1: sector_cluster | E1: industry_detail | F1: hq_country | G1: dax_member_as_of_date | H1: Marktkapitalisierung in Mio. € (Stand: 04.01.2026) | I1: notes_sampling
A2: 1 | B2: Adidas | C2: ADS | D2: Consumer | E2: Sportartikel | F2: Bayern | G2: 22. Juni 1998 | H2: 28070.86 | I2: Trotz intensiver Recherche auf offiziellen Konzernquellen und in Berichten gibt es keine öffentlich zugängliche KI‑Ethik‑ oder Responsible‑AI‑Policy von adidas
A3: 2 | B3: Airbus | C3: AIR | D3: Industrie | E3: Luftfahrt, Raumfahrt, Rüstung | F3: Niederlande | G3: 20. Sep. 2021 | H3: 146046.49 | I3: Keine öffentlichen, dedizierten „Responsible AI Policies“ im Sinne eines separaten Dokuments gefunden; die wichtigsten Aussagen sind in der Human‑rights‑Seite und im Digital‑Ethics‑Kapitel des Verhaltenskodex integriert.
A4: 3 | B4: Allianz | C4: ALV | D4: Finance | E4: Versicherungen | F4: Bayern | G4: 1. Juli 1988 | H4: 138065.08 | I4: Keine dedizierten öffentlichen „Allianz Standard for Responsible AI“‑Dokumente gefunden; der Standard wird nur intern erwähnt.
A5: 4 | B5: BASF | C5: BAS | D5: Materials/Chemicals | E5: Chemie | F5: Rheinland-Pfalz | G5: 1. Juli 1988 | H5: 36934 | I5: Es wurde keine öffentlich zugängliche, eigenständige „Data & AI Policy“ von BASF gefunden. Hinweise auf eine interne Data‑&‑AI‑Policy erscheinen im Responsible‑AI‑Text, sind aber nicht öffentlich abrufbar.
A6: 5 | B6: Bayer | C6: BAYN | D6: Materials/Chemicals | E6: Chemie, Pharma | F6: Nordrhein-Westfalen | G6: 1. Juli 1988 | H6: 33814.35 | I6: Mehrere relevante Dokumente gefunden.
A7: 6 | B7: Beiersdorf | C7: BEI | D7: Consumer | E7: Konsumgüter (Produktion) | F7: Hamburg | G7: 20. Juni 2022 | H7: 19043.54 | I7: Die einzige explizite AI‑Policy‑Aussage stammt aus dem Annual Report 2024. Die Code‑of‑Conduct‑Dokumente und die Human‑Rights‑Policy enthalten relevante Leitplanken zu digitaler Verantwortung, Daten‑ und Menschenrechtsschutz, aber keine spezifischen KI‑Prinzipien
A8: 7 | B8: BMW | C8: BMW | D8: Industrie | E8: Automobil (Produktion) | F8: Bayern | G8: 1. Juli 1988 | H8: 52864.52 | I8: Mehrere relevante Dokumente gefunden.
A9: 8 | B9: Brenntag | C9: BNR | D9: Materials/Chemicals | E9: Chemie (Handel) | F9: Nordrhein-Westfalen | G9: 20. Sep. 2021 | H9: 6654.82 | I9: Es konnten keine spezifischen öffentlichen KI‑Leitlinien oder Responsible‑AI‑Policies von Brenntag SE gefunden werden
A10: 9 | B10: Commerzbank | C10: CBK | D10: Finance | E10: Banken | F10: Hessen | G10: 27. Feb. 2023 | H10: 37853.56 | I10: Die zentrale AI-Quelle ist das Dokument „KI-Grundsätze im Commerzbank-Konzern“
A11: 10 | B11: Continental | C11: CON | D11: Industrie | E11: Automobil (Zulieferer) | F11: Niedersachsen | G11: 24. Sep. 2012 | H11: 12640.94 | I11: Mehrere semi-relevante Dokumente gefunden.
A12: 11 | B12: Daimler Truck | C12: DTG | D12: Industrie | E12: Nutzfahrzeuge (Produktion) | F12: Baden-Württemberg | G12: 21. März 2022 | H12: 25660.46 | I12: Keine eigenständigen, konzernweiten „Responsible AI Policy“ oder „AI Principles“ separat vom Code of Conduct/Integrity Code identifiziert
A13: 12 | B13: Deutsche Bank | C13: DBK | D13: Finance | E13: Banken | F13: Hessen | G13: 1. Juli 1988 | H13: 57682.6 | I13: Die konkretesten AI-Prinzipien lagen öffentlich am klarsten im Supplier Code of Conduct (AI & Data Ethics Principles) sowie Governance-Hinweise (z. B. „AI Oversight Forum“) in ESG/IR-Reports vor; darüber hinaus keine weiteren belastbaren Policy-Dokumente.
... A21: 20 | B21: Hannover Rück | C21: HNR1 | D21: Finance | E21: Versicherungen | F21: Niedersachsen | G21: 21. März 2022 | H21: 29852.05 | I21: Kein eigenständiger Responsible‑AI‑Policy oder explizite AI‑Ethics‑Guideline auf Konzern‑Ebene gefunden.
A22: 21 | B22: Heidelberg Materials | C22: HEI | D22: Materials/Chemicals | E22: Baustoffe | F22: Baden-Württemberg | G22: 21. Juni 2010 | H22: 36922.57
A23: 22 | B23: Henkel | C23: HEN3 | D23: Materials/Chemicals | E23: Konsumgüter, Chemie | F23: Nordrhein-Westfalen | G23: 1. Juli 1988 | H23: 25541.89
A24: 23 | B24: Infineon | C24: IFX | D24: Tech | E24: Halbleiter | F24: Bayern | G24: 21. Sep. 2009 | H24: 45690.61
A25: 24 | B25: Mercedes-Benz Group | C25: MBG | D25: Industrie | E25: Automobil (Produktion) | F25: Baden-Württemberg | G25: 21. Dez. 19981 | H25: 53792.73
A26: 25 | B26: Merck | C26: MRK | D26: Materials/Chemicals | E26: Chemie, Pharma | F26: Hessen | G26: 18. Juni 2007 | H26: 49572.48
A27: 26 | B27: MTU Aero Engines | C27: MTX | D27: Industrie | E27: Luftfahrt | F27: Bayern | G27: 23. Sep. 2019 | H27: 17772.21
A28: 27 | B28: Münchener Rück | C28: MUV2 | D28: Finance | E28: Versicherungen | F28: Bayern | G28: 23. Sep. 1996 | H28: 67763.8
A29: 28 | B29: Porsche Automobil Holding | C29: PAH3 | D29: Industrie | E29: Holding | F29: Baden-Württemberg | G29: 20. Sep. 2021 | H29: 11369.72
A30: 29 | B30: Qiagen | C30: QIA | D30: Tech | E30: Biotechnologie | F30: Niederlande | G30: 20. Sep. 2021 | H30: 7781.46
A31: 30 | B31: Rheinmetall | C31: RHM | D31: Industrie | E31: Wehrtechnik, Automobil (Zulieferer) | F31: Nordrhein-Westfalen | G31: 20. März 2023 | H31: 66606.82
A32: 31 | B32: RWE | C32: RWE | D32: Utilities | E32: Energie (Versorgung) | F32: Nordrhein-Westfalen | G32: 1. Juli 1988 | H32: 30562.07
A33: 32 | B33: SAP | C33: SAP | D33: Tech | E33: Software | F33: Baden-Württemberg | G33: 18. Sep. 1995 | H33: 220619.35
... A41: 40 | B41: Zalando | C41: ZAL | D41: Consumer | E41: Versandhandel (Mode) | F41: Berlin | G41: 20. Sep. 2021 | H41: 6113.98

Sheet 01_Document_Log
A1: doc_id | B1: company_id | C1: doc_title | D1: doc_type | E1: publisher | F1: publication_date | G1: version | H1: language | I1: url | J1: access_date | K1: file_name_local | L1: inclusion_status | M1: exclusion_reason | N1: relevance_notes
A2: 1 | B2: 1 | C2: Fair Play Code of Conduct | D2: Code of Conduct | E2: adidas AG | F2: n.n. | G2: n.n. | H2: EN | I2: https://www.adidas-group.com/en/investors/corporate-governance/adidas-fair-play-code-of-conduct | J2: 16.02.2026 | K2: 001_01_FairPlayCode_1602026.pdf | L2: Nicht inkudiert | M2: Keine KI Relevanz | N2: Stellt umfassend die ethischen Erwartungen an alle adidas‑Mitarbeitenden dar (Antikorruption, Datenschutz, Verhalten), enthält Governance‑Mechanismen wie Schulungen und Berichtswege. Trotz fehlendem KI‑Bezug ist es das stärkste normative Dokument.
A3: 2 | B3: 1 | C3: Compliance Policy | D3: Code of Conduct | E3: adidas AG | F3: n.n. | G3: n.n. | H3: EN | I3: https://www.adidas-group.com/en/investors/corporate-governance/adidas-fair-play-code-of-conduct | J3: 16.02.2026 | K3: 002_01_compliance_policy_160226.pdf | L3: Nicht inkudiert | M3: Keine KI Relevanz | N3: Erläutert konkret die Regeln zu Bestechung, Geschenken, Betrug, Wettbewerbsrecht und Interessenkonflikten sowie die Pflichten und Verfahren bei Verstößen. Wichtiges Governance‑Rahmenwerk, obwohl keine KI‑Themen adressiert werden.
A4: 3 | B4: 1 | C4: Human Rights Policy | D4: Other | E4: adidas AG | F4: 01.02.2024 | G4: n.n. | H4: EN | I4: https://www.adidas-group.com/en/sustainability/transparency/policies | J4: 16.02.2026 | K4: 003_01_Human_Rights_Policy_160226.pdf | L4: Nicht inkudiert | M4: Keine KI Relevanz | N4: Verankert adidas’ Verpflichtung zu internationalen Menschenrechtsstandards und beschreibt Due‑Diligence‑Prozesse zur Identifizierung und Vermeidung negativer Auswirkungen. Relevante Werte wie Fairness, Gleichheit und Schutz vulnerabler Gruppen können später als Kontext für KI‑Ethik dienen.
A5: 4 | B5: 1 | C5: ETHICAL COMMUNICATION GUIDELINES | D5: Code of Conduct | E5: Adidas Foundation | F5: n.n. | G5: n.n. | H5: EN | I5: https://www.adidasfoundation.org/about/policies-and-guidelines | J5: 16.02.2026 | K5: 004_01_Ethical_comms_guide_160226.pdf | L5: Nicht inkudiert | M5: Keine KI Relevanz
A6: 5 | B6: 1 | C6: Safeguarding Policy | D6: Code of Conduct | E6: Adidas Foundation | F6: n.n. | G6: n.n. | H6: EN | I6: https://www.adidasfoundation.org/about/policies-and-guidelines | J6: 16.02.2026 | K6: 005_SafeguardingPolicy_160226.pdf | L6: Nicht inkudiert | M6: Keine KI Relevanz
A7: 6 | B7: 1 | C7: Supervisory Board Report 2024 | D7: Annual Report | E7: Adidas Group | F7: 01.03.2025 | G7: n.n. | H7: EN | I7: https://report.adidas-group.com/2024/en/to-our-shareholders/supervisory-board-report.html | J7: 16.02.2026 | K7: 006_01_Supervisory_Report_2024_160226.pdf | L7: Nicht inkudiert | M7: Keine KI Relevanz
A8: 7 | B8: 1 | C8: Integrated Management System Global Policy | D8: Sustainability Report | E8: Adidas AG | F8: 01.01.2026 | G8: n.n. | H8: EN | I8: https://www.adidas-group.com/de/nachhaltigkeit/transparenz/richtlinien?tag=Eigene+Standorte | J8: 16.02.2026 | K8: 007_01_IMSGP_160226.pdf | L8: Nicht inkudiert | M8: Keine KI Relevanz
B9: 1 | D9: AI Principles | E9: Adidas AG | L9: Nicht gefunden | N9: No public AI/Responsible AI guideline, policy or principles found (as of 2026‑02‑16)
B10: 1 | D10: AI Policy | E10: Adidas AG | L10: Nicht gefunden | N10: No public AI/Responsible AI guideline, policy or principles found (as of 2026‑02‑16)
B11: 1 | D11: Responsible AI / Ethics | E11: Adidas AG | L11: Nicht gefunden | N11: No public AI/Responsible AI guideline, policy or principles found (as of 2026‑02‑16)
A12: 8 | B12: 2 | C12: Our approach to Artificial Intelligence (AI) | D12: AI Policy | E12: Airbus SE | F12: n.n. | G12: n.n. | H12: EN | I12: https://www.airbus.com/en/sustainability-draft/our-approach-to-sustainability/human-rights | J12: 16.02.2026 | K12: 008_02_AI_Approach_160226 | L12: Inkludiert
A13: 9 | B13: 2 | C13: Airbus Code of Conduct – 2025 Edition | D13: Code of Conduct | E13: Airbus SE | F13: n.n. | G13: n.n. | H13: EN | I13: https://www.airbus.com/sites/g/files/jlcbta136/files/2025-04/2025-Airbus-Code-of-Conduct-EN.pdf | J13: 16.02.2026 | K13: 009_02_Code-of-Conduct_160226.pdf | L13: Inkludiert
A14: 10 | B14: 2 | C14: Airbus Supplier Code of Conduct | D14: Code of Conduct | E14: Airbus SE | F14: n.n. | G14: n.n. | H14: EN | I14: https://www.airbus.com/sites/g/files/jlcbta136/files/2021-07/Airbus-Supplier-Code-of-Conduct.pdf | J14: 16.02.2026 | K14: 010_02_Supplier-Code-of-Conduct_160226.pdf | L14: Nicht inkudiert | M14: Keine KI Relevanz
A15: 11 | B15: 2 | C15: Airbus Ethics & Compliance Anti‑Corruption Policy | D15: Other | E15: Airbus SE | F15: n.n. | G15: n.n. | H15: EN | I15: https://www.airbus.com/sites/g/files/jlcbta136/files/2021-10/Airbus-Ethics-and-Compliance-Anti-Corruption-Policy.pdf | J15: 16.02.2026 | K15: 011_02_Ethics-and-Compliance-Anti-Corruption-Policy_160226.pdf | L15: Nicht inkudiert | M15: Keine KI Relevanz
A16: 12 | B16: 2 | C16: Pioneering sustainable aerospace (Sustainability publication 2025) | D16: Sustainability Report | E16: Airbus SE | F16: 2025 | G16: n.n. | H16: EN | I16: https://www.airbus.com/sites/g/files/jlcbta136/files/2025-04/2025_Airbus_Pioneering_sustainable_aerospace_publication.pdf | J16: 16.02.2026 | K16: 012_02_Pioneering_sustainable_aerospace_publication_160226.pdf | L16: Nicht inkudiert | M16: Keine KI Relevanz
A17: 13 | B17: 2 | C17: Airbus Summit 2025 – Harnessing the power of responsible AI | D17: Press Release | E17: Airbus SE | F17: 25.03.2025 | G17: n.n. | H17: EN | I17: https://www.airbus.com/en/airbus-summit-2025/harnessing-the-power-of-responsible-ai | J17: 16.02.2026 | K17: 013_02_Harnessing the power of responsible AI _160226pdf | L17: Nicht inkudiert | M17: PR ohne normative Substanz
A18: 14 | B18: 2 | C18: Information Notice of the 2025 Annual General Meeting | D18: Annual Report | E18: Airbus SE | F18: 15.04.2025 | G18: n.n. | I18: https://www.airbus.com/sites/g/files/jlcbta136/files/2025-03/information_notice.pdf | J18: 16.02.2026 | K18: 014_02_Annual_General_Meeting_2025_160226.pdf | L18: Nicht inkudiert | M18: Keine KI Relevanz
A19: 15 | B19: 2 | C19: Artificial Intelligence | D19: Website Page | E19: Airbus SE | F19: n.n. | G19: n.n. | H19: EN | I19: https://www.airbus.com/en/innovation/digital-transformation/artificial-intelligence | J19: 16.02.2026 | K19: 015_02_AI_Website_160226 | L19: Nicht inkudiert | M19: PR ohne normative Substanz | N19: Kein Bezug zur KI Ethikrichtlinien; beschreibt nur technischen/ wirtschaftlichen Einsatz von KI
B20: 2 | D20: AI Principles | E20: Airbus SE | L20: Nicht gefunden | N20: No public AI/Responsible AI guideline or principles found (as of 2026‑02‑16)
B21: 2 | D21: Responsible AI / Ethics | E21: Airbus SE | L21: Nicht gefunden | N21: No public AI/Responsible AI guideline or principles found (as of 2026‑02‑16)
A22: 16 | B22: 3 | C22: Responsible Use of Artificial Intelligence (AI) | D22: Responsible AI / Ethics | E22: Allianz SE | F22: n.n. | G22: n.n. | H22: EN | I22: https://www.allianz.com/en/about-us/strategy-values/responsible-use-of-artificial-intelligence.html | J22: 16.02.2026 | K22: 016_03_Responsible Use of Artificial Intelligence_160226.pdf | L22: Inkludiert
A23: 17 | B23: 3 | C23: Allianz Code of Conduct | D23: Code of Conduct | E23: Allianz SE | F23: 2025 | G23: n.n. | H23: EN | I23: https://www.allianz.com/content/dam/onemarketing/azcom/Allianz_com/about-us/strategy-values/compliance/code-of-conduct/code-of-conduct-accessible.pdf | J23: 16.02.2026 | K23: 017_03_code-of-conduct_160226.pdf | L23: Inkludiert
A24: 18 | B24: 3 | C24: Privacy Statement – Data Ethics section | D24: Other | E24: Allianz SE | F24: 2025 | G24: n.n. | H24: EN | I24: https://www.allianz.com/en/privacy-statement.html | J24: 16.02.2026 | K24: 018_03_Privacy Statement_160226.pdf | L24: Inkludiert
A25: 19 | B25: 3 | C25: Allianz Privacy Standard – Public Version | D25: Other | E25: Allianz SE | F25: 43221 | G25: 1.0 | H25: EN | I25: https://www.allianzgloballife.com/content/dam/onemarketing/azgl/allianzgloballife/doc/31122019/en_gb/Allianz-Privacy-Standard_PUBLIC_EN.pdf | J25: 16.02.2026 | K25: 019_03_Privacy-Standard_PUBLIC_EN_160226.pdf | L25: Nicht inkudiert | M25: Duplikat / Veraltete Version
A26: 20 | B26: 3 | C26: Allianz Group Sustainability Report 2023 – Data ethics/AI governance sections | D26: Sustainability Report | E26: Allianz SE | F26: 2023 | G26: n.n. | H26: EN | I26: https://www.allianz.com/content/dam/onemarketing/azcom/Allianz_com/sustainability/documents/Allianz_Group_Sustainability_Report_2023-web.pdf | J26: 16.02.2026 | K26: 020_03_Sustainability_Report_2023_160226.pdf | L26: Nicht inkudiert | M26: Duplikat / Veraltete Version
A27: 21 | B27: 3 | C27: Responsible AI: a sustainable approach to transformative technology | D27: Responsible AI / Ethics | E27: Allianz Global Investors (subsidiary) | F27: n.n. | G27: n.n. | H27: EN | I27: https://www.allianzgi.com/documents/Responsible-AI-a-sustainable-approach-to-transformative-technology | J27: 16.02.2026 | K27: 021_03_Responsible_AI_160226.pdf | L27: Inkludiert | N27: Tochtergesellschaft der Allianz SE
B28: 3 | D28: AI Principles | E28: Allianz SE | L28: Nicht gefunden | N28: No public AI policy or principles found (as of 2026‑02‑16)
B29: 3 | D29: AI Policy | E29: Allianz SE | L29: Nicht gefunden | N29: No public AI policy or principles found (as of 2026‑02‑16)
A30: 22 | B30: 4 | C30: Responsible AI at BASF | D30: Responsible AI / Ethics | E30: BASF SE | F30: n.n. | G30: n.n. | H30: EN | I30: https://www.basf.com/global/en/who-we-are/digitalization/artificial-intelligence/Responsible-AI-at-BASF | J30: 16.02.2026 | K30: 022_04_Responsible_AI_160226.pdf | L30: Inkludiert
A31: 23 | B31: 4 | C31: BASF Code of Conduct | D31: Code of Conduct | E31: BASF SE | F31: n.n. | G31: n.n. | H31: EN | I31: https://www.basf.com/dam/jcr:0304db1d-bcbb-3015-a965-62627c1b61d2/basf/www/global/documents/en/investor-relations/calendar-and-publications/reports/2025/BASF_Code-of-Conduct.pdf | J31: 16.02.2026 | K31: 023_04_Code-of-Conduct_160226.pdf | L31: Inkludiert
A32: 24 | B32: 4 | C32: Data protection @ BASF – Data processing in the BASF Group | D32: Other | E32: BASF SE | F32: n.n. | G32: n.n. | H32: EN | I32: https://www.basf.com/global/en/legal/data-protection-at-basf | J32: 16.02.2026 | K32: 024_04_Data protection_160226.pdf | L32: Inkludiert
A33: 25 | B33: 4 | C33: BASF Group’s Policy Statement on Human Rights | D33: Other | E33: BASF SE | F33: n.n. | G33: n.n. | H33: EN | I33: https://www.basf.com/dam/jcr:4944a24f-defc-4987-9dd6-d38dba24efd9/basf/www/global/documents/en/sustainability/we-value-people-and-treat-them-with-respect/human-rights/Human-Rights-Policy-Statement-BASF-Group.pdf | J33: 16.02.2026 | K33: 025_04_Human-Rights-Policy-Statement_160226.pdf | L33: Nicht inkudiert | M33: Keine KI Relevanz
A34: 26 | B34: 4 | C34: Supplier Code of Conduct (Version 2024) | D34: Code of Conduct | E34: BASF SE | F34: 45474 | G34: n.n. | H34: EN | I34: https://www.basf.com/dam/jcr:83c0af8a-4e46-37c0-945f-3fd15ff4fca3/basf/www/global/documents/en/about-us/suppliers-and-partners/supplier-code-of-conduct/Supplier_Code_of_conduct_Version%202024%20-%20English.pdf | J34: 16.02.2026 | K34: 025_04_Supplier_Code_of_conduct_160226.pdf | L34: Nicht inkudiert | M34: Keine KI Relevanz
B35: 4 | D35: AI Principles | E35: BASF SE | L35: Nicht gefunden | N35: No public AI policy or principles found (as of 2026‑02‑16)
B36: 4 | D36: AI Policy | E36: BASF SE | L36: Nicht gefunden | N36: No public AI policy or principles found (as of 2026‑02‑16)
A37: 27 | B37: 5 | C37: Bioethical Principles – AI in the context of human healthcare | D37: AI Principles | E37: Bayer AG | F37: n.n. | G37: n.n. | H37: EN | I37: https://www.bayer.com/en/sustainability/bioethical-principles | J37: 16.02.2026 | K37: 027_05_Bioethical Principles_160226.pdf | L37: Inkludiert
A38: 28 | B38: 5 | C38: Generative Artificial Intelligence (GenAI) Guidance and Rules – version 3 | D38: AI Policy | E38: Bayer AG | F38: 17.10.2024 | G38: V3 | H38: EN | I38: https://idnet.bayer.com/sites/idnet/files/final-en-genai-guidelines-and-rules-v3.pdf | J38: 16.02.2026 | K38: 028_05_genai-guidelines_160226.pdf | L38: Inkludiert
A39: 29 | B39: 5 | C39: Our Code of Conduct – Responsible use of Artificial Intelligence section | D39: Code of Conduct | E39: Bayer AG | F39: n.n. | G39: n.n. | H39: EN | I39: https://www.bayer.com/en/commitments/code-of-conduct | J39: 16.02.2026 | K39: 029_05_Code of Conduct_160226.pdf | L39: Inkludiert
A40: 30 | B40: 5 | C40: Unleashing the Potential of AI – AI Ethics and Responsibility section | D40: Responsible AI / Ethics | E40: Bayer AG | F40: n.n. | G40: n.n. | H40: EN | I40: https://www.bayer.com/en/innovation/unleashing-the-potential-of-ai | J40: 16.02.2026 | K40: 030_05_Unleashing the Potential of AI_160226.pdf | L40: Inkludiert
A41: 31 | B41: 5 | C41: Bioethics Council: Responsible innovation with ethical AI | D41: Other | E41: Bayer AG | F41: 45261 | G41: n.n. | H41: EN | I41: https://www.bayer.com/sites/default/files/interview-bioethics-council-meeting-ethics-of-generative-ai-2023.pdf | J41: 16.02.2026 | K41: 31_05_interview-bioethics-council-meeting_160226.pdf | L41: Inkludiert | N41: Interview
A42: 32 | B42: 6 | C42: Beiersdorf Code of Conduct 2024 | D42: Code of Conduct | E42: Beiersdorf AG | F42: 2024 | G42: n.n. | H42: EN | I42: https://www.beiersdorf.com/-/media/Beiersdorf/landingpages/code-of-conduct/Beiersdorf-Code-of-Conduct-2024-EN.pdf | J42: 16.02.2026 | K42: 032_06_Code-of-Conduct_160226.pdf | L42: Inkludiert
A43: 33 | B43: 6 | C43: Declaration of Principles on Upholding Human Rights | D43: ESG/CSR Report | E43: Beiersdorf AG | F43: 2023 | G43: n.n. | H43: EN | I43: https://www.beiersdorf.com/-/media/Beiersdorf/stories/news-and-stories/news/BW_Declaration_of_Principles_on_Upholding_Human_Rights.pdf | J43: 16.02.2026 | K43: 033_06_Declaration of Principles on Upholding Human Rights_160226.pdf | L43: Nicht inkudiert | M43: Keine KI Relevanz
A44: 34 | B44: 6 | C44: Beiersdorf Annual Report 2024 (Combined Management Report – digitalisation and AI section) | D44: Annual Report | E44: Beiersdorf AG | F44: 2024 | G44: n.n. | H44: EN | I44: https://www.beiersdorf.com/~/media/Beiersdorf/investors/financial-publication/2025/annual-report/Beiersdorf-Annual-Report-2024.pdf | J44: 16.02.2026 | K44: 034_06_Annual-Report-2024_160226.pdf | L44: Inkludiert
A45: 36 | B45: 6 | C45: Beiersdorf driving AI innovations – interview with Dirk Ploss (Hamburg News) | D45: Other | E45: Beiersdorf AG | F45: 12.02.2025 | G45: n.n. | H45: EN | I45: https://hamburg-business.com/en/news/beiersdorf-driving-ai-innovations | J45: 16.02.2026 | K45: 035_06_Hamburg Business_120626.pdf | L45: Inkludiert | N45: Interview
B46: 6 | D46: AI Principles | E46: Beiersdorf AG | L46: Nicht gefunden | N46: No public AI/Responsible AI guideline, policy or principles found (as of 2026‑02‑16)
B47: 6 | D47: AI Policy | E47: Beiersdorf AG | L47: Nicht gefunden | N47: No public AI/Responsible AI guideline, policy or principles found (as of 2026‑02‑16)
B48: 6 | D48: Responsible AI / Ethics | E48: Beiersdorf AG | L48: Nicht gefunden | N48: No public AI/Responsible AI guideline, policy or principles found (as of 2026‑02‑16)
A49: 37 | B49: 7 | C49: BMW Group code of ethics for artificial intelligence | D49: AI Principles | E49: BMW Group | F49: 12.10.2020 | G49: n.n. | H49: EN | I49: https://www.press.bmwgroup.com/global/article/detail/T0318411EN/seven-principles-for-ai:-bmw-group-sets-out-code-of-ethics-for-the-use-of-artificial-intelligence?language=en | J49: 16.02.2026 | K49: 037_07_Code_of_ethics_for_AI_160226.PDF | L49: Inkludiert
A50: 38 | B50: 7 | C50: BMW Group digital identity: Five guiding principles for dealing with digital technology | D50: Responsible AI / Ethics | E50: BMW Group | F50: Juni 2024 | G50: n.n. | H50: EN | I50: https://www.bmwgroup.com/content/dam/grpw/websites/bmwgroup_com/innovation/downloadds/en/2024/Digitales_Selbstverstaendnis_EN.pdf | J50: 16.02.2026 | K50: 038_07_Digitales_Selbstverstaendnis_160226.pdf | L50: Inkludiert
A51: 39 | B51: 7 | C51: We Are Compliance – BMW Group Code of Conduct (2025 edition) | D51: Code of Conduct | E51: BMW Group | F51: Dezember 2025 | G51: n.n. | H51: EN | I51: https://www.bmwgroup.com/content/dam/grpw/websites/bmwgroup_com/company/downloads/en/2025/BMW_Group_Compliance_Code_of_Conduct_EN.pdf | J51: 16.02.2026 | K51: 039_07_Compliance_Code_of_Conduct_160226.pdf | L51: Nicht inkudiert | M51: Keine KI Relevanz
A52: 40 | B52: 7 | C52: BMW Group Report 2024 – Sustainability Statement (selected sections) | D52: Code of Conduct | E52: BMW Group | F52: Dezember 2025 | G52: n.n. | H52: EN | I52: https://www.bmwgroup-werke.com/content/dam/grpw/websites/bmwgroup_com/company/downloads/en/2025/BMW_Group_Compliance_HumanRights_Code_EN.pdf | J52: 16.02.2026 | K52: 040_07_Compliance_HumanRights_Code_160226.pdf | L52: Nicht inkudiert | M52: Keine KI Relevanz
A53: 41 | B53: 7 | C53: BMW Group Code on Human Rights and Working Conditions (2025) | D53: ESG/CSR Report | E53: BMW Group | F53: n.n. | G53: n.n. | H53: EN | I53: https://www.bmwgroup.com/en/report/2024/downloads/BMW-Group-Report-2024-en.pdf | J53: 16.02.2026 | K53: 041_07_ESG-Report-2024_160226.pdf | L53: Nicht inkudiert | M53: Keine KI Relevanz
B54: 7 | D54: AI Policy | E54: BMW Group | L54: Nicht gefunden | N54: No public AI policy found (as of 2026‑02‑16)
A55: 42 | B55: 8 | C55: Code of Business Conduct and Ethics | D55: Code of Conduct | E55: Brenntag SE | F55: 2024 | G55: n.n. | H55: EN | I55: https://brenntagprod-media.e-spirit.cloud/06432017-be1f-41ce-8d1d-564e2a66d213/documents/global/compliance/brenntag_code-of-conduct_en.pdf | J55: 17.02.2026 | K55: 042_08_code-of-conduct_170226.pdf | L55: Nicht inkudiert | M55: Keine KI Relevanz | N55: Obwohl keine KI‑spezifischen Prinzipien erwähnt werden, legt der Verhaltenskodex den ethischen Rahmen und die organisatorischen Mechanismen (Compliance‑Management, Trainings, Whistleblowing) fest, die auch für KI‑Governance relevant sind.
A56: 43 | B56: 8 | C56: Supplier Code of Conduct | D56: Code of Conduct | E56: Brenntag SE | F56: 2023 | G56: n.n. | H56: EN | I56: https://brenntagprod-media.e-spirit.cloud/06432017-be1f-41ce-8d1d-564e2a66d213/documents/global/compliance/global_brenntag-supplier-code-of-conduct-2023_en.pdf | J56: 17.02.2026 | K56: 043_08_supplier-code-of-conduct_170226.pdf | L56: Nicht inkudiert | M56: Keine KI Relevanz | N56: Die Richtlinie ist zwar nicht KI‑spezifisch, bildet aber einen wichtigen Governance‑Baustein für verantwortungsvolle Beschaffung und könnte im Kontext von Datenlieferanten und KI‑Systemen relevant sein.
A57: 44 | B57: 8 | C57: Group Sustainability Statement (FY 2024) | D57: Sustainability Report | E57: Brenntag SE | F57: n.n. | G57: n.n. | H57: EN | I57: https://brenntagprod-media.e-spirit.cloud/06432017-be1f-41ce-8d1d-564e2a66d213/documents/corporate/investor-relations/2024/annual-report-2024/brenntag_ar2024_group-sustainability-statement_en.pdf | J57: 17.02.2026 | K57: 044_08_sustainability-statement_170226.pdf | L57: Nicht inkudiert | M57: Keine KI Relevanz | N57: Obwohl keine expliziten AI‑Richtlinien vorhanden sind, liefert der Bericht Kontext zu Compliance, Datenschutz und Business‑Conduct‑Strategien, die als Umfeld für KI‑Regeln dienen können.
A58: 45 | B58: 8 | C58: Press Release: “Brenntag implements autonomous AI agents on its Salesforce platform as first customer in Germany” | D58: Press Release | E58: Brenntag SE | F58: 05.11.2024 | G58: n.n. | H58: EN | I58: https://corporate.brenntag.com/en/media/news/brenntag-implements-autonomous-ai-agents-on-its-salesforce-platform-as-first-customer-in-germany.html | J58: 17.02.2026 | K58: 045_08_Salesforce_Brenntag_170226.pdf | L58: Nicht inkudiert | M58: PR ohne normative Substanz
B59: 8 | D59: AI Principles | E59: Brenntag SE | L59: Nicht gefunden | N59: No public AI/Responsible AI guideline, policy or principles found (as of 2026‑02‑17)
B60: 8 | D60: AI Policy | E60: Brenntag SE | L60: Nicht gefunden | N60: No public AI/Responsible AI guideline, policy or principles found (as of 2026‑02‑17)
B61: 8 | D61: Responsible AI / Ethics | E61: Brenntag SE | L61: Nicht gefunden | N61: No public AI/Responsible AI guideline, policy or principles found (as of 2026‑02‑17)
A62: 46 | B62: 9 | C62: „KI‑Grundsätze im Commerzbank‑Konzern“ (Artificial Intelligence Principles) | D62: AI Principles | E62: Commerzbank AG | F62: 19.10.2023 | G62: n.n | H62: DE/EN | I62: https://www.commerzbank.de/group/what-moves-us/2024-article-media/24-03/ki-grundsaetze.pdf | J62: 17.02.2026 | K62: 046_09_ki-grundsaetze_170226.pdf | L62: Inkludiert | N62: Also includes Responsible AI / Ethics
A63: 47 | B63: 9 | C63: Artikel „AI principles – principle agreement will strengthen trust in AI“ | D63: Press Release | E63: Commerzbank AG | F63: 08.05.2025 | G63: n.n. | H63: DE/EN | I63: https://www.commerzbank.de/group/what-drives-us/innovation-digital-transformation/2024-ai-principles.html | J63: 17.02.2026 | K63: 047_09_Principle agreement_170226.pdf | L63: Nicht inkudiert | M63: PR ohne normative Substanz
A64: 48 | B64: 9 | C64: Whitepaper „Risk‑based approach to AI and Machine Learning“ | D64: AI Policy | E64: Commerzbank AG | F64: 15.03.2023 | G64: n.n | H64: DE/EN | I64: https://www.commerzbank.de/group/newsroom/publications/2023/position-paper-ai-act.pdf | J64: 17.02.2026 | K64: 048_09_whitepaper-ai-act_170226.pdf | L64: Inkludiert
A65: 49 | B65: 9 | C65: Code of Conduct („Yellow Compass“) – Version 2024 | D65: Code of Conduct | E65: Commerzbank AG | F65: 2024 | G65: V2024 | H65: DE/EN | I65: https://core-p-001.sitecorecontenthub.cloud/api/public/content/8008521917234a78a40d4f10b91c2806?v=c4b71f08 | J65: 17.02.2026 | K65: 049_09_Code of Conduct_170226.pdf | L65: Nicht inkudiert | M65: Keine KI Relevanz
A66: 50 | B66: 9 | C66: ESG Framework – Acting responsibly, growing sustainably | D66: ESG/CSR Report | E66: Commerzbank AG | F66: n.n. | G66: n.n. | H66: EN | I66: https://www.commerzbank.de/ms/documents/en/esg-framework-pdf.pdf | J66: 17.02.2026 | K66: 050_09_esg-framework_170226.pdf | L66: Nicht inkudiert | M66: Keine KI Relevanz
A67: 51 | B67: 10 | C67: Ethics regulations for artificial intelligence (press release) | D67: Press Release | E67: Continental AG | F67: 08.06.2020 | G67: n.n. | H67: EN | I67: https://www.continental.com/en/press/press-releases/ai-code-of-ethics/ | J67: 17.02.2026 | K67: 051_10_Ethics Regulations for Artificial Intelligence_170226.pdf | L67: Nicht inkudiert | M67: PR ohne normative Substanz
A68: 52 | B68: 10 | C68: Continental Code of Conduct | D68: Code of Conduct | E68: Continental AG | F68: 46023 | G68: Version 01/01/2026 | H68: EN | I68: https://cdn.continental.com/fileadmin/__imported/sites/corporate/_international/english/hubpages/60_20company/20_20corporate_20governance/50_20compliance/coc_en.pdf | J68: 17.02.2026 | K68: 052_10_coc_170226.pdf | L68: Inkludiert
A69: 53 | B69: 10 | C69: Continental Business Partner Code of Conduct | D69: Code of Conduct | E69: Continental AG | F69: n.n. | G69: Veersion Juli 2023 | H69: EN | I69: https://cdn.continental.com/fileadmin/__imported/sites/corporate/_international/german/hubpages/60_20unternehmen/20_20corporate_20governance/50_20compliance/brochure_bpcoc_en_with_signature.pdf | J69: 17.02.2026 | K69: 053_10_bpcoc_170226.pdf | L69: Inkludiert | N69: Hat eine kleine AI Sektion
A70: 54 | B70: 10 | C70: Survey: Germans fear job losses due to artificial intelligence (press release) | D70: Press Release | E70: Continental AG | F70: 28.03.2023 | G70: n.n. | H70: EN | I70: https://www.continental.com/en/press/press-releases/germans-fear-job-losses-due-to-artificial-intelligence/ | J70: 17.02.2026 | K70: 054_10_Survey_170226.pdf | L70: Nicht inkudiert | M70: PR ohne normative Substanz
A71: 55 | B71: 10 | C71: Turn Change Into Opportunity – Embrace Sustainability: Integrated Sustainability Report 2022 | D71: Sustainability Report | E71: Continental AG | F71: 2022 | G71: n.n. | H71: EN | I71: https://www.continental.com/fileadmin/__imported/sites/corporate/_international/german/hubpages/10_20presse/studien_und_publikationen/continental_sustainability_report_2022.pdf | J71: 17.02.2026 | K71: 055_10_sustainability_report_170226.pdf | L71: Nicht inkudiert | M71: Duplikat / Veraltete Version | N71: Referenzieren nur die AI Code of Ethics, aber geben selbst keine Inhalte über die Themen des CoE hinaus wieder: › Compliance with laws, regulations, Continental’s rules, standards and instructions › Workplace and fair working conditions › Health, safety, the environment, and product integrity › Employee diversity, anti-discrimination, fairness in the use of AI › Data protection and cybersecurity when using AI › Confidential information, intellectual property
B72: 10 | D72: AI Principles | E72: Continental AG | L72: Nicht gefunden | N72: No public AI/Responsible AI guideline, policy or principles found (as of 2026‑02‑17)
B73: 10 | D73: AI Policy | E73: Continental AG | L73: Nicht gefunden | N73: No public AI/Responsible AI guideline, policy or principles found (as of 2026‑02‑17)
B74: 10 | D74: Responsible AI / Ethics | E74: Continental AG | L74: Nicht gefunden | N74: No public AI/Responsible AI guideline, policy or principles found (as of 2026‑02‑17)
A75: 56 | B75: 11 | C75: Daimler Truck Code of Conduct – Guideline to doing the right thing | D75: Code of Conduct | E75: Daimler Truck Holding AG | F75: n.n. | G75: n.n. | H75: EN | I75: https://www.daimlertruck.com/fileadmin/user_upload/documents/company/compliance/Daimler-Truck-Code-of-Conduct-english.pdf | J75: 17.02.2026 | K75: 056_11_Code-of-Conduct_170226.pdf | L75: Inkludiert | N75: Dieses zentrale Compliance‑Dokument enthält ein eigenes Kapitel zu künstlicher Intelligenz. Es verpflichtet alle Beschäftigten zur verantwortungsvollen Nutzung von AI und formuliert konkrete Prinzipien wie Erklärbarkeit, Datenschutz, Sicherheit, Fairness und den Schutz von Beschäftigtenrechten. Die breite Verbindlichkeit und klare Verpflichtungen machen dieses Dokument zur wichtigsten Quelle
A76: 57 | B76: 11 | C76: Our Integrity Code (IC 0.2) | D76: AI Principles | E76: Daimler Truck Holding AG | F76: 1.4.2022 | G76: n.n. | H76: EN | I76: https://dtsa.daimlertruck.com/assets/files/king_vi/Our%20Integrity%20Code_1%20April%202022.pdf | J76: 17.02.2026 | K76: 057_11_Our Integrity Code_170226.pdf | L76: Inkludiert | N76: Der Integritätskodex gilt konzernweit und erläutert in Abschnitt 3.5.3 „Artificial intelligence“ die AI‑Grundsätze. Er betont die Umsetzung „fordernder AI‑Prinzipien“ für verantwortungsvolle Entwicklung und Nutzung von AI, einschliesslich Erklärbarkeit, Datenschutz, Sicherheit und Verlässlichkeit
A77: 58 | B77: 11 | C77: Declaration of Principles on Social Responsibility and Human Rights at Daimler Truck | D77: Other | E77: Daimler Truck Holding AG | F77: 44866 | G77: n.n. | H77: EN | I77: https://www.daimlertruck.com/fileadmin/user_upload/documents/sustainability/social/2022_12_07_Broschuere_Grundsatzerklaerung-Menschenrechte-EN.pdf | J77: 17.02.2026 | K77: 058_11_Grundsatzerklaerung-Menschenrechte_170226.pdf | L77: Nicht inkudiert | M77: Duplikat / Veraltete Version
A78: 59 | B78: 11 | C78: Business Partner Standards – Doing the Right Thing Together | D78: Code of Conduct | E78: Daimler Truck Holding AG | F78: n.n. | G78: n.n. | H78: EN | I78: https://www.daimlertruck.com/fileadmin/user_upload/dokumente/unternehmen/compliance/Business_Partner_Standards.pdf | J78: 17.02.2026 | K78: 059_11_Business_Partner_Standards_170226.pdf | L78: Nicht inkudiert | M78: Keine KI Relevanz
A79: 60 | B79: 11 | C79: Data Compliance Management System – Our commitment to data responsibility | D79: Other | E79: Daimler Truck Holding AG | F79: n.n. | G79: n.n. | H79: EN | I79: https://www.daimlertruck.com/en/company/compliance/data-compliance | J79: 17.02.2026 | K79: 060_11_Data Compliance Management System _170226.pdf | L79: Nicht inkudiert | M79: Keine KI Relevanz
A80: 61 | B80: 11 | C80: Daimler Truck Sustainability Report 2021 – Selected sections (automated driving & AI) | D80: ESG/CSR Report | E80: Daimler Truck Holding AG | F80: n.n. | G80: 2024 | H80: EN | I80: https://www.daimlertruck.com/en/sustainability/reportings | J80: 17.02.2026 | K80: 061_11_annual report-incl-esg_170226.pdf | L80: Nicht inkudiert | M80: Keine KI Relevanz
B81: 11 | D81: AI Policy | E81: Daimler Truck Holding AG | L81: Nicht gefunden | N81: No public AI policy or ethics found (as of 2026‑02‑17)
B82: 11 | D82: Responsible AI / Ethics | E82: Daimler Truck Holding AG | L82: Nicht gefunden | N82: No public AI policy or ethics found (as of 2026‑02‑17)
A83: 62 | B83: 12 | C83: Deutsche Bank Group Supplier Code of Conduct | D83: Code of Conduct | E83: Deutsche Bank AG | F83: 45778 | G83: n.n. | H83: EN | I83: https://vendor-portal.db.com/Files/Documents1/SupplierCodeofConductMay2025.pdf | J83: 17.02.2026 | K83: 062_12_SupplierCodeofConduct_170226.pdf | L83: Inkludiert | N83: Includes Responsible AI / AI Principles
A84: 63 | B84: 12 | C84: Deutsche Bank Code of Conduct – Our duty for a long‑term success | D84: Code of Conduct | E84: Deutsche Bank AG | F84: n.n. | G84: n.n. | H84: EN | I84: https://investor-relations.db.com/files/documents/documents/code-of-business-conduct-and-ethics-for-deutsche-bank-group.pdf?language_id=1 | J84: 17.02.2026 | K84: 063_12_code-of-business-conduct-and-ethics-_170226.pdf | L84: Nicht inkudiert | M84: Keine KI Relevanz
A85: 64 | B85: 12 | C85: Non‑Financial Report 2023 (Deutsche Bank Group) | D85: ESG/CSR Report | E85: Deutsche Bank AG | F85: 2023 | G85: n.n. | H85: EN | I85: https://investor-relations.db.com/files/documents/annual-reports/2024/Non-Financial-Report-2023.pdf | J85: 17.02.2026 | K85: 064_12_Non-Financial-Report_170226.pdf | L85: Inkludiert | N85: Short Section on AI Oversight Forum
A86: 65 | B86: 12 | C86: Statement on Human Rights | D86: ESG/CSR Report | E86: Deutsche Bank AG | F86: n.n. | G86: n.n. | H86: EN | I86: https://www.db.com/what-we-do/responsibility/sustainability/documents/2025-06-june/DB-Statement-on-Human-Rights-EN.pdf | J86: 17.02.2026 | K86: 065_12_Statement-on-Human-Rights_170226.pdf | L86: Nicht inkudiert | M86: Keine KI Relevanz
A87: 66 | B87: 12 | C87: Artificial Intelligence: seizing opportunities and recognizing risks | D87: Website Page | E87: Deutsche Bank AG | F87: n.n. | G87: n.n. | H87: EN | I87: https://security.db.com/knowledge-bases/artificial-intelligence | J87: 17.02.2026 | K87: 066_12_Artificial Intelligence Overview_170226.pdf | L87: Nicht inkudiert | M87: Zu Vage (keine Kriterien, Regeln) | N87: Nur technische Erklärung, was KI eigentlich ist
A88: 67 | B88: 12 | C88: How Artificial Intelligence is changing banking | D88: Website Page | E88: Deutsche Bank AG | F88: n.n. | G88: n.n. | H88: EN | I88: https://www.db.com/what-next/digital-disruption/better-than-humans/how-artificial-intelligence-is-changing-banking/index?language_id=1 | J88: 17.02.2026 | K88: 067_12_How Artificial Intelligence is changing banking_170226.pdf | L88: Nicht inkudiert | M88: Zu Vage (keine Kriterien, Regeln) | N88: Kein Bezug zur Ethik oÄ
A89: 68 | B89: 12 | C89: The responsible use of AI in financial services – From principles to practice (News article) | E89: Deutsche Bank AG | F89: 12.11.2029 | G89: n.n. | H89: EN | I89: https://www.db.com/news/detail/20191112-the-responsible-use-of-ai-in-financial-services-from-principles-to-practice?language_id=1 | J89: 17.02.2026 | K89: 068_12_The responsible use of AI in Financial services_170226.pdf | L89: Nicht inkudiert | M89: Zu Vage (keine Kriterien, Regeln)
A90: 69 | B90: 12 | C90: Unleashing the potential of AI in securities services | D90: AI Policy | E90: Deutsche Bank AG | F90: 44348 | G90: n.n. | H90: EN | I90: https://flow.db.com/files/documents/more/publications/white-papers-guides/Unleashing-the-potential-of-AI-in-securities-services.pdf | J90: 17.02.2026 | K90: 069_12_Unleashing-the-potential-of-AI-in-securities-services_170226.pdf | L90: Inkludiert
A91: 70 | B91: 12 | C91: Adopting generative AI in banking (white paper with Kodex AI) | D91: AI Policy | E91: Deutsche Bank AG | F91: n.n. | G91: n.n. | H91: EN | I91: https://flow.db.com/files/documents/more/publications/white-papers-guides/whitepaper-Adopting-Generative-AI-in-Banking.pdf | J91: 17.02.2026 | K91: 070_12_whitepaper-Adopting-Generative-AI-in-Banking_170226.pdf | L91: Inkludiert
A92: 71 | B92: 13 | C92: Response to European Commission’s White Paper on artificial intelligence | D92: Other | E92: Deutsche Börse Group | F92: 43983 | G92: n.n. | H92: EN | I92: https://www.deutsche-boerse.com/resource/blob/2095828/1649f1a7f54a924a0fb99f1b9bdd1694/data/20200610-db-response_en.pdf | J92: 17.02.2026 | K92: 071_13_db-response_170226.pdf | L92: Nicht inkudiert | M92: Duplikat / Veraltete Version
A93: 72 | B93: 13 | C93: Response to IOSCO consultation on AI in capital markets | D93: Other | E93: Deutsche Börse Group | F93: 10.04.2025 | G93: n.n. | H93: EN | I93: https://www.deutsche-boerse.com/resource/blob/4300280/dc0bd81c97cf978b924e43234f56f03d/data/20240426_DBG_response_IOSCO_AI_consultation.pdf | J93: 17.02.2026 | K93: 072_13_DBG_response_IOSCO Consultation_170226.pdf | L93: Nicht inkudiert
A94: 73 | B94: 13 | C94: Targeted consultation on artificial intelligence in the financial sector – contribution by Deutsche Börse Group | D94: Other | E94: Deutsche Börse Group | F94: 13.09.2024 | G94: n.n. | H94: EN | I94: https://www.deutsche-boerse.com/resource/blob/4344538/c7fb1c04440815b6ea29f17d9d7d62f1/data/20240912_DBG_response_EC%20Targeted%20consultation%20on%20artificial%20intelligence%20in%20the%20financial%20sector.pdf | J94: 17.02.2026 | K94: 073_13_DBG_response_EC_170226.pdf | L94: Inkludiert | N94: Die Deutsche Börse beschreibt ihren Ansatz, AI graduell und in getesteten Proof‑of‑Concept‑Phasen einzuführen, um Transparenz, Stabilität und Anlegerschutz zu gewährleisten. Sie benennt konkrete Risiken (Bias, Black‑Box‑Eigenschaften, Halluzinationen) und betont die Bedeutung solider Daten‑Governance und eines eigenen AI‑Governance‑Rahmens. Diese Aussagen liefern Hinweise für verantwortungsvolle KI‑Einführung, auch wenn das Dokument keine formale Policy darstellt.
A95: 74 | B95: 13 | C95: Market Data Policy Guidelines and FAQ – Section 10: Use of DBAG information in AI solutions (Version 2_8) | D95: Other | E95: Deutsche Börse Group | F95: 24.09.2025 | G95: V2.8 | H95: EN | I95: https://www.mds.deutsche-boerse.com/resource/blob/4028410/ee46a8181b463a0f413d0faa695c0001/data/Market%20Data%20Policy%20Guidelines%20and%20FAQ_V2_7.pdf | J95: 17.02.2026 | K95: 074_13_Market Data Policy Guidelines_170226.pdf | L95: Inkludiert | N95: ieses Regelwerk ist das einzige formale Dokument der Deutsche‑Börse‑Gruppe, das den Einsatz von KI explizit adressiert. Abschnitt 10 definiert, was als „AI Solution“ gilt (z. B. Deep‑Learning‑Modelle, generative KI und LLMs) und verpflichtet Kunden, eine passende Non‑Display‑Data‑Usage‑Lizenz zu erwerben und robuste interne Kontrollsysteme zur Nachverfolgung der Datennutzung über alle Nutzungsebenen hinweg zu unterhalten
A96: 75 | B96: 13 | C96: Code of Business Conduct | D96: Code of Conduct | E96: Deutsche Börse Group | F96: n.n. | G96: n.n. | H96: EN | I96: https://www.deutsche-boerse.com/resource/blob/45222/a244f5d7ff9f341689489b58f65a1dc0/data/code-of-business-conduct_en.pdf | J96: 17.02.2026 | K96: 075_13_code-of-business-conduct_170226.pdf | L96: Nicht inkudiert | M96: Keine KI Relevanz
A97: 76 | B97: 13 | C97: Code of Conduct for Suppliers | D97: Code of Conduct | E97: Deutsche Börse Group | F97: 12.11.2025 | G97: n.n. | H97: EN | I97: https://www.deutsche-boerse.com/resource/blob/160140/f940243aedc8611ac81e5c012777c7bd/data/code-of-coduct-suppliers_en.pdf | J97: 17.02.2026 | K97: 076_13_code-of-coduct-suppliers_170226.pdf | L97: Nicht inkudiert | M97: Keine KI Relevanz
A98: 77 | B98: 13 | C98: Human Rights Strategy Policy Statement | D98: ESG/CSR Report | E98: Deutsche Börse Group | F98: 09.12.2025 | G98: n.n. | H98: EN | I98: https://www.deutsche-boerse.com/resource/blob/3800562/9f347e74f9934e23edda9ecb28c85bc7/data/dbg-menschenrechtserklaerung_en.pdf | J98: 17.02.2026 | K98: 077_13_dbg-menschenrechtserklaerung_170226.pdf | L98: Nicht inkudiert | M98: Keine KI Relevanz
A99: 78 | B99: 13 | C99: Digital Finance – Deutsche Börse Group | D99: Website Page | E99: Deutsche Börse Group | F99: n.n. | G99: n.n. | H99: DE | I99: https://www.deutsche-boerse.com/dbg-de/ueber-uns/regulierung/regulation-df | J99: 17.02.2026 | K99: 078_13_Digital Finance_170226.pdf | L99: Nicht inkudiert | M99: Keine KI Relevanz
A100: 79 | B100: 13 | C100: Press release: More than two-thirds of investment managers use AI | D100: Press Release | E100: Deutsche Börse Group | F100: 19.01.2026 | G100: n.n. | H100: EN | I100: https://www.deutsche-boerse.com/dbg-en/media/news-stories/press-releases/More-than-Two-thirds-of-Investment-Managers-Prominently-Using-AI-to-Support-Front-Office-SimCorp-Study-Reveals-4910704 | J100: 17.02.2026 | K100: 079_13_SimCorp Study_170226.pdf | L100: Nicht inkudiert | M100: PR ohne normative Substanz
...

Sheet 02_Values_Codebook
A1: value_id | B1: value_name | C1: definition_short | D1: include_rules | E1: exclude_rules | F1: synonyms_terms | G1: example_phrases | H1: notes_boundary_cases
A2: VAL_01 | B2: Human Agency & Oversight | C2: Menschen behalten Kontrolle/Überwachung über KI | D2: Wenn menschliche Kontrolle/Override/Review explizit gefordert | E2: Reine Floskel „human-centered“ ohne Mechanik | F2: human oversight; human-in-the-loop; human control; override; review | G2: human review; override; escalation to humans | H2: Unterscheide Wert vs Governance-Kriterium 'Eskalationswege'
A3: VAL_02 | B3: Accountability & Responsibility | C3: Zuständigkeit/Verantwortung für KI-Entscheidungen/Outcomes | D3: Wenn Verantwortliche Rollen/Verantwortungsprinzip genannt | E3: Reines „we take responsibility“ ohne Bezug zu KI | F3: responsibility; accountability; ownership; governance | G3: clear accountability; responsible for AI | H3: Kann mit GOV_01 (Zuständigkeiten) kollidieren – hier nur als Wert codieren
A4: VAL_03 | B4: Transparency | C4: Nachvollziehbarkeit über Einsatz/Zweck/Entscheidungslogik | D4: Wenn Transparenzpflichten oder Offenlegung zu KI erwähnt | E4: Transparenz nur im Sinne von „Kommunikation“ ohne KI-Bezug | F4: transparency; disclosure; openness | G4: transparent use of AI; disclose AI involvement | H4: Abgrenzen zu Explainability (VAL_04)
A5: VAL_04 | B5: Explainability | C5: Erklärbarkeit von KI-Entscheidungen/Outputs | D5: Wenn Erklärbarkeit/Interpretierbarkeit explizit gefordert | E5: „transparent“ ohne Erklärkomponente | F5: explainability; interpretability; explanation | G5: provide explanations; explain model outputs | H5: Technisch vs kommunikativ – beide zählen
A6: VAL_05 | B6: Fairness & Non-Discrimination | C6: Vermeidung unfairer Benachteiligung/Bias | D6: Wenn Bias/Benachteiligung/Anti-Diskriminierung bei KI genannt | E6: Allgemeine Diversity-Statements ohne KI-Bezug | F6: fairness; bias mitigation; non-discrimination; equity | G6: avoid bias; non-discriminatory outcomes | H6: Achtung: Legal Compliance ist VAL_14, nicht hier
A7: VAL_06 | B7: Privacy & Data Protection | C7: Schutz personenbezogener Daten/Datensparsamkeit | D7: Wenn Datenschutz bei KI/Training/Use erwähnt | E7: Datenschutz rein allgemein ohne KI-Kontext | F7: privacy; data protection; GDPR; data minimization | G7: privacy by design; data minimization | H7: Kann auch als Governance (Tools/Checks) auftauchen – hier Wert
A8: VAL_07 | B8: Security & Cybersecurity | C8: Schutz vor Angriffen/Manipulation/Leakage | D8: Wenn Security für KI-Systeme oder Daten betont | E8: Allgemeine IT-Security ohne KI-Kontext (Grenzfall) | F8: security; cybersecurity; adversarial; secure-by-design | G8: protect against attacks; secure systems | H8: Grenzfall: Wenn nur IT allgemein -> evtl. nicht codieren
A9: VAL_08 | B9: Safety & Harm Prevention | C9: Vermeidung von Schäden (physisch, psychisch, sozial) | D9: Wenn Risiko/Schadensvermeidung durch KI erwähnt | E9: Nur „safe“ als Marketingwort | F9: safety; harm prevention; risk reduction | G9: avoid harm; safe AI | H9: Abgrenzen zu Robustness (VAL_09)
A10: VAL_09 | B10: Technical Robustness & Reliability | C10: Zuverlässigkeit, Stabilität, Fehlerresistenz | D10: Wenn Robustheit/Genauigkeit/Testing für KI betont | E10: Reine Qualitätsfloskel ohne Bezug | F10: robustness; reliability; resilience; testing | G10: robust and reliable; tested systems | H10: Kann in GOV_03 (Tools/Checks) konkret werden
A11: VAL_10 | B11: Contestability & Redress | C11: Anfechtbarkeit, Beschwerde, Wiedergutmachung | D11: Wenn Betroffene Einspruch/Review/Redress bei KI-Entscheidungen haben | E11: Reine Customer-Service Aussagen ohne KI | F11: appeal; contest; redress; complaint | G11: right to contest; grievance mechanism | H11: Stark verwandt mit GOV_06 (Eskalation) – hier Wert
A12: VAL_11 | B12: Inclusiveness & Accessibility | C12: Einbezug/Barrierefreiheit/Teilhabe | D12: Wenn KI inklusiv/zugänglich gestaltet werden soll | E12: Allgemeine DEI ohne KI | F12: accessibility; inclusiveness; participation | G12: inclusive design; accessible AI | H12: Wenn nur HR-DEI -> eher raus
... A19: VAL_18 | B19: Human Rights | C19: Menschenrechte als Rahmen (UNGP etc.) | D19: Wenn Human Rights explizit als Leitprinzip genannt | E19: Allgemeine Werte ohne Human-Rights-Bezug | F19: human rights; dignity; UNGP | G19: respect human rights; protect dignity | H19: Nicht jedes Doc wird das haben – ok

Sheet 03_Values_Coding
A1: company_id | B1: doc_id | C1: value_id | D1: value_present | E1: binding_level | F1: binding_justification | G1: evidence_quote | H1: evidence_location | I1: coder_confidence | J1: notes | K1: value_points
K2: =Tabelle5[[#This Row],[value_present]]*Tabelle5[[#This Row],[binding_level]] -> 0
K3: =Tabelle5[[#This Row],[value_present]]*Tabelle5[[#This Row],[binding_level]] -> 0
K4: =Tabelle5[[#This Row],[value_present]]*Tabelle5[[#This Row],[binding_level]] -> 0
K5: =Tabelle5[[#This Row],[value_present]]*Tabelle5[[#This Row],[binding_level]] -> 0
K6: =Tabelle5[[#This Row],[value_present]]*Tabelle5[[#This Row],[binding_level]] -> 0
K7: =Tabelle5[[#This Row],[value_present]]*Tabelle5[[#This Row],[binding_level]] -> 0
K8: =Tabelle5[[#This Row],[value_present]]*Tabelle5[[#This Row],[binding_level]] -> 0
K9: =Tabelle5[[#This Row],[value_present]]*Tabelle5[[#This Row],[binding_level]] -> 0
K10: =Tabelle5[[#This Row],[value_present]]*Tabelle5[[#This Row],[binding_level]] -> 0
K11: =Tabelle5[[#This Row],[value_present]]*Tabelle5[[#This Row],[binding_level]] -> 0
K12: =Tabelle5[[#This Row],[value_present]]*Tabelle5[[#This Row],[binding_level]] -> 0
K13: =Tabelle5[[#This Row],[value_present]]*Tabelle5[[#This Row],[binding_level]] -> 0
... K572: =Tabelle5[[#This Row],[value_present]]*Tabelle5[[#This Row],[binding_level]] -> 0

Sheet 03b_Values_Company_Level
A1: company_id | B1: value_id | C1: value_present_company | D1: binding_level_company | E1: value_points_company | F1: doc_id_strongest | G1: evidence_location_strongest
C2: =IF(Tabelle18[[#This Row],[binding_level_company]]>=1,1,0) -> 0 | D2: =_xlfn.MAXIFS(Tabelle5[[#This Row],[binding_level]], Tabelle5[[#This Row],[company_id]],Tabelle18[[#This Row],[company_id]], Tabelle5[[#This Row],[value_id]], Tabelle18[[#This Row],[value_id]], Tabelle5[[#This Row],[value_present]],"1") -> 0 | E2: =_xlfn.MAXIFS(Tabelle5[[#This Row],[value_points]], Tabelle5[[#This Row],[company_id]],Tabelle18[[#This Row],[company_id]], Tabelle5[[#This Row],[value_id]], Tabelle18[[#This Row],[value_id]], Tabelle5[[#This Row],[value_present]],"1") -> 0
C3: =IF(Tabelle18[[#This Row],[binding_level_company]]>=1,1,0) -> 0 | D3: =_xlfn.MAXIFS(Tabelle5[[#This Row],[binding_level]], Tabelle5[[#This Row],[company_id]],Tabelle18[[#This Row],[company_id]], Tabelle5[[#This Row],[value_id]], Tabelle18[[#This Row],[value_id]], Tabelle5[[#This Row],[value_present]],"1") -> 0 | E3: =_xlfn.MAXIFS(Tabelle5[[#This Row],[value_points]], Tabelle5[[#This Row],[company_id]],Tabelle18[[#This Row],[company_id]], Tabelle5[[#This Row],[value_id]], Tabelle18[[#This Row],[value_id]], Tabelle5[[#This Row],[value_present]],"1") -> 0
C4: =IF(Tabelle18[[#This Row],[binding_level_company]]>=1,1,0) -> 0 | D4: =_xlfn.MAXIFS(Tabelle5[[#This Row],[binding_level]], Tabelle5[[#This Row],[company_id]],Tabelle18[[#This Row],[company_id]], Tabelle5[[#This Row],[value_id]], Tabelle18[[#This Row],[value_id]], Tabelle5[[#This Row],[value_present]],"1") -> 0 | E4: =_xlfn.MAXIFS(Tabelle5[[#This Row],[value_points]], Tabelle5[[#This Row],[company_id]],Tabelle18[[#This Row],[company_id]], Tabelle5[[#This Row],[value_id]], Tabelle18[[#This Row],[value_id]], Tabelle5[[#This Row],[value_present]],"1") -> 0
C5: =IF(Tabelle18[[#This Row],[binding_level_company]]>=1,1,0) -> 0 | D5: =_xlfn.MAXIFS(Tabelle5[[#This Row],[binding_level]], Tabelle5[[#This Row],[company_id]],Tabelle18[[#This Row],[company_id]], Tabelle5[[#This Row],[value_id]], Tabelle18[[#This Row],[value_id]], Tabelle5[[#This Row],[value_present]],"1") -> 0 | E5: =_xlfn.MAXIFS(Tabelle5[[#This Row],[value_points]], Tabelle5[[#This Row],[company_id]],Tabelle18[[#This Row],[company_id]], Tabelle5[[#This Row],[value_id]], Tabelle18[[#This Row],[value_id]], Tabelle5[[#This Row],[value_present]],"1") -> 0
C6: =IF(Tabelle18[[#This Row],[binding_level_company]]>=1,1,0) -> 0 | D6: =_xlfn.MAXIFS(Tabelle5[[#This Row],[binding_level]], Tabelle5[[#This Row],[company_id]],Tabelle18[[#This Row],[company_id]], Tabelle5[[#This Row],[value_id]], Tabelle18[[#This Row],[value_id]], Tabelle5[[#This Row],[value_present]],"1") -> 0 | E6: =_xlfn.MAXIFS(Tabelle5[[#This Row],[value_points]], Tabelle5[[#This Row],[company_id]],Tabelle18[[#This Row],[company_id]], Tabelle5[[#This Row],[value_id]], Tabelle18[[#This Row],[value_id]], Tabelle5[[#This Row],[value_present]],"1") -> 0
C7: =IF(Tabelle18[[#This Row],[binding_level_company]]>=1,1,0) -> 0 | D7: =_xlfn.MAXIFS(Tabelle5[[#This Row],[binding_level]], Tabelle5[[#This Row],[company_id]],Tabelle18[[#This Row],[company_id]], Tabelle5[[#This Row],[value_id]], Tabelle18[[#This Row],[value_id]], Tabelle5[[#This Row],[value_present]],"1") -> 0 | E7: =_xlfn.MAXIFS(Tabelle5[[#This Row],[value_points]], Tabelle5[[#This Row],[company_id]],Tabelle18[[#This Row],[company_id]], Tabelle5[[#This Row],[value_id]], Tabelle18[[#This Row],[value_id]], Tabelle5[[#This Row],[value_present]],"1") -> 0
C8: =IF(Tabelle18[[#This Row],[binding_level_company]]>=1,1,0) -> 0 | D8: =_xlfn.MAXIFS(Tabelle5[[#This Row],[binding_level]], Tabelle5[[#This Row],[company_id]],Tabelle18[[#This Row],[company_id]], Tabelle5[[#This Row],[value_id]], Tabelle18[[#This Row],[value_id]], Tabelle5[[#This Row],[value_present]],"1") -> 0 | E8: =_xlfn.MAXIFS(Tabelle5[[#This Row],[value_points]], Tabelle5[[#This Row],[company_id]],Tabelle18[[#This Row],[company_id]], Tabelle5[[#This Row],[value_id]], Tabelle18[[#This Row],[value_id]], Tabelle5[[#This Row],[value_present]],"1") -> 0
C9: =IF(Tabelle18[[#This Row],[binding_level_company]]>=1,1,0) -> 0 | D9: =_xlfn.MAXIFS(Tabelle5[[#This Row],[binding_level]], Tabelle5[[#This Row],[company_id]],Tabelle18[[#This Row],[company_id]], Tabelle5[[#This Row],[value_id]], Tabelle18[[#This Row],[value_id]], Tabelle5[[#This Row],[value_present]],"1") -> 0 | E9: =_xlfn.MAXIFS(Tabelle5[[#This Row],[value_points]], Tabelle5[[#This Row],[company_id]],Tabelle18[[#This Row],[company_id]], Tabelle5[[#This Row],[value_id]], Tabelle18[[#This Row],[value_id]], Tabelle5[[#This Row],[value_present]],"1") -> 0
C10: =IF(Tabelle18[[#This Row],[binding_level_company]]>=1,1,0) -> 0 | D10: =_xlfn.MAXIFS(Tabelle5[[#This Row],[binding_level]], Tabelle5[[#This Row],[company_id]],Tabelle18[[#This Row],[company_id]], Tabelle5[[#This Row],[value_id]], Tabelle18[[#This Row],[value_id]], Tabelle5[[#This Row],[value_present]],"1") -> 0 | E10: =_xlfn.MAXIFS(Tabelle5[[#This Row],[value_points]], Tabelle5[[#This Row],[company_id]],Tabelle18[[#This Row],[company_id]], Tabelle5[[#This Row],[value_id]], Tabelle18[[#This Row],[value_id]], Tabelle5[[#This Row],[value_present]],"1") -> 0
C11: =IF(Tabelle18[[#This Row],[binding_level_company]]>=1,1,0) -> 0 | D11: =_xlfn.MAXIFS(Tabelle5[[#This Row],[binding_level]], Tabelle5[[#This Row],[company_id]],Tabelle18[[#This Row],[company_id]], Tabelle5[[#This Row],[value_id]], Tabelle18[[#This Row],[value_id]], Tabelle5[[#This Row],[value_present]],"1") -> 0 | E11: =_xlfn.MAXIFS(Tabelle5[[#This Row],[value_points]], Tabelle5[[#This Row],[company_id]],Tabelle18[[#This Row],[company_id]], Tabelle5[[#This Row],[value_id]], Tabelle18[[#This Row],[value_id]], Tabelle5[[#This Row],[value_present]],"1") -> 0
C12: =IF(Tabelle18[[#This Row],[binding_level_company]]>=1,1,0) -> 0 | D12: =_xlfn.MAXIFS(Tabelle5[[#This Row],[binding_level]], Tabelle5[[#This Row],[company_id]],Tabelle18[[#This Row],[company_id]], Tabelle5[[#This Row],[value_id]], Tabelle18[[#This Row],[value_id]], Tabelle5[[#This Row],[value_present]],"1") -> 0 | E12: =_xlfn.MAXIFS(Tabelle5[[#This Row],[value_points]], Tabelle5[[#This Row],[company_id]],Tabelle18[[#This Row],[company_id]], Tabelle5[[#This Row],[value_id]], Tabelle18[[#This Row],[value_id]], Tabelle5[[#This Row],[value_present]],"1") -> 0
C13: =IF(Tabelle18[[#This Row],[binding_level_company]]>=1,1,0) -> 0 | D13: =_xlfn.MAXIFS(Tabelle5[[#This Row],[binding_level]], Tabelle5[[#This Row],[company_id]],Tabelle18[[#This Row],[company_id]], Tabelle5[[#This Row],[value_id]], Tabelle18[[#This Row],[value_id]], Tabelle5[[#This Row],[value_present]],"1") -> 0 | E13: =_xlfn.MAXIFS(Tabelle5[[#This Row],[value_points]], Tabelle5[[#This Row],[company_id]],Tabelle18[[#This Row],[company_id]], Tabelle5[[#This Row],[value_id]], Tabelle18[[#This Row],[value_id]], Tabelle5[[#This Row],[value_present]],"1") -> 0
... C41: =IF(Tabelle18[[#This Row],[binding_level_company]]>=1,1,0) -> 0 | D41: =_xlfn.MAXIFS(Tabelle5[[#This Row],[binding_level]], Tabelle5[[#This Row],[company_id]],Tabelle18[[#This Row],[company_id]], Tabelle5[[#This Row],[value_id]], Tabelle18[[#This Row],[value_id]], Tabelle5[[#This Row],[value_present]],"1") -> 0 | E41: =_xlfn.MAXIFS(Tabelle5[[#This Row],[value_points]], Tabelle5[[#This Row],[company_id]],Tabelle18[[#This Row],[company_id]], Tabelle5[[#This Row],[value_id]], Tabelle18[[#This Row],[value_id]], Tabelle5[[#This Row],[value_present]],"1") -> 0

Sheet 04_Governance_Codebook
A1: gov_crit_id | B1: criterion_name | C1: score_0_definition | D1: score_1_definition | E1: score_2_definition | F1: score_3_definition | G1: evidence_minimum | H1: typical_evidence_terms
A2: GOV_01 | B2: Zuständigkeiten | C2: Keine Rollen/Zuständigkeiten genannt | D2: Rollen/Verantwortung grob benannt (z.B. 'Ethics committee') | E2: Konkrete Rollen+Aufgaben beschrieben (Owner, Approver, RACI) | F2: Implementiert: Verantwortlichkeiten mit Reporting/Regelterminen/Belegen | G2: Rollentitel + klarer Bezug zu KI/AI-Governance | H2: owner; accountability; committee; board; RACI
A3: GOV_02 | B3: Prozesse | C3: Kein Prozess erwähnt | D3: Prozessabsicht erwähnt (z.B. 'we review AI') | E3: Prozessschritte beschrieben (Lifecycle, Gateways, Freigaben) | F3: Implementiert: Prozess mit Nachweisen (KPIs, regelmäßige Reviews, Prozessdokumente) | G3: Mind. ein Prozessschritt + Trigger + Verantwortliche | H3: AI lifecycle; approval; review; gating; SOP
A4: GOV_03 | B4: Tools/Checks | C4: Keine Checks/Tools | D4: Checks allgemein erwähnt (z.B. 'risk assessment') | E4: Konkrete Tools/Checks benannt (Bias test, model cards, DPIA) | F4: Implementiert: Tooling im Betrieb + Pflicht/Protokoll + Ergebnisse berichtet | G4: Name des Checks/Tools + wann eingesetzt | H4: bias test; model card; DPIA; validation; monitoring
A5: GOV_04 | B5: Audits | C5: Keine Audits | D5: Audit/Assessment erwähnt ohne Details | E5: Audit-Mechanik beschrieben (intern/extern, Frequenz) | F5: Implementiert: Auditberichte/KPIs/Review-Zyklen nachweisbar | G5: Auditart + Frequenz oder Verantwortliche | H5: audit; assurance; internal control; external review
A6: GOV_05 | B6: Schulungen | C6: Keine Trainings | D6: Training angekündigt/empfohlen | E6: Trainingsprogramm beschrieben (Zielgruppe, Inhalte, Pflichtgrad) | F6: Implementiert: Pflichttrainings + Nachweis (Completion, LMS, KPIs) | G6: Mind. Zielgruppe + Pflicht/Regelmäßigkeit | H6: training; awareness; mandatory; LMS; certification
A7: GOV_06 | B7: Eskalationswege | C7: Keine Eskalation | D7: Kontakt/Ansprechpartner genannt | E7: Konkreter Eskalationsprozess beschrieben (Stufen, Fristen) | F7: Implementiert: geübter Prozess/Case-Handling/Reporting | G7: Stufenlogik oder Mechanik (Ticket, Hotline, Committee) | H7: escalation; grievance; hotline; incident; ticket
A8: GOV_07 | B8: Reporting | C8: Kein Reporting | D8: Reporting-Absicht erwähnt | E8: Reporting-Struktur beschrieben (Was, an wen, wie oft) | F8: Implementiert: regelmäßige Reports/KPIs öffentlich oder intern belegt | G8: KPI/Reportgegenstand + Empfänger + Frequenz | H8: reporting; KPI; dashboard; disclosure; metrics

Sheet 05_Governance_Coding
A1: company_id | B1: gov_crit_id | C1: doc_id_primary_evidence | D1: score_0_3 | E1: evidence_quote | F1: evidence_location | G1: why_not_higher | H1: coder_confidence | I1: notes

Sheet 06_Derived_Indices
A1: company_id | B1: sector_cluster | C1: values_raw_points | D1: values_max_points | E1: convergence_index_0_1 | F1: gov_points_sum | G1: gov_index_0_100
C2: =SUMIF(Tabelle18[[#This Row],[value_points_company]],Tabelle5[[#This Row],[company_id]],Tabelle8[[#This Row],[company_id]]) -> 0 | D2: =(COUNTA('02_Values_Codebook'!A:A)-1)*3 -> 54 | E2: =Tabelle8[[#This Row],[values_raw_points]]/Tabelle8[[#This Row],[values_max_points]] -> 0 | F2: =SUMIF(Tabelle7[[#This Row],[score_0_3]],Tabelle7[[#This Row],[company_id]],Tabelle8[[#This Row],[company_id]]) -> 0 | G2: =(Tabelle8[[#This Row],[gov_points_sum]]/21)*100 -> 0
C3: =SUMIF(Tabelle18[[#This Row],[value_points_company]],Tabelle5[[#This Row],[company_id]],Tabelle8[[#This Row],[company_id]]) -> 0 | D3: =(COUNTA('02_Values_Codebook'!A:A)-1)*3 -> 54 | E3: =Tabelle8[[#This Row],[values_raw_points]]/Tabelle8[[#This Row],[values_max_points]] -> 0 | F3: =SUMIF(Tabelle7[[#This Row],[score_0_3]],Tabelle7[[#This Row],[company_id]],Tabelle8[[#This Row],[company_id]]) -> 0 | G3: =(Tabelle8[[#This Row],[gov_points_sum]]/21)*100 -> 0
C4: =SUMIF(Tabelle18[[#This Row],[value_points_company]],Tabelle5[[#This Row],[company_id]],Tabelle8[[#This Row],[company_id]]) -> 0 | D4: =(COUNTA('02_Values_Codebook'!A:A)-1)*3 -> 54 | E4: =Tabelle8[[#This Row],[values_raw_points]]/Tabelle8[[#This Row],[values_max_points]] -> 0 | F4: =SUMIF(Tabelle7[[#This Row],[score_0_3]],Tabelle7[[#This Row],[company_id]],Tabelle8[[#This Row],[company_id]]) -> 0 | G4: =(Tabelle8[[#This Row],[gov_points_sum]]/21)*100 -> 0
C5: =SUMIF(Tabelle18[[#This Row],[value_points_company]],Tabelle5[[#This Row],[company_id]],Tabelle8[[#This Row],[company_id]]) -> 0 | D5: =(COUNTA('02_Values_Codebook'!A:A)-1)*3 -> 54 | E5: =Tabelle8[[#This Row],[values_raw_points]]/Tabelle8[[#This Row],[values_max_points]] -> 0 | F5: =SUMIF(Tabelle7[[#This Row],[score_0_3]],Tabelle7[[#This Row],[company_id]],Tabelle8[[#This Row],[company_id]]) -> 0 | G5: =(Tabelle8[[#This Row],[gov_points_sum]]/21)*100 -> 0
C6: =SUMIF(Tabelle18[[#This Row],[value_points_company]],Tabelle5[[#This Row],[company_id]],Tabelle8[[#This Row],[company_id]]) -> 0 | D6: =(COUNTA('02_Values_Codebook'!A:A)-1)*3 -> 54 | E6: =Tabelle8[[#This Row],[values_raw_points]]/Tabelle8[[#This Row],[values_max_points]] -> 0 | F6: =SUMIF(Tabelle7[[#This Row],[score_0_3]],Tabelle7[[#This Row],[company_id]],Tabelle8[[#This Row],[company_id]]) -> 0 | G6: =(Tabelle8[[#This Row],[gov_points_sum]]/21)*100 -> 0
C7: =SUMIF(Tabelle18[[#This Row],[value_points_company]],Tabelle5[[#This Row],[company_id]],Tabelle8[[#This Row],[company_id]]) -> 0 | D7: =(COUNTA('02_Values_Codebook'!A:A)-1)*3 -> 54 | E7: =Tabelle8[[#This Row],[values_raw_points]]/Tabelle8[[#This Row],[values_max_points]] -> 0 | F7: =SUMIF(Tabelle7[[#This Row],[score_0_3]],Tabelle7[[#This Row],[company_id]],Tabelle8[[#This Row],[company_id]]) -> 0 | G7: =(Tabelle8[[#This Row],[gov_points_sum]]/21)*100 -> 0
C8: =SUMIF(Tabelle18[[#This Row],[value_points_company]],Tabelle5[[#This Row],[company_id]],Tabelle8[[#This Row],[company_id]]) -> 0 | D8: =(COUNTA('02_Values_Codebook'!A:A)-1)*3 -> 54 | E8: =Tabelle8[[#This Row],[values_raw_points]]/Tabelle8[[#This Row],[values_max_points]] -> 0 | F8: =SUMIF(Tabelle7[[#This Row],[score_0_3]],Tabelle7[[#This Row],[company_id]],Tabelle8[[#This Row],[company_id]]) -> 0 | G8: =(Tabelle8[[#This Row],[gov_points_sum]]/21)*100 -> 0
C9: =SUMIF(Tabelle18[[#This Row],[value_points_company]],Tabelle5[[#This Row],[company_id]],Tabelle8[[#This Row],[company_id]]) -> 0 | D9: =(COUNTA('02_Values_Codebook'!A:A)-1)*3 -> 54 | E9: =Tabelle8[[#This Row],[values_raw_points]]/Tabelle8[[#This Row],[values_max_points]] -> 0 | F9: =SUMIF(Tabelle7[[#This Row],[score_0_3]],Tabelle7[[#This Row],[company_id]],Tabelle8[[#This Row],[company_id]]) -> 0 | G9: =(Tabelle8[[#This Row],[gov_points_sum]]/21)*100 -> 0
C10: =SUMIF(Tabelle18[[#This Row],[value_points_company]],Tabelle5[[#This Row],[company_id]],Tabelle8[[#This Row],[company_id]]) -> 0 | D10: =(COUNTA('02_Values_Codebook'!A:A)-1)*3 -> 54 | E10: =Tabelle8[[#This Row],[values_raw_points]]/Tabelle8[[#This Row],[values_max_points]] -> 0 | F10: =SUMIF(Tabelle7[[#This Row],[score_0_3]],Tabelle7[[#This Row],[company_id]],Tabelle8[[#This Row],[company_id]]) -> 0 | G10: =(Tabelle8[[#This Row],[gov_points_sum]]/21)*100 -> 0
C11: =SUMIF(Tabelle18[[#This Row],[value_points_company]],Tabelle5[[#This Row],[company_id]],Tabelle8[[#This Row],[company_id]]) -> 0 | D11: =(COUNTA('02_Values_Codebook'!A:A)-1)*3 -> 54 | E11: =Tabelle8[[#This Row],[values_raw_points]]/Tabelle8[[#This Row],[values_max_points]] -> 0 | F11: =SUMIF(Tabelle7[[#This Row],[score_0_3]],Tabelle7[[#This Row],[company_id]],Tabelle8[[#This Row],[company_id]]) -> 0 | G11: =(Tabelle8[[#This Row],[gov_points_sum]]/21)*100 -> 0
C12: =SUMIF(Tabelle18[[#This Row],[value_points_company]],Tabelle5[[#This Row],[company_id]],Tabelle8[[#This Row],[company_id]]) -> 0 | D12: =(COUNTA('02_Values_Codebook'!A:A)-1)*3 -> 54 | E12: =Tabelle8[[#This Row],[values_raw_points]]/Tabelle8[[#This Row],[values_max_points]] -> 0 | F12: =SUMIF(Tabelle7[[#This Row],[score_0_3]],Tabelle7[[#This Row],[company_id]],Tabelle8[[#This Row],[company_id]]) -> 0 | G12: =(Tabelle8[[#This Row],[gov_points_sum]]/21)*100 -> 0
C13: =SUMIF(Tabelle18[[#This Row],[value_points_company]],Tabelle5[[#This Row],[company_id]],Tabelle8[[#This Row],[company_id]]) -> 0 | D13: =(COUNTA('02_Values_Codebook'!A:A)-1)*3 -> 54 | E13: =Tabelle8[[#This Row],[values_raw_points]]/Tabelle8[[#This Row],[values_max_points]] -> 0 | F13: =SUMIF(Tabelle7[[#This Row],[score_0_3]],Tabelle7[[#This Row],[company_id]],Tabelle8[[#This Row],[company_id]]) -> 0 | G13: =(Tabelle8[[#This Row],[gov_points_sum]]/21)*100 -> 0
... C41: =SUMIF(Tabelle18[[#This Row],[value_points_company]],Tabelle5[[#This Row],[company_id]],Tabelle8[[#This Row],[company_id]]) -> 0 | D41: =(COUNTA('02_Values_Codebook'!A:A)-1)*3 -> 54 | E41: =Tabelle8[[#This Row],[values_raw_points]]/Tabelle8[[#This Row],[values_max_points]] -> 0 | F41: =SUMIF(Tabelle7[[#This Row],[score_0_3]],Tabelle7[[#This Row],[company_id]],Tabelle8[[#This Row],[company_id]]) -> 0 | G41: =(Tabelle8[[#This Row],[gov_points_sum]]/21)*100 -> 0

Sheet 07_Boundary_Cases
A1: case_id | B1: date | C1: company_id | D1: doc_id | E1: dimension(values/governance) | F1: value_id_or_gov_crit_id | G1: problem_description | H1: decision | I1: rule_added_to_codebook | J1: codebook_version

Sheet 08_Codebook_Changelog
A1: codebook_version | B1: date | C1: change_type(add/modify/remove) | D1: item_id(value_id/gov_crit_id) | E1: what_changed | F1: why_changed | G1: impact_on_previous_coding(recode_needed yes/no)
A2: V0 | B2: 04.01.2026 | C2: Initial Setup

Sheet 09_Coding_Memos
A1: company_id | B1: overall_notes | C1: key_documents_used | D1: areas_of_uncertainty | E1: follow_up_needed

Sheet 99_Lookups
A1: Sektoren | C1: Dokumententyp | E1: Sprache | G1: Inkludierungsstatus | I1: Ausschlussgrund | K1: Kodierungskonfidenz | M1: Bindigkeitsniveau | O1: Value_present | Q1: Score_0_3
A2: Industrie | C2: AI Principles | E2: DE | G2: Inkludiert | I2: PR ohne normative Substanz | K2: Hoch | M2: 1 | O2: 0 | Q2: 0
A3: Finance | C3: AI Policy | E3: EN | G3: Nicht inkudiert | I3: Keine KI Relevanz | K3: Mittel | M3: 2 | O3: 1 | Q3: 1
A4: Tech | C4: Responsible AI / Ethics | E4: DE/EN | G4: Nicht gefunden | I4: Duplikat / Veraltete Version | K4: Niedrig | M4: 3 | Q4: 2
A5: Health | C5: Code of Conduct | E5: Andere | I5: Paywalled / kein Zugriff | Q5: 3
A6: Consumer | C6: ESG/CSR Report | I6: Zu Vage (keine Kriterien, Regeln)
A7: Utilities | C7: Sustainability Report | I7: Andere
A8: Materials/Chemicals | C8: Annual Report
A9: Other/Hybrid | C9: Website Page
C10: Press Release
C11: Other
